{
  "type": "Feature",
  "properties": {
    "gn:admin1_code":"16.0",
    "gn:asciiname":"Donje Mrke",
    "gn:country_code":"ME",
    "gn:dem":88,
    "gn:feature_class":"P",
    "gn:feature_code":"PPL",
    "gn:name":"Donje Mrke",
    "gn:population":0,
    "gn:timezone":"Europe/Podgorica",
    "iso:country":"ME",
    "name:und_x_variant":[
        "Mrke",
        "Donje Mrke"
    ],
    "wof:name":"Donje Mrke",
    "wof:placetype":"locality"
},
  "geometry": {"coordinates":[19.33556,42.5125],"type":"Point"}
}