{
  "type": "Feature",
  "properties": {
    "gn:admin1_code":"4.0",
    "gn:asciiname":"Slatina",
    "gn:country_code":"ME",
    "gn:dem":680,
    "gn:feature_class":"P",
    "gn:feature_code":"PPL",
    "gn:name":"Slatina",
    "gn:population":0,
    "gn:timezone":"Europe/Podgorica",
    "iso:country":"ME",
    "name:srp_x_preferred":[
        "Slatina"
    ],
    "wof:name":"Slatina",
    "wof:placetype":"locality"
},
  "geometry": {"coordinates":[19.84222,42.96944000000001],"type":"Point"}
}