{
  "type": "Feature",
  "properties": {
    "gn:admin1_code":"9.0",
    "gn:asciiname":"Aluga",
    "gn:country_code":"ME",
    "gn:dem":993,
    "gn:feature_class":"P",
    "gn:feature_code":"PPL",
    "gn:name":"Aluga",
    "gn:population":0,
    "gn:timezone":"Europe/Podgorica",
    "iso:country":"ME",
    "name:und_x_variant":[
        "Aluge",
        "Aluga"
    ],
    "wof:name":"Aluga",
    "wof:placetype":"locality"
},
  "geometry": {"coordinates":[19.2925,42.88167],"type":"Point"}
}