{
  "type": "Feature",
  "properties": {
    "gn:admin1_code":"6.0",
    "gn:asciiname":"Jaicevici",
    "gn:country_code":"ME",
    "gn:dem":875,
    "gn:feature_class":"P",
    "gn:feature_code":"PPL",
    "gn:name":"Jai\u0107evi\u0107i",
    "gn:population":0,
    "gn:timezone":"Europe/Podgorica",
    "iso:country":"ME",
    "name:srp_x_preferred":[
        "Jai\u0107evi\u0107i"
    ],
    "wof:name":"Jaicevici",
    "wof:placetype":"locality"
},
  "geometry": {"coordinates":[18.82722,42.42694],"type":"Point"}
}