{
  "type": "Feature",
  "properties": {
    "gn:admin1_code":"14.0",
    "gn:asciiname":"Crnobori",
    "gn:country_code":"ME",
    "gn:dem":1072,
    "gn:feature_class":"P",
    "gn:feature_code":"PPLL",
    "gn:name":"Crnobori",
    "gn:population":0,
    "gn:timezone":"Europe/Podgorica",
    "iso:country":"ME",
    "name:und_x_variant":[
        "Crnoborje",
        "Crnobori"
    ],
    "wof:name":"Crnobori",
    "wof:placetype":"locality"
},
  "geometry": {"coordinates":[19.30806,43.25417],"type":"Point"}
}