{
  "type": "Feature",
  "properties": {
    "gn:admin1_code":"9.0",
    "gn:asciiname":"Suva Gora",
    "gn:country_code":"ME",
    "gn:dem":1371,
    "gn:feature_class":"P",
    "gn:feature_code":"PPL",
    "gn:name":"Suva Gora",
    "gn:population":0,
    "gn:timezone":"Europe/Podgorica",
    "iso:country":"ME",
    "name:srp_x_preferred":[
        "Suva Gora"
    ],
    "wof:name":"Suva Gora",
    "wof:placetype":"locality"
},
  "geometry": {"coordinates":[19.63806,42.77389],"type":"Point"}
}