{
  "type": "Feature",
  "properties": {
    "gn:admin1_code":"15.0",
    "gn:asciiname":"Vucje Seliste",
    "gn:country_code":"ME",
    "gn:dem":1394,
    "gn:feature_class":"P",
    "gn:feature_code":"PPL",
    "gn:name":"Vu\u010dje Seli\u0161te",
    "gn:population":0,
    "gn:timezone":"Europe/Podgorica",
    "iso:country":"ME",
    "name:srp_x_preferred":[
        "Vu\u010dje Seli\u0161te"
    ],
    "wof:name":"Vucje Seliste",
    "wof:placetype":"locality"
},
  "geometry": {"coordinates":[18.93722,43.23444],"type":"Point"}
}