{
  "type": "Feature",
  "properties": {
    "gn:admin1_code":"6.0",
    "gn:asciiname":"Zmukici",
    "gn:country_code":"ME",
    "gn:dem":611,
    "gn:feature_class":"P",
    "gn:feature_code":"PPL",
    "gn:name":"\u017dmuki\u0107i",
    "gn:population":0,
    "gn:timezone":"Europe/Podgorica",
    "iso:country":"ME",
    "name:srp_x_preferred":[
        "\u017dmuki\u0107i"
    ],
    "wof:name":"Zmukici",
    "wof:placetype":"locality"
},
  "geometry": {"coordinates":[18.69528,42.58583],"type":"Point"}
}