{
  "type": "Feature",
  "properties": {
    "gn:admin1_code":"18.0",
    "gn:asciiname":"Suvo Polje",
    "gn:country_code":"ME",
    "gn:dem":1247,
    "gn:feature_class":"P",
    "gn:feature_code":"PPL",
    "gn:name":"Suvo Polje",
    "gn:population":0,
    "gn:timezone":"Europe/Podgorica",
    "iso:country":"ME",
    "name:srp_x_preferred":[
        "Suvo Polje"
    ],
    "wof:name":"Suvo Polje",
    "wof:placetype":"locality"
},
  "geometry": {"coordinates":[19.01667,43.00528],"type":"Point"}
}