{
  "type": "Feature",
  "properties": {
    "gn:admin1_code":"20.0",
    "gn:asciiname":"Brajse",
    "gn:country_code":"ME",
    "gn:dem":51,
    "gn:feature_class":"P",
    "gn:feature_code":"PPL",
    "gn:name":"Braj\u0161e",
    "gn:population":0,
    "gn:timezone":"Europe/Podgorica",
    "iso:country":"ME",
    "name:und_x_variant":[
        "Brai\u0161a",
        "Braj\u0161e"
    ],
    "wof:name":"Brajse",
    "wof:placetype":"locality"
},
  "geometry": {"coordinates":[19.31389,42.02333],"type":"Point"}
}