{
  "type": "Feature",
  "properties": {
    "gn:admin1_code":"14.0",
    "gn:asciiname":"Podrid",
    "gn:country_code":"ME",
    "gn:dem":895,
    "gn:feature_class":"P",
    "gn:feature_code":"PPL",
    "gn:name":"Podrid",
    "gn:population":0,
    "gn:timezone":"Europe/Podgorica",
    "iso:country":"ME",
    "name:srp_x_preferred":[
        "Podrid"
    ],
    "wof:name":"Podrid",
    "wof:placetype":"locality"
},
  "geometry": {"coordinates":[19.16417,43.42583],"type":"Point"}
}