{
  "type": "Feature",
  "properties": {
    "gn:admin1_code":"12.0",
    "gn:asciiname":"Petrovici",
    "gn:country_code":"ME",
    "gn:dem":710,
    "gn:feature_class":"P",
    "gn:feature_code":"PPLL",
    "gn:name":"Petrovi\u0107i",
    "gn:population":0,
    "gn:timezone":"Europe/Podgorica",
    "iso:country":"ME",
    "name:und_x_variant":[
        "Petrovac",
        "Petrovic",
        "Petrovi\u0107i"
    ],
    "wof:name":"Petrovici",
    "wof:placetype":"locality"
},
  "geometry": {"coordinates":[18.51611,42.74222],"type":"Point"}
}