{
  "type": "Feature",
  "properties": {
    "gn:admin1_code":"12.0",
    "gn:asciiname":"Donje Crkvice",
    "gn:country_code":"ME",
    "gn:dem":1051,
    "gn:feature_class":"P",
    "gn:feature_code":"PPLL",
    "gn:name":"Donje Crkvice",
    "gn:population":0,
    "gn:timezone":"Europe/Podgorica",
    "iso:country":"ME",
    "name:und_x_variant":[
        "Crkvice",
        "Donje Crkvice"
    ],
    "wof:name":"Donje Crkvice",
    "wof:placetype":"locality"
},
  "geometry": {"coordinates":[18.54167,42.95667],"type":"Point"}
}