{
  "type": "Feature",
  "properties": {
    "gn:admin1_code":"15.0",
    "gn:asciiname":"Zabrde",
    "gn:country_code":"ME",
    "gn:dem":1101,
    "gn:feature_class":"P",
    "gn:feature_code":"PPL",
    "gn:name":"Zabr\u0111e",
    "gn:population":0,
    "gn:timezone":"Europe/Podgorica",
    "iso:country":"ME",
    "name:srp_x_preferred":[
        "Zabr\u0111e"
    ],
    "wof:name":"Zabrde",
    "wof:placetype":"locality"
},
  "geometry": {"coordinates":[18.86528,43.02806],"type":"Point"}
}