{
  "type": "Feature",
  "properties": {
    "gn:admin1_code":"21.0",
    "gn:asciiname":"Okruglica",
    "gn:country_code":"ME",
    "gn:dem":1607,
    "gn:feature_class":"P",
    "gn:feature_code":"PPL",
    "gn:name":"Okruglica",
    "gn:population":0,
    "gn:timezone":"Europe/Podgorica",
    "iso:country":"ME",
    "name:bos_x_preferred":[
        "Okruglica"
    ],
    "name:ceb_x_preferred":[
        "Okruglica"
    ],
    "name:fra_x_preferred":[
        "Okruglica"
    ],
    "name:hrv_x_preferred":[
        "Okruglica"
    ],
    "name:slv_x_preferred":[
        "Okruglica"
    ],
    "name:srp_x_preferred":[
        "Okruglica"
    ],
    "name:srp_x_variant":[
        "\u041e\u043a\u0440\u0443\u0433\u043b\u0438\u0446\u0430"
    ],
    "name:swe_x_preferred":[
        "Okruglica"
    ],
    "wof:name":"Okruglica",
    "wof:placetype":"locality"
},
  "geometry": {"coordinates":[19.26611,43.02639],"type":"Point"}
}