{
  "type": "Feature",
  "properties": {
    "gn:admin1_code":"21.0",
    "gn:asciiname":"Okruglica",
    "gn:country_code":"ME",
    "gn:dem":1607,
    "gn:feature_class":"P",
    "gn:feature_code":"PPL",
    "gn:name":"Okruglica",
    "gn:population":0,
    "gn:timezone":"Europe/Podgorica",
    "iso:country":"ME",
    "name:srp_x_preferred":[
        "Okruglica"
    ],
    "wof:name":"Okruglica",
    "wof:placetype":"locality"
},
  "geometry": {"coordinates":[19.26611,43.02639],"type":"Point"}
}