{
  "type": "Feature",
  "properties": {
    "gn:admin1_code":"9.0",
    "gn:asciiname":"Vrtovi",
    "gn:country_code":"ME",
    "gn:dem":924,
    "gn:feature_class":"P",
    "gn:feature_code":"PPL",
    "gn:name":"Vrtovi",
    "gn:population":0,
    "gn:timezone":"Europe/Podgorica",
    "iso:country":"ME",
    "name:srp_x_preferred":[
        "Vrtovi"
    ],
    "wof:name":"Vrtovi",
    "wof:placetype":"locality"
},
  "geometry": {"coordinates":[19.32167,42.71861],"type":"Point"}
}