{
  "type": "Feature",
  "properties": {
    "gn:admin1_code":"12.0",
    "gn:asciiname":"Razdolje",
    "gn:country_code":"ME",
    "gn:dem":930,
    "gn:feature_class":"P",
    "gn:feature_code":"PPL",
    "gn:name":"Razdolje",
    "gn:population":0,
    "gn:timezone":"Europe/Podgorica",
    "iso:country":"ME",
    "name:srp_x_preferred":[
        "Razdolje"
    ],
    "wof:name":"Razdolje",
    "wof:placetype":"locality"
},
  "geometry": {"coordinates":[18.76917000000001,42.7175],"type":"Point"}
}