{
  "type": "Feature",
  "properties": {
    "gn:admin1_code":"4.0",
    "gn:asciiname":"Zurnovice",
    "gn:country_code":"ME",
    "gn:dem":842,
    "gn:feature_class":"P",
    "gn:feature_code":"PPL",
    "gn:name":"Zurnovice",
    "gn:population":0,
    "gn:timezone":"Europe/Podgorica",
    "iso:country":"ME",
    "name:srp_x_preferred":[
        "Zurnovice"
    ],
    "wof:name":"Zurnovice",
    "wof:placetype":"locality"
},
  "geometry": {"coordinates":[19.60083,43.02472],"type":"Point"}
}