{
  "type": "Feature",
  "properties": {
    "gn:admin1_code":"5.0",
    "gn:asciiname":"Podbabac",
    "gn:country":"ME",
    "gn:country_code":"ME",
    "gn:dem":174,
    "gn:fcode":"PPL",
    "gn:feature_class":"P",
    "gn:feature_code":"PPL",
    "gn:name":"Podbabac",
    "gn:population":5,
    "gn:timezone":"Europe/Podgorica",
    "iso:country":"ME",
    "name:srp_x_preferred":[
        "Podbabac"
    ],
    "qs:name":"Podbabac",
    "qs:photos_9r":0,
    "qs:photos_sr":0,
    "qs:pop_sr":"1",
    "wof:name":"Podbabac",
    "wof:placetype":"locality",
    "wof:population":5
},
  "geometry": {"coordinates":[18.89111,42.28083],"type":"Point"}
}