{
  "type": "Feature",
  "properties": {
    "gn:country":"ME",
    "gn:fcode":"PPL",
    "gn:pop":5,
    "iso:country":"ME",
    "name:srp_x_preferred":[
        "Podbabac"
    ],
    "qs:name":"Podbabac",
    "qs:photos_9r":0,
    "qs:photos_sr":0,
    "qs:pop_sr":"1",
    "wof:name":"Podbabac",
    "wof:placetype":"locality",
    "wof:population":5
},
  "geometry": {"coordinates":[18.89111,42.28083],"type":"Point"}
}