{
  "type": "Feature",
  "properties": {
    "gn:admin1_code":"6.0",
    "gn:asciiname":"Trnjine",
    "gn:country_code":"ME",
    "gn:dem":781,
    "gn:feature_class":"P",
    "gn:feature_code":"PPL",
    "gn:name":"Trnjine",
    "gn:population":0,
    "gn:timezone":"Europe/Podgorica",
    "iso:country":"ME",
    "name:und_x_variant":[
        "Trnine",
        "Trnjine"
    ],
    "wof:name":"Trnjine",
    "wof:placetype":"locality"
},
  "geometry": {"coordinates":[18.86028,42.56389],"type":"Point"}
}