{
  "type": "Feature",
  "properties": {
    "gn:admin1_code":"16.0",
    "gn:asciiname":"Donje Stravce",
    "gn:country_code":"ME",
    "gn:dem":1160,
    "gn:feature_class":"P",
    "gn:feature_code":"PPL",
    "gn:name":"Donje Strav\u010de",
    "gn:population":0,
    "gn:timezone":"Europe/Podgorica",
    "iso:country":"ME",
    "name:srp_x_preferred":[
        "Donje Strav\u010de"
    ],
    "wof:name":"Donje Stravce",
    "wof:placetype":"locality"
},
  "geometry": {"coordinates":[19.465,42.58083],"type":"Point"}
}