{
  "type": "Feature",
  "properties": {
    "gn:admin1_code":"15.0",
    "gn:asciiname":"Cokova Luka",
    "gn:country_code":"ME",
    "gn:dem":489,
    "gn:feature_class":"P",
    "gn:feature_code":"PPL",
    "gn:name":"\u010cokova Luka",
    "gn:population":0,
    "gn:timezone":"Europe/Podgorica",
    "iso:country":"ME",
    "name:srp_x_preferred":[
        "\u010cokova Luka"
    ],
    "wof:name":"Cokova Luka",
    "wof:placetype":"locality"
},
  "geometry": {"coordinates":[18.84889,43.31194],"type":"Point"}
}