{
  "type": "Feature",
  "properties": {
    "gn:admin1_code":"7.0",
    "gn:asciiname":"Serdar Kula",
    "gn:country_code":"ME",
    "gn:dem":81,
    "gn:feature_class":"P",
    "gn:feature_code":"PPL",
    "gn:name":"Serdar Kula",
    "gn:population":0,
    "gn:timezone":"Europe/Podgorica",
    "iso:country":"ME",
    "name:srp_x_preferred":[
        "Serdar Kula"
    ],
    "wof:name":"Serdar Kula",
    "wof:placetype":"locality"
},
  "geometry": {"coordinates":[19.18667,42.48778],"type":"Point"}
}