{
  "type": "Feature",
  "properties": {
    "gn:admin1_code":"9.0",
    "gn:asciiname":"Pjescanica",
    "gn:country_code":"ME",
    "gn:dem":962,
    "gn:feature_class":"P",
    "gn:feature_code":"PPL",
    "gn:name":"Pje\u0161\u010danica",
    "gn:population":0,
    "gn:timezone":"Europe/Podgorica",
    "iso:country":"ME",
    "name:srp_x_preferred":[
        "Pje\u0161\u010danica"
    ],
    "wof:name":"Pjescanica",
    "wof:placetype":"locality"
},
  "geometry": {"coordinates":[19.52444,42.7875],"type":"Point"}
}