{
  "type": "Feature",
  "properties": {
    "gn:admin1_code":"16.0",
    "gn:asciiname":"Poprat",
    "gn:country_code":"ME",
    "gn:dem":1098,
    "gn:feature_class":"P",
    "gn:feature_code":"PPL",
    "gn:name":"Poprat",
    "gn:population":0,
    "gn:timezone":"Europe/Podgorica",
    "iso:country":"ME",
    "name:srp_x_preferred":[
        "Poprat"
    ],
    "wof:name":"Poprat",
    "wof:placetype":"locality"
},
  "geometry": {"coordinates":[19.51194,42.45556],"type":"Point"}
}