{
  "type": "Feature",
  "properties": {
    "gn:admin1_code":"9.0",
    "gn:asciiname":"Luge",
    "gn:country_code":"ME",
    "gn:dem":316,
    "gn:feature_class":"P",
    "gn:feature_code":"PPL",
    "gn:name":"Luge",
    "gn:population":0,
    "gn:timezone":"Europe/Podgorica",
    "iso:country":"ME",
    "name:und_x_variant":[
        "Luzi",
        "Luge"
    ],
    "wof:name":"Luge",
    "wof:placetype":"locality"
},
  "geometry": {"coordinates":[19.40361,42.78111],"type":"Point"}
}