{
  "type": "Feature",
  "properties": {
    "gn:country":"ME",
    "gn:fcode":"PPLL",
    "gn:pop":73,
    "iso:country":"ME",
    "qs:name":"Slatina",
    "qs:photos_9r":0,
    "qs:photos_sr":0,
    "qs:pop_sr":"1",
    "wd:wordcount":542,
    "wof:name":"Slatina",
    "wof:placetype":"locality",
    "wof:population":73
},
  "geometry": {"coordinates":[19.14722,42.58667],"type":"Point"}
}