{
  "type": "Feature",
  "properties": {
    "gn:country":"ME",
    "gn:fcode":"PPLL",
    "gn:population":73,
    "iso:country":"ME",
    "name:azb_x_preferred":[
        "\u0633\u062a\u06cc\u0626\u0627"
    ],
    "name:ben_x_preferred":[
        "\u09b8\u09cd\u09b2\u09be\u09a4\u09bf\u09a8\u09be"
    ],
    "name:bos_x_preferred":[
        "Slatina"
    ],
    "name:bul_x_preferred":[
        "\u0421\u043b\u0430\u0442\u0438\u043d\u0430"
    ],
    "name:ceb_x_preferred":[
        "Slatina"
    ],
    "name:ces_x_preferred":[
        "Slatina"
    ],
    "name:deu_x_preferred":[
        "Slatina"
    ],
    "name:eng_x_preferred":[
        "Slatina"
    ],
    "name:epo_x_preferred":[
        "Slatina"
    ],
    "name:eus_x_preferred":[
        "Slatina"
    ],
    "name:fin_x_preferred":[
        "Slatina"
    ],
    "name:fra_x_preferred":[
        "Slatina"
    ],
    "name:heb_x_preferred":[
        "\u05e1\u05dc\u05d0\u05d8\u05d9\u05e0\u05d4"
    ],
    "name:hin_x_preferred":[
        "\u0938\u094d\u0932\u0947\u091f\u093f\u0928\u093e"
    ],
    "name:hrv_x_preferred":[
        "Slatina"
    ],
    "name:hun_x_preferred":[
        "Slatina"
    ],
    "name:ita_x_preferred":[
        "Slatina"
    ],
    "name:jpn_x_preferred":[
        "\u30b9\u30e9\u30c6\u30a3\u30ca"
    ],
    "name:kaz_x_preferred":[
        "\u0421\u043b\u0430\u0442\u0438\u043d\u0430"
    ],
    "name:min_x_preferred":[
        "Slatina"
    ],
    "name:mkd_x_preferred":[
        "\u0421\u043b\u0430\u0442\u0438\u043d\u0430"
    ],
    "name:nld_x_preferred":[
        "Slatina"
    ],
    "name:nno_x_preferred":[
        "Slatina"
    ],
    "name:pol_x_preferred":[
        "Slatina"
    ],
    "name:por_x_preferred":[
        "Slatina"
    ],
    "name:ron_x_preferred":[
        "Slatina"
    ],
    "name:rus_x_preferred":[
        "\u0421\u043b\u0430\u0442\u0438\u043d\u0430"
    ],
    "name:slk_x_preferred":[
        "Slatina"
    ],
    "name:slv_x_preferred":[
        "Slatina"
    ],
    "name:spa_x_preferred":[
        "Slatina"
    ],
    "name:sqi_x_preferred":[
        "Sllatina"
    ],
    "name:srp_x_preferred":[
        "\u0421\u043b\u0430\u0442\u0438\u043d\u0430"
    ],
    "name:swe_x_preferred":[
        "Slatina"
    ],
    "name:tat_x_preferred":[
        "\u0421\u043b\u0430\u0442\u0438\u043d\u0430"
    ],
    "name:ukr_x_preferred":[
        "\u0421\u043b\u0430\u0442\u0438\u043d\u0430"
    ],
    "qs:name":"Slatina",
    "qs:photos_9r":0,
    "qs:photos_sr":0,
    "qs:pop_sr":"1",
    "wd:wordcount":542,
    "wof:name":"Slatina",
    "wof:placetype":"locality",
    "wof:population":73
},
  "geometry": {"coordinates":[19.14722,42.58667],"type":"Point"}
}