{
  "type": "Feature",
  "properties": {
    "gn:admin1_code":"14.0",
    "gn:asciiname":"Dub",
    "gn:country_code":"ME",
    "gn:dem":819,
    "gn:feature_class":"P",
    "gn:feature_code":"PPL",
    "gn:name":"Dub",
    "gn:population":0,
    "gn:timezone":"Europe/Podgorica",
    "iso:country":"ME",
    "name:srp_x_preferred":[
        "Dub"
    ],
    "wof:name":"Dub",
    "wof:placetype":"locality"
},
  "geometry": {"coordinates":[19.255,43.39083],"type":"Point"}
}