{
  "type": "Feature",
  "properties": {
    "gn:admin1_code":"2.0",
    "gn:asciiname":"Gurza",
    "gn:country_code":"ME",
    "gn:dem":592,
    "gn:feature_class":"P",
    "gn:feature_code":"PPL",
    "gn:name":"Gurza",
    "gn:population":0,
    "gn:timezone":"Europe/Podgorica",
    "iso:country":"ME",
    "name:und_x_variant":[
        "Guraza",
        "Gurza"
    ],
    "wof:name":"Gurza",
    "wof:placetype":"locality"
},
  "geometry": {"coordinates":[19.17,42.16111],"type":"Point"}
}