{
  "type": "Feature",
  "properties": {
    "gn:admin1_code":"14.0",
    "gn:asciiname":"Sumani",
    "gn:country_code":"ME",
    "gn:dem":897,
    "gn:feature_class":"P",
    "gn:feature_code":"PPL",
    "gn:name":"\u0160umani",
    "gn:population":0,
    "gn:timezone":"Europe/Podgorica",
    "iso:country":"ME",
    "name:fra_x_preferred":[
        "\u0160umani"
    ],
    "name:ron_x_preferred":[
        "\u0160umani"
    ],
    "name:slv_x_preferred":[
        "\u0160umani"
    ],
    "name:srp_x_preferred":[
        "\u0160umani"
    ],
    "name:srp_x_variant":[
        "\u0428\u0443\u043c\u0430\u043d\u0438"
    ],
    "wof:name":"Sumani",
    "wof:placetype":"locality"
},
  "geometry": {"coordinates":[19.32583,43.29306],"type":"Point"}
}