{
  "type": "Feature",
  "properties": {
    "gn:admin1_code":"12.0",
    "gn:asciiname":"Jalovca Do",
    "gn:country_code":"ME",
    "gn:dem":918,
    "gn:feature_class":"P",
    "gn:feature_code":"PPL",
    "gn:name":"Jalov\u010da Do",
    "gn:population":0,
    "gn:timezone":"Europe/Podgorica",
    "iso:country":"ME",
    "name:srp_x_preferred":[
        "Jalov\u010da Do"
    ],
    "wof:name":"Jalovca Do",
    "wof:placetype":"locality"
},
  "geometry": {"coordinates":[18.69083,42.70972],"type":"Point"}
}