{
  "type": "Feature",
  "properties": {
    "gn:admin1_code":"6.0",
    "gn:asciiname":"Malezine Zagrade",
    "gn:country_code":"ME",
    "gn:dem":69,
    "gn:feature_class":"P",
    "gn:feature_code":"PPL",
    "gn:name":"Malezine Zagrade",
    "gn:population":0,
    "gn:timezone":"Europe/Podgorica",
    "iso:country":"ME",
    "name:srp_x_preferred":[
        "Malezine Zagrade"
    ],
    "wof:name":"Malezine Zagrade",
    "wof:placetype":"locality"
},
  "geometry": {"coordinates":[19.09417,42.34917],"type":"Point"}
}