{
  "type": "Feature",
  "properties": {
    "gn:admin1_code":"5.0",
    "gn:asciiname":"Lazi",
    "gn:country_code":"ME",
    "gn:dem":58,
    "gn:feature_class":"P",
    "gn:feature_code":"PPL",
    "gn:name":"Lazi",
    "gn:population":0,
    "gn:timezone":"Europe/Podgorica",
    "iso:country":"ME",
    "name:bos_x_preferred":[
        "Lazi"
    ],
    "name:ceb_x_preferred":[
        "Lazi"
    ],
    "name:deu_x_preferred":[
        "Lazi"
    ],
    "name:epo_x_preferred":[
        "Lazi"
    ],
    "name:fra_x_preferred":[
        "Lazi"
    ],
    "name:hrv_x_preferred":[
        "Lazi"
    ],
    "name:hun_x_preferred":[
        "Lazi"
    ],
    "name:jpn_x_preferred":[
        "\u30ef\u30b8"
    ],
    "name:lit_x_preferred":[
        "Lazai"
    ],
    "name:sco_x_preferred":[
        "Lazi"
    ],
    "name:slv_x_preferred":[
        "Lazi"
    ],
    "name:srp_x_preferred":[
        "Lazi"
    ],
    "name:srp_x_variant":[
        "\u041b\u0430\u0437\u0438"
    ],
    "name:swe_x_preferred":[
        "Lazi"
    ],
    "wof:name":"Lazi",
    "wof:placetype":"locality"
},
  "geometry": {"coordinates":[18.84833,42.29667],"type":"Point"}
}