{
  "type": "Feature",
  "properties": {
    "gn:admin1_code":"5.0",
    "gn:asciiname":"Lazi",
    "gn:country_code":"ME",
    "gn:dem":58,
    "gn:feature_class":"P",
    "gn:feature_code":"PPL",
    "gn:name":"Lazi",
    "gn:population":0,
    "gn:timezone":"Europe/Podgorica",
    "iso:country":"ME",
    "name:srp_x_preferred":[
        "Lazi"
    ],
    "wof:name":"Lazi",
    "wof:placetype":"locality"
},
  "geometry": {"coordinates":[18.84833,42.29667],"type":"Point"}
}