{
  "type": "Feature",
  "properties": {
    "gn:admin1_code":"12.0",
    "gn:asciiname":"Gornje Srijede",
    "gn:country_code":"ME",
    "gn:dem":1038,
    "gn:feature_class":"P",
    "gn:feature_code":"PPL",
    "gn:name":"Gornje Srijede",
    "gn:population":0,
    "gn:timezone":"Europe/Podgorica",
    "iso:country":"ME",
    "name:und_x_variant":[
        "\u00d0orojevi\u0107a Vatan",
        "Gornje Srijede"
    ],
    "wof:name":"Gornje Srijede",
    "wof:placetype":"locality"
},
  "geometry": {"coordinates":[18.72944,42.93611],"type":"Point"}
}