{
  "type": "Feature",
  "properties": {
    "gn:admin1_code":"4.0",
    "gn:asciiname":"Dobrakovo",
    "gn:country_code":"ME",
    "gn:dem":627,
    "gn:feature_class":"P",
    "gn:feature_code":"PPL",
    "gn:name":"Dobrakovo",
    "gn:population":0,
    "gn:timezone":"Europe/Podgorica",
    "iso:country":"ME",
    "name:und_x_variant":[
        "Selo Kapetanovi\u0107a",
        "Dobrakovo"
    ],
    "wof:name":"Dobrakovo",
    "wof:placetype":"locality"
},
  "geometry": {"coordinates":[19.77444,43.13944],"type":"Point"}
}