{
  "type": "Feature",
  "properties": {
    "gn:admin1_code":"4.0",
    "gn:asciiname":"Dobrakovo",
    "gn:country_code":"ME",
    "gn:dem":627,
    "gn:feature_class":"P",
    "gn:feature_code":"PPL",
    "gn:name":"Dobrakovo",
    "gn:population":0,
    "gn:timezone":"Europe/Podgorica",
    "iso:country":"ME",
    "name:fra_x_preferred":[
        "Dobrakovo"
    ],
    "name:ron_x_preferred":[
        "Dobrakovo"
    ],
    "name:rus_x_preferred":[
        "\u0414\u043e\u0431\u0440\u0430\u043a\u043e\u0432\u043e"
    ],
    "name:slv_x_preferred":[
        "Dobrakovo"
    ],
    "name:srp_x_preferred":[
        "\u0414\u043e\u0431\u0440\u0430\u043a\u043e\u0432\u043e"
    ],
    "name:und_x_variant":[
        "Selo Kapetanovi\u0107a"
    ],
    "wof:name":"Dobrakovo",
    "wof:placetype":"locality"
},
  "geometry": {"coordinates":[19.77444,43.13944],"type":"Point"}
}