{
  "type": "Feature",
  "properties": {
    "gn:admin1_code":"12.0",
    "gn:asciiname":"Dobrus",
    "gn:country_code":"ME",
    "gn:dem":441,
    "gn:feature_class":"P",
    "gn:feature_code":"PPL",
    "gn:name":"Dobru\u0161",
    "gn:population":0,
    "gn:timezone":"Europe/Podgorica",
    "iso:country":"ME",
    "name:srp_x_preferred":[
        "Dobru\u0161"
    ],
    "wof:name":"Dobrus",
    "wof:placetype":"locality"
},
  "geometry": {"coordinates":[18.96694,42.65556],"type":"Point"}
}