{
  "type": "Feature",
  "properties": {
    "gn:admin1_code":"6.0",
    "gn:asciiname":"Cevo",
    "gn:country_code":"ME",
    "gn:dem":748,
    "gn:feature_class":"P",
    "gn:feature_code":"PPLL",
    "gn:name":"\u010cevo",
    "gn:population":0,
    "gn:timezone":"Europe/Podgorica",
    "iso:country":"ME",
    "name:fra_x_preferred":[
        "\u010cevo"
    ],
    "name:ron_x_preferred":[
        "\u010cevo"
    ],
    "name:slv_x_preferred":[
        "\u010cevo"
    ],
    "name:srp_x_preferred":[
        "\u0427\u0435\u0432\u043e"
    ],
    "wof:name":"Cevo",
    "wof:placetype":"locality"
},
  "geometry": {"coordinates":[18.91917,42.545],"type":"Point"}
}