{
  "type": "Feature",
  "properties": {
    "gn:admin1_code":"3.0",
    "gn:asciiname":"Donji Luzac",
    "gn:country_code":"ME",
    "gn:dem":716,
    "gn:feature_class":"P",
    "gn:feature_code":"PPL",
    "gn:name":"Donji Lu\u017eac",
    "gn:population":0,
    "gn:timezone":"Europe/Podgorica",
    "iso:country":"ME",
    "name:und_x_variant":[
        "Lu\u017eac",
        "Donji Lu\u017eac"
    ],
    "wof:name":"Donji Luzac",
    "wof:placetype":"locality"
},
  "geometry": {"coordinates":[19.855,42.83889],"type":"Point"}
}