{
  "type": "Feature",
  "properties": {
    "gn:admin1_code":"1.0",
    "gn:asciiname":"Savrdak",
    "gn:country_code":"ME",
    "gn:dem":928,
    "gn:feature_class":"P",
    "gn:feature_code":"PPL",
    "gn:name":"Savrdak",
    "gn:population":0,
    "gn:timezone":"Europe/Podgorica",
    "iso:country":"ME",
    "wof:name":"Savrdak",
    "wof:placetype":"locality"
},
  "geometry": {"coordinates":[19.76306,42.69556],"type":"Point"}
}