{
  "type": "Feature",
  "properties": {
    "gn:admin1_code":"7.0",
    "gn:asciiname":"Slapci",
    "gn:country_code":"ME",
    "gn:dem":49,
    "gn:feature_class":"P",
    "gn:feature_code":"PPL",
    "gn:name":"Slapci",
    "gn:population":0,
    "gn:timezone":"Europe/Podgorica",
    "iso:country":"ME",
    "name:und_x_variant":[
        "Slap",
        "Slapci"
    ],
    "wof:name":"Slapci",
    "wof:placetype":"locality"
},
  "geometry": {"coordinates":[19.0175,42.63056],"type":"Point"}
}