{
  "type": "Feature",
  "properties": {
    "gn:admin1_code":"14.0",
    "gn:asciiname":"Damjanovici",
    "gn:country_code":"ME",
    "gn:dem":1109,
    "gn:feature_class":"P",
    "gn:feature_code":"PPL",
    "gn:name":"Damjanovi\u0107i",
    "gn:population":0,
    "gn:timezone":"Europe/Podgorica",
    "iso:country":"ME",
    "name:srp_x_preferred":[
        "Damjanovi\u0107i"
    ],
    "wof:name":"Damjanovici",
    "wof:placetype":"locality"
},
  "geometry": {"coordinates":[19.32111,43.40861],"type":"Point"}
}