{
  "type": "Feature",
  "properties": {
    "gn:admin1_code":"12.0",
    "gn:asciiname":"Nugo",
    "gn:country_code":"ME",
    "gn:dem":938,
    "gn:feature_class":"P",
    "gn:feature_code":"PPL",
    "gn:name":"Nugo",
    "gn:population":0,
    "gn:timezone":"Europe/Podgorica",
    "iso:country":"ME",
    "name:srp_x_preferred":[
        "Nugo"
    ],
    "wof:name":"Nugo",
    "wof:placetype":"locality"
},
  "geometry": {"coordinates":[18.61417,42.68722],"type":"Point"}
}