{
  "type": "Feature",
  "properties": {
    "gn:admin1_code":"7.0",
    "gn:asciiname":"Gradina",
    "gn:country_code":"ME",
    "gn:dem":130,
    "gn:feature_class":"P",
    "gn:feature_code":"PPL",
    "gn:name":"Gradina",
    "gn:population":0,
    "gn:timezone":"Europe/Podgorica",
    "iso:country":"ME",
    "wof:name":"Gradina",
    "wof:placetype":"locality"
},
  "geometry": {"coordinates":[19.20361,42.54194],"type":"Point"}
}