{
  "type": "Feature",
  "properties": {
    "gn:admin1_code":"7.0",
    "gn:asciiname":"Gradina",
    "gn:country_code":"ME",
    "gn:dem":130,
    "gn:feature_class":"P",
    "gn:feature_code":"PPL",
    "gn:name":"Gradina",
    "gn:population":0,
    "gn:timezone":"Europe/Podgorica",
    "iso:country":"ME",
    "name:bos_x_preferred":[
        "Gradina"
    ],
    "name:bul_x_preferred":[
        "\u0413\u0440\u0430\u0434\u0438\u043d\u0430"
    ],
    "name:ceb_x_preferred":[
        "Gradina"
    ],
    "name:fra_x_preferred":[
        "Gradina"
    ],
    "name:hrv_x_preferred":[
        "Gradina"
    ],
    "name:hun_x_preferred":[
        "Gradina"
    ],
    "name:ita_x_preferred":[
        "Gradina"
    ],
    "name:nld_x_preferred":[
        "Gradina"
    ],
    "name:pol_x_preferred":[
        "Gradina"
    ],
    "name:ron_x_preferred":[
        "Gradina"
    ],
    "name:rus_x_preferred":[
        "\u0413\u0440\u0430\u0434\u0438\u043d\u0430"
    ],
    "name:slv_x_preferred":[
        "Gradina"
    ],
    "name:srp_x_preferred":[
        "\u0413\u0440\u0430\u0434\u0438\u043d\u0430"
    ],
    "name:swe_x_preferred":[
        "Gradina"
    ],
    "name:ukr_x_preferred":[
        "\u0413\u0440\u0430\u0434\u0438\u043d\u0430"
    ],
    "wof:name":"Gradina",
    "wof:placetype":"locality"
},
  "geometry": {"coordinates":[19.20361,42.54194],"type":"Point"}
}