{
  "type": "Feature",
  "properties": {
    "gn:gn_country":"ME",
    "gn:gn_fcode":"PPL",
    "gn:gn_pop":5,
    "gn:population":5,
    "iso:country":"ME",
    "qs_pg:aaroncc":"ME",
    "qs_pg:gn_country":"ME",
    "qs_pg:gn_fcode":"PPL",
    "qs_pg:gn_pop":5,
    "qs_pg:name":"Tripkovi\u0107i",
    "qs_pg:photos_9r":0,
    "qs_pg:photos_sr":0,
    "qs_pg:pop_sr":1,
    "qs_pg:qs_pg_placetype":"locality",
    "wof:name":"Tripkovi\u0107i",
    "wof:placetype":"locality",
    "wof:population":5
},
  "geometry": {"coordinates":[18.76417,42.46306],"type":"Point"}
}