{
  "type": "Feature",
  "properties": {
    "gn:admin1_code":"6.0",
    "gn:asciiname":"Zovica",
    "gn:country_code":"ME",
    "gn:dem":826,
    "gn:feature_class":"P",
    "gn:feature_code":"PPL",
    "gn:name":"Zovica",
    "gn:population":0,
    "gn:timezone":"Europe/Podgorica",
    "iso:country":"ME",
    "name:srp_x_preferred":[
        "Zovica"
    ],
    "wof:name":"Zovica",
    "wof:placetype":"locality"
},
  "geometry": {"coordinates":[18.85917,42.56861],"type":"Point"}
}