{
  "type": "Feature",
  "properties": {
    "gn:admin1_code":"14.0",
    "gn:asciiname":"Vijenac",
    "gn:country_code":"ME",
    "gn:dem":1176,
    "gn:feature_class":"P",
    "gn:feature_code":"PPLL",
    "gn:name":"Vijenac",
    "gn:population":0,
    "gn:timezone":"Europe/Podgorica",
    "iso:country":"ME",
    "wof:name":"Vijenac",
    "wof:placetype":"locality"
},
  "geometry": {"coordinates":[19.44333,43.32917],"type":"Point"}
}