{
  "type": "Feature",
  "properties": {
    "gn:admin1_code":"12.0",
    "gn:asciiname":"Stubicki Kraj",
    "gn:country_code":"ME",
    "gn:dem":663,
    "gn:feature_class":"P",
    "gn:feature_code":"PPL",
    "gn:name":"Stubi\u010dki Kraj",
    "gn:population":0,
    "gn:timezone":"Europe/Podgorica",
    "iso:country":"ME",
    "name:srp_x_preferred":[
        "Stubi\u010dki Kraj"
    ],
    "wof:name":"Stubicki Kraj",
    "wof:placetype":"locality"
},
  "geometry": {"coordinates":[18.98944,42.71583],"type":"Point"}
}