{
  "type": "Feature",
  "properties": {
    "gn:admin1_code":"12.0",
    "gn:asciiname":"Ploce",
    "gn:country_code":"ME",
    "gn:dem":240,
    "gn:feature_class":"P",
    "gn:feature_code":"PPL",
    "gn:name":"Plo\u010de",
    "gn:population":0,
    "gn:timezone":"Europe/Podgorica",
    "iso:country":"ME",
    "name:srp_x_preferred":[
        "Plo\u010de"
    ],
    "wof:name":"Ploce",
    "wof:placetype":"locality"
},
  "geometry": {"coordinates":[19.00167,42.67444],"type":"Point"}
}