{
  "type": "Feature",
  "properties": {
    "gn:admin1_code":"3.0",
    "gn:asciiname":"Krs",
    "gn:country_code":"ME",
    "gn:dem":1043,
    "gn:feature_class":"P",
    "gn:feature_code":"PPL",
    "gn:name":"Kr\u0161",
    "gn:population":0,
    "gn:timezone":"Europe/Podgorica",
    "iso:country":"ME",
    "wof:name":"Krs",
    "wof:placetype":"locality"
},
  "geometry": {"coordinates":[19.84889,42.71806],"type":"Point"}
}