{
  "type": "Feature",
  "properties": {
    "gn:admin1_code":"16.0",
    "gn:asciiname":"Skorafci",
    "gn:country_code":"ME",
    "gn:dem":571,
    "gn:feature_class":"P",
    "gn:feature_code":"PPL",
    "gn:name":"Skorafci",
    "gn:population":0,
    "gn:timezone":"Europe/Podgorica",
    "iso:country":"ME",
    "name:srp_x_preferred":[
        "Skorafci"
    ],
    "wof:name":"Skorafci",
    "wof:placetype":"locality"
},
  "geometry": {"coordinates":[19.39944,42.35472],"type":"Point"}
}