{
  "type": "Feature",
  "properties": {
    "gn:admin1_code":"10.0",
    "gn:asciiname":"Zagvozdak",
    "gn:country_code":"ME",
    "gn:dem":948,
    "gn:feature_class":"P",
    "gn:feature_code":"PPL",
    "gn:name":"Zagvozdak",
    "gn:population":0,
    "gn:timezone":"Europe/Podgorica",
    "iso:country":"ME",
    "name:srp_x_preferred":[
        "Zagvozdak"
    ],
    "wof:name":"Zagvozdak",
    "wof:placetype":"locality"
},
  "geometry": {"coordinates":[18.65,42.59083],"type":"Point"}
}