{
  "type": "Feature",
  "properties": {
    "gn:admin1_code":"14.0",
    "gn:asciiname":"Donja Rudnica",
    "gn:country_code":"ME",
    "gn:dem":883,
    "gn:feature_class":"P",
    "gn:feature_code":"PPL",
    "gn:name":"Donja Rudnica",
    "gn:population":0,
    "gn:timezone":"Europe/Podgorica",
    "iso:country":"ME",
    "name:und_x_variant":[
        "Rudnica",
        "Donja Rudnica"
    ],
    "wof:name":"Donja Rudnica",
    "wof:placetype":"locality"
},
  "geometry": {"coordinates":[19.32528,43.37944],"type":"Point"}
}