{
  "type": "Feature",
  "properties": {
    "gn:admin1_code":"12.0",
    "gn:asciiname":"Vasiljevici",
    "gn:country_code":"ME",
    "gn:dem":837,
    "gn:feature_class":"P",
    "gn:feature_code":"PPLL",
    "gn:name":"Vasiljevi\u0107i",
    "gn:population":0,
    "gn:timezone":"Europe/Podgorica",
    "iso:country":"ME",
    "wof:name":"Vasiljevici",
    "wof:placetype":"locality"
},
  "geometry": {"coordinates":[19.12444,42.72722],"type":"Point"}
}