{
  "type": "Feature",
  "properties": {
    "gn:admin1_code":"16.0",
    "gn:asciiname":"Barutana",
    "gn:country_code":"ME",
    "gn:dem":132,
    "gn:feature_class":"P",
    "gn:feature_code":"PPL",
    "gn:name":"Barutana",
    "gn:population":0,
    "gn:timezone":"Europe/Podgorica",
    "iso:country":"ME",
    "name:srp_x_preferred":[
        "Barutana"
    ],
    "wof:name":"Barutana",
    "wof:placetype":"locality"
},
  "geometry": {"coordinates":[19.14194,42.3925],"type":"Point"}
}