{
  "type": "Feature",
  "properties": {
    "gn:admin1_code":"8.0",
    "gn:asciiname":"Petrovici",
    "gn:country_code":"ME",
    "gn:dem":126,
    "gn:feature_class":"P",
    "gn:feature_code":"PPL",
    "gn:name":"Petrovi\u0107i",
    "gn:population":0,
    "gn:timezone":"Europe/Podgorica",
    "iso:country":"ME",
    "name:srp_x_preferred":[
        "Petrovi\u0107i"
    ],
    "wof:name":"Petrovici",
    "wof:placetype":"locality"
},
  "geometry": {"coordinates":[18.64361,42.45444000000001],"type":"Point"}
}