{
  "type": "Feature",
  "properties": {
    "gn:admin1_code":"2.0",
    "gn:asciiname":"Bukovik",
    "gn:country_code":"ME",
    "gn:dem":308,
    "gn:feature_class":"P",
    "gn:feature_code":"PPL",
    "gn:name":"Bukovik",
    "gn:population":0,
    "gn:timezone":"Europe/Podgorica",
    "iso:country":"ME",
    "name:bos_x_preferred":[
        "Bukovik"
    ],
    "name:bul_x_preferred":[
        "\u0411\u0443\u043a\u043e\u0432\u0438\u043a"
    ],
    "name:ceb_x_preferred":[
        "Bukovik"
    ],
    "name:fra_x_preferred":[
        "Bukovik"
    ],
    "name:hrv_x_preferred":[
        "Bukovik"
    ],
    "name:nld_x_preferred":[
        "Bukovik"
    ],
    "name:slv_x_preferred":[
        "Bukovik"
    ],
    "name:sqi_x_preferred":[
        "Bukoviku"
    ],
    "name:srp_x_preferred":[
        "Bukovik"
    ],
    "name:srp_x_variant":[
        "\u0411\u0443\u043a\u043e\u0432\u0438\u043a"
    ],
    "name:swe_x_preferred":[
        "Bukovik"
    ],
    "wof:name":"Bukovik",
    "wof:placetype":"locality"
},
  "geometry": {"coordinates":[19.02722,42.23111],"type":"Point"}
}