{
  "type": "Feature",
  "properties": {
    "gn:admin1_code":"6.0",
    "gn:asciiname":"Uba",
    "gn:country_code":"ME",
    "gn:dem":855,
    "gn:feature_class":"P",
    "gn:feature_code":"PPL",
    "gn:name":"Uba",
    "gn:population":0,
    "gn:timezone":"Europe/Podgorica",
    "iso:country":"ME",
    "name:ceb_x_preferred":[
        "Uba"
    ],
    "name:fra_x_preferred":[
        "Uba"
    ],
    "name:hye_x_preferred":[
        "\u0548\u0582\u0562\u0561"
    ],
    "name:kaz_x_preferred":[
        "\u0423\u0431\u0430"
    ],
    "name:pol_x_preferred":[
        "Uba"
    ],
    "name:spa_x_preferred":[
        "UBA"
    ],
    "name:srp_x_preferred":[
        "Uba"
    ],
    "name:swe_x_preferred":[
        "Uba"
    ],
    "name:ukr_x_preferred":[
        "\u0423\u0431\u0430"
    ],
    "wof:name":"Uba",
    "wof:placetype":"locality"
},
  "geometry": {"coordinates":[18.84389,42.47528],"type":"Point"}
}