{
  "type": "Feature",
  "properties": {
    "gn:admin1_code":"14.0",
    "gn:asciiname":"Gornja Tikova",
    "gn:country_code":"ME",
    "gn:dem":914,
    "gn:feature_class":"P",
    "gn:feature_code":"PPL",
    "gn:name":"Gornja Tikova",
    "gn:population":0,
    "gn:timezone":"Europe/Podgorica",
    "iso:country":"ME",
    "name:srp_x_preferred":[
        "Gornja Tikova"
    ],
    "wof:name":"Gornja Tikova",
    "wof:placetype":"locality"
},
  "geometry": {"coordinates":[19.22889,43.35639000000001],"type":"Point"}
}