{
  "type": "Feature",
  "properties": {
    "gn:admin1_code":"18.0",
    "gn:asciiname":"Mrdenovac",
    "gn:country_code":"ME",
    "gn:dem":1412,
    "gn:feature_class":"P",
    "gn:feature_code":"PPL",
    "gn:name":"Mr\u0111enovac",
    "gn:population":0,
    "gn:timezone":"Europe/Podgorica",
    "iso:country":"ME",
    "wof:name":"Mrdenovac",
    "wof:placetype":"locality"
},
  "geometry": {"coordinates":[19.12972,43.05444],"type":"Point"}
}