{
  "type": "Feature",
  "properties": {
    "gn:admin1_code":"16.0",
    "gn:asciiname":"Lazorci",
    "gn:country_code":"ME",
    "gn:dem":916,
    "gn:feature_class":"P",
    "gn:feature_code":"PPL",
    "gn:name":"Lazorci",
    "gn:population":0,
    "gn:timezone":"Europe/Podgorica",
    "iso:country":"ME",
    "name:srp_x_preferred":[
        "Lazorci"
    ],
    "wof:name":"Lazorci",
    "wof:placetype":"locality"
},
  "geometry": {"coordinates":[19.45278,42.49528],"type":"Point"}
}