{
  "type": "Feature",
  "properties": {
    "gn:admin1_code":"9.0",
    "gn:asciiname":"Musovica Rijeka",
    "gn:country_code":"ME",
    "gn:dem":1103,
    "gn:feature_class":"P",
    "gn:feature_code":"PPL",
    "gn:name":"Mu\u0161ovi\u0107a Rijeka",
    "gn:population":0,
    "gn:timezone":"Europe/Podgorica",
    "iso:country":"ME",
    "name:und_x_variant":[
        "Rijeka Mu\u0161ovi\u0107a",
        "Mi\u0161ovi\u0107a Rijeka",
        "Mu\u0161ovi\u0107a Rijeka"
    ],
    "wof:name":"Musovica Rijeka",
    "wof:placetype":"locality"
},
  "geometry": {"coordinates":[19.5775,42.83944],"type":"Point"}
}