{
  "type": "Feature",
  "properties": {
    "gn:admin1_code":"10.0",
    "gn:asciiname":"Markov Do",
    "gn:country_code":"ME",
    "gn:dem":568,
    "gn:feature_class":"P",
    "gn:feature_code":"PPL",
    "gn:name":"Markov Do",
    "gn:population":0,
    "gn:timezone":"Europe/Podgorica",
    "iso:country":"ME",
    "name:srp_x_preferred":[
        "Markov Do"
    ],
    "wof:name":"Markov Do",
    "wof:placetype":"locality"
},
  "geometry": {"coordinates":[18.70528,42.56361],"type":"Point"}
}