{
  "type": "Feature",
  "properties": {
    "gn:admin1_code":"5.0",
    "gn:asciiname":"Lugovi",
    "gn:country_code":"ME",
    "gn:dem":14,
    "gn:feature_class":"P",
    "gn:feature_code":"PPL",
    "gn:name":"Lugovi",
    "gn:population":0,
    "gn:timezone":"Europe/Podgorica",
    "iso:country":"ME",
    "name:bos_x_preferred":[
        "Lugovi"
    ],
    "name:fra_x_preferred":[
        "Lugovi"
    ],
    "name:hrv_x_preferred":[
        "Lugovi"
    ],
    "name:slv_x_preferred":[
        "Lugovi"
    ],
    "name:srp_x_preferred":[
        "Lugovi"
    ],
    "name:srp_x_variant":[
        "\u041b\u0443\u0433\u043e\u0432\u0438"
    ],
    "wof:name":"Lugovi",
    "wof:placetype":"locality"
},
  "geometry": {"coordinates":[18.84972,42.29056],"type":"Point"}
}