{
  "type": "Feature",
  "properties": {
    "gn:admin1_code":"16.0",
    "gn:asciiname":"Nik Maras",
    "gn:country_code":"ME",
    "gn:dem":840,
    "gn:feature_class":"P",
    "gn:feature_code":"PPL",
    "gn:name":"Nik Mara\u0161",
    "gn:population":0,
    "gn:timezone":"Europe/Podgorica",
    "iso:country":"ME",
    "name:und_x_variant":[
        "Nikmara\u0161i",
        "Nikmaro\u0161",
        "Nik Mara\u0161"
    ],
    "wof:name":"Nik Maras",
    "wof:placetype":"locality"
},
  "geometry": {"coordinates":[19.43611,42.44194],"type":"Point"}
}