{
  "type": "Feature",
  "properties": {
    "gn:admin1_code":"14.0",
    "gn:asciiname":"Lukovici",
    "gn:country_code":"ME",
    "gn:dem":1472,
    "gn:feature_class":"P",
    "gn:feature_code":"PPL",
    "gn:name":"Lukovi\u0107i",
    "gn:population":0,
    "gn:timezone":"Europe/Podgorica",
    "iso:country":"ME",
    "name:srp_x_preferred":[
        "Lukovi\u0107i"
    ],
    "wof:name":"Lukovici",
    "wof:placetype":"locality"
},
  "geometry": {"coordinates":[19.04222,43.28806],"type":"Point"}
}