{
  "type": "Feature",
  "properties": {
    "gn:admin1_code":"4.0",
    "gn:asciiname":"Selakovici",
    "gn:country_code":"ME",
    "gn:dem":992,
    "gn:feature_class":"P",
    "gn:feature_code":"PPL",
    "gn:name":"Selakovi\u0107i",
    "gn:population":0,
    "gn:timezone":"Europe/Podgorica",
    "iso:country":"ME",
    "name:srp_x_preferred":[
        "Selakovi\u0107i"
    ],
    "wof:name":"Selakovici",
    "wof:placetype":"locality"
},
  "geometry": {"coordinates":[19.65556,43.08722],"type":"Point"}
}