{
  "type": "Feature",
  "properties": {
    "gn:admin1_code":"12.0",
    "gn:asciiname":"Rakita",
    "gn:country_code":"ME",
    "gn:dem":789,
    "gn:feature_class":"P",
    "gn:feature_code":"PPL",
    "gn:name":"Rakita",
    "gn:population":0,
    "gn:timezone":"Europe/Podgorica",
    "iso:country":"ME",
    "name:srp_x_preferred":[
        "Rakita"
    ],
    "wof:name":"Rakita",
    "wof:placetype":"locality"
},
  "geometry": {"coordinates":[18.87444,42.86972],"type":"Point"}
}