{
  "type": "Feature",
  "properties": {
    "gn:admin1_code":"4.0",
    "gn:asciiname":"Kucetine",
    "gn:country_code":"ME",
    "gn:dem":729,
    "gn:feature_class":"P",
    "gn:feature_code":"PPL",
    "gn:name":"Ku\u0107etine",
    "gn:population":0,
    "gn:timezone":"Europe/Podgorica",
    "iso:country":"ME",
    "wof:name":"Kucetine",
    "wof:placetype":"locality"
},
  "geometry": {"coordinates":[19.74444,43.15278],"type":"Point"}
}