{
  "type": "Feature",
  "properties": {
    "gn:admin1_code":"12.0",
    "gn:asciiname":"Zabrnjica",
    "gn:country_code":"ME",
    "gn:dem":832,
    "gn:feature_class":"P",
    "gn:feature_code":"PPL",
    "gn:name":"Zabrnjica",
    "gn:population":0,
    "gn:timezone":"Europe/Podgorica",
    "iso:country":"ME",
    "name:ceb_x_preferred":[
        "Zabrnjica"
    ],
    "name:fra_x_preferred":[
        "Zabrnjica"
    ],
    "name:msa_x_preferred":[
        "Zabrnjica"
    ],
    "name:nld_x_preferred":[
        "Zabrnjica"
    ],
    "name:por_x_preferred":[
        "Zabrnjica"
    ],
    "name:slv_x_preferred":[
        "Zabrnjica"
    ],
    "name:srp_x_preferred":[
        "Zabrnjica"
    ],
    "name:srp_x_variant":[
        "\u0417\u0430\u0431\u0440\u045a\u0438\u0446\u0430"
    ],
    "name:urd_x_preferred":[
        "\u0632\u0628\u0631\u0646\u062c\u06cc\u06a9\u0627"
    ],
    "wof:name":"Zabrnjica",
    "wof:placetype":"locality"
},
  "geometry": {"coordinates":[19.01278,42.78861],"type":"Point"}
}