{
  "type": "Feature",
  "properties": {
    "gn:admin1_code":"4.0",
    "gn:asciiname":"Dobro Brdo",
    "gn:country_code":"ME",
    "gn:dem":1028,
    "gn:feature_class":"P",
    "gn:feature_code":"PPL",
    "gn:name":"Dobro Brdo",
    "gn:population":0,
    "gn:timezone":"Europe/Podgorica",
    "iso:country":"ME",
    "name:srp_x_preferred":[
        "Dobro Brdo"
    ],
    "wof:name":"Dobro Brdo",
    "wof:placetype":"locality"
},
  "geometry": {"coordinates":[19.715,43.12639],"type":"Point"}
}