{
  "type": "Feature",
  "properties": {
    "iso:country":"ME",
    "name:als_x_preferred":[
        "Kruja"
    ],
    "name:ara_x_preferred":[
        "\u0643\u0631\u0648\u064a\u0647"
    ],
    "name:bul_x_preferred":[
        "\u041a\u0440\u0443\u044f"
    ],
    "name:cat_x_preferred":[
        "Kruj\u00eb"
    ],
    "name:ceb_x_preferred":[
        "Kruj\u00eb"
    ],
    "name:ces_x_preferred":[
        "Kruj\u00eb"
    ],
    "name:dan_x_preferred":[
        "Kruj\u00eb"
    ],
    "name:deu_x_preferred":[
        "Kruja"
    ],
    "name:ell_x_preferred":[
        "\u039a\u03c1\u03bf\u03cd\u03b3\u03b9\u03b1"
    ],
    "name:fas_x_preferred":[
        "\u06a9\u0631\u0648\u06cc\u0647"
    ],
    "name:fin_x_preferred":[
        "Kruja"
    ],
    "name:fra_x_preferred":[
        "Kruj\u00eb"
    ],
    "name:heb_x_preferred":[
        "\u05e7\u05e8\u05d5\u05d9\u05d4"
    ],
    "name:hrv_x_preferred":[
        "Kruja"
    ],
    "name:hun_x_preferred":[
        "Kruja"
    ],
    "name:ita_x_preferred":[
        "Kruja"
    ],
    "name:jpn_x_preferred":[
        "\u30af\u30eb\u30e4"
    ],
    "name:kor_x_preferred":[
        "\ud06c\ub8e8\uc5ec"
    ],
    "name:lit_x_preferred":[
        "Kruj\u0117"
    ],
    "name:lmo_x_preferred":[
        "Cr\u00f2ia"
    ],
    "name:mkd_x_preferred":[
        "\u041a\u0440\u043e\u0458\u0430"
    ],
    "name:nld_x_preferred":[
        "Kruj\u00eb"
    ],
    "name:nno_x_preferred":[
        "Kruj\u00eb"
    ],
    "name:nor_x_preferred":[
        "Kruj\u00eb"
    ],
    "name:pnb_x_preferred":[
        "\u06a9\u0631\u0648\u06cc\u06c1"
    ],
    "name:pol_x_preferred":[
        "Kruja"
    ],
    "name:por_x_preferred":[
        "Cruja"
    ],
    "name:ron_x_preferred":[
        "Kruja"
    ],
    "name:rus_x_preferred":[
        "\u041a\u0440\u0443\u044f"
    ],
    "name:slk_x_preferred":[
        "Kruj\u00eb"
    ],
    "name:slv_x_preferred":[
        "Kruja"
    ],
    "name:spa_x_preferred":[
        "Kruj\u00eb"
    ],
    "name:sqi_x_preferred":[
        "Kruja"
    ],
    "name:srp_x_preferred":[
        "\u041a\u0440\u043e\u0458\u0430"
    ],
    "name:swe_x_preferred":[
        "Kruja"
    ],
    "name:tur_x_preferred":[
        "Ak\u00e7ahisar"
    ],
    "name:ukr_x_preferred":[
        "\u041a\u0440\u0443\u044f"
    ],
    "name:unk_x_variant":[
        "Kruci"
    ],
    "name:urd_x_preferred":[
        "\u06a9\u0631\u0648\u06cc\u06c1"
    ],
    "name:vie_x_preferred":[
        "Kruj\u00eb"
    ],
    "name:vol_x_preferred":[
        "Kruja"
    ],
    "name:war_x_preferred":[
        "Kruj\u00eb"
    ],
    "name:zho_x_preferred":[
        "\u514b\u9c81\u4e9a"
    ],
    "qs:gn_country":"ME",
    "qs:gn_fcode":"PPL",
    "qs:gn_pop":0,
    "qs:name":"Kruj\u00eb",
    "qs:name_adm0":"Shqip\u00ebri",
    "qs:name_adm1":"Durr\u00ebs",
    "qs:photos":407,
    "qs:photos_1k":82,
    "qs:photos_9k":2,
    "qs:photos_9r":5,
    "qs:photos_all":407,
    "qs:photos_sr":6,
    "qs:placetype":"Town",
    "qs:pop_sr":"0",
    "qs:woe_adm0":23424742,
    "wof:name":"Kruj\u00eb",
    "wof:placetype":"locality"
},
  "geometry": {"coordinates":[19.17417,41.98],"type":"Point"}
}