{
  "type": "Feature",
  "properties": {
    "iso:country":"ME",
    "name:unk_x_variant":[
        "Kruci"
    ],
    "qs:gn_country":"ME",
    "qs:gn_fcode":"PPL",
    "qs:gn_pop":0,
    "qs:name":"Kruj\u00eb",
    "qs:name_adm0":"Shqip\u00ebri",
    "qs:name_adm1":"Durr\u00ebs",
    "qs:photos":407,
    "qs:photos_1k":82,
    "qs:photos_9k":2,
    "qs:photos_9r":5,
    "qs:photos_all":407,
    "qs:photos_sr":6,
    "qs:placetype":"Town",
    "qs:pop_sr":"0",
    "qs:woe_adm0":23424742,
    "wof:name":"Kruj\u00eb",
    "wof:placetype":"locality"
},
  "geometry": {"coordinates":[19.17417,41.98],"type":"Point"}
}