{
  "type": "Feature",
  "properties": {
    "gn:admin1_code":"6.0",
    "gn:asciiname":"Bogojev Do",
    "gn:country_code":"ME",
    "gn:dem":825,
    "gn:feature_class":"P",
    "gn:feature_code":"PPL",
    "gn:name":"Bogojev Do",
    "gn:population":0,
    "gn:timezone":"Europe/Podgorica",
    "iso:country":"ME",
    "name:srp_x_preferred":[
        "Bogojev Do"
    ],
    "wof:name":"Bogojev Do",
    "wof:placetype":"locality"
},
  "geometry": {"coordinates":[18.73111,42.63778],"type":"Point"}
}