{
  "type": "Feature",
  "properties": {
    "gn:admin1_code":"14.0",
    "gn:asciiname":"Gornji Gradac",
    "gn:country_code":"ME",
    "gn:dem":682,
    "gn:feature_class":"P",
    "gn:feature_code":"PPL",
    "gn:name":"Gornji Gradac",
    "gn:population":0,
    "gn:timezone":"Europe/Podgorica",
    "iso:country":"ME",
    "name:bos_x_preferred":[
        "Gornji Gradac"
    ],
    "name:fra_x_preferred":[
        "Gornji Gradac"
    ],
    "name:hrv_x_preferred":[
        "Gornji Gradac"
    ],
    "name:srp_x_preferred":[
        "Gornji Gradac"
    ],
    "name:srp_x_variant":[
        "\u0413\u043e\u0440\u045a\u0438 \u0413\u0440\u0430\u0434\u0430\u0446"
    ],
    "wof:name":"Gornji Gradac",
    "wof:placetype":"locality"
},
  "geometry": {"coordinates":[19.16278,43.38667],"type":"Point"}
}