{
  "type": "Feature",
  "properties": {
    "gn:admin1_code":"15.0",
    "gn:asciiname":"Kovaci",
    "gn:country_code":"ME",
    "gn:dem":1286,
    "gn:feature_class":"P",
    "gn:feature_code":"PPLL",
    "gn:name":"Kova\u010di",
    "gn:population":0,
    "gn:timezone":"Europe/Podgorica",
    "iso:country":"ME",
    "wof:name":"Kovaci",
    "wof:placetype":"locality"
},
  "geometry": {"coordinates":[18.75278,43.13806],"type":"Point"}
}