{
  "type": "Feature",
  "properties": {
    "gn:admin1_code":"6.0",
    "gn:asciiname":"Drum",
    "gn:country_code":"ME",
    "gn:dem":416,
    "gn:feature_class":"P",
    "gn:feature_code":"PPL",
    "gn:name":"Drum",
    "gn:population":0,
    "gn:timezone":"Europe/Podgorica",
    "iso:country":"ME",
    "name:srp_x_preferred":[
        "Drum"
    ],
    "wof:name":"Drum",
    "wof:placetype":"locality"
},
  "geometry": {"coordinates":[19.02444,42.42833],"type":"Point"}
}