{
  "type": "Feature",
  "properties": {
    "gn:admin1_code":"6.0",
    "gn:asciiname":"Kragujev Do",
    "gn:country_code":"ME",
    "gn:dem":1101,
    "gn:feature_class":"P",
    "gn:feature_code":"PPLL",
    "gn:name":"Kragujev Do",
    "gn:population":0,
    "gn:timezone":"Europe/Podgorica",
    "iso:country":"ME",
    "wof:name":"Kragujev Do",
    "wof:placetype":"locality"
},
  "geometry": {"coordinates":[18.81139,42.64861],"type":"Point"}
}