{
  "type": "Feature",
  "properties": {
    "gn:admin1_code":"15.0",
    "gn:asciiname":"Budanj",
    "gn:country_code":"ME",
    "gn:dem":1092,
    "gn:feature_class":"P",
    "gn:feature_code":"PPL",
    "gn:name":"Budanj",
    "gn:population":0,
    "gn:timezone":"Europe/Podgorica",
    "iso:country":"ME",
    "name:bos_x_preferred":[
        "Budanj"
    ],
    "name:ceb_x_preferred":[
        "Budanj"
    ],
    "name:fra_x_preferred":[
        "Budanj"
    ],
    "name:hrv_x_preferred":[
        "Budanj"
    ],
    "name:srp_x_preferred":[
        "Budanj"
    ],
    "name:srp_x_variant":[
        "\u0411\u0443\u0434\u0430\u045a"
    ],
    "name:swe_x_preferred":[
        "Budanj"
    ],
    "wof:name":"Budanj",
    "wof:placetype":"locality"
},
  "geometry": {"coordinates":[18.82667,43.16667],"type":"Point"}
}