{
  "type": "Feature",
  "properties": {
    "gn:admin1_code":"4.0",
    "gn:asciiname":"Johovac",
    "gn:country_code":"ME",
    "gn:dem":863,
    "gn:feature_class":"P",
    "gn:feature_code":"PPL",
    "gn:name":"Johovac",
    "gn:population":0,
    "gn:timezone":"Europe/Podgorica",
    "iso:country":"ME",
    "name:bos_x_preferred":[
        "Johovac"
    ],
    "name:ceb_x_preferred":[
        "Johovac"
    ],
    "name:fra_x_preferred":[
        "Johovac"
    ],
    "name:hrv_x_preferred":[
        "Johovac"
    ],
    "name:rus_x_preferred":[
        "\u042f\u0445\u043e\u0432\u0430\u0446"
    ],
    "name:slv_x_preferred":[
        "Johovac"
    ],
    "name:srp_x_preferred":[
        "Johovac"
    ],
    "name:srp_x_variant":[
        "\u0408\u043e\u0445\u043e\u0432\u0430\u0446"
    ],
    "name:swe_x_preferred":[
        "Johovac"
    ],
    "name:urd_x_preferred":[
        "\u06cc\u0648\u06c1\u0648\u0648\u0627\u062a\u0633"
    ],
    "wof:name":"Johovac",
    "wof:placetype":"locality"
},
  "geometry": {"coordinates":[19.72028,43.13444000000001],"type":"Point"}
}