{
  "type": "Feature",
  "properties": {
    "gn:country":"ME",
    "gn:fcode":"PPL",
    "gn:population":182,
    "iso:country":"ME",
    "qs:name":"Farmaci",
    "qs:photos_9r":0,
    "qs:photos_sr":0,
    "qs:pop_sr":"1",
    "wof:name":"Farmaci",
    "wof:placetype":"locality",
    "wof:population":182
},
  "geometry": {"coordinates":[19.19194,42.41417],"type":"Point"}
}