{
  "type": "Feature",
  "properties": {
    "gn:admin1_code":"6.0",
    "gn:asciiname":"Tospude",
    "gn:country_code":"ME",
    "gn:dem":683,
    "gn:feature_class":"P",
    "gn:feature_code":"PPL",
    "gn:name":"Tospude",
    "gn:population":0,
    "gn:timezone":"Europe/Podgorica",
    "iso:country":"ME",
    "name:srp_x_preferred":[
        "Tospude"
    ],
    "wof:name":"Tospude",
    "wof:placetype":"locality"
},
  "geometry": {"coordinates":[18.70833,42.64139],"type":"Point"}
}