{
  "type": "Feature",
  "properties": {
    "gn:admin1_code":"8.0",
    "gn:asciiname":"Rake",
    "gn:country_code":"ME",
    "gn:dem":6,
    "gn:feature_class":"P",
    "gn:feature_code":"PPL",
    "gn:name":"Rake",
    "gn:population":0,
    "gn:timezone":"Europe/Podgorica",
    "iso:country":"ME",
    "name:ceb_x_preferred":[
        "Rake"
    ],
    "name:deu_x_preferred":[
        "Rake"
    ],
    "name:fra_x_preferred":[
        "Rake"
    ],
    "name:ita_x_preferred":[
        "Rake"
    ],
    "name:nld_x_preferred":[
        "Rake"
    ],
    "name:pol_x_preferred":[
        "Rake"
    ],
    "name:sco_x_preferred":[
        "Rake"
    ],
    "name:spa_x_preferred":[
        "Rake"
    ],
    "name:srp_x_preferred":[
        "Rake"
    ],
    "name:swe_x_preferred":[
        "Rake"
    ],
    "name:urd_x_preferred":[
        "\u062c\u0631\u0627\u0641\u06c1"
    ],
    "wof:name":"Rake",
    "wof:placetype":"locality"
},
  "geometry": {"coordinates":[18.65,42.45083],"type":"Point"}
}