{
  "type": "Feature",
  "properties": {
    "gn:admin1_code":"4.0",
    "gn:asciiname":"Kicava",
    "gn:country_code":"ME",
    "gn:dem":1023,
    "gn:feature_class":"P",
    "gn:feature_code":"PPLL",
    "gn:name":"Ki\u010dava",
    "gn:population":0,
    "gn:timezone":"Europe/Podgorica",
    "iso:country":"ME",
    "name:fra_x_preferred":[
        "Ki\u010dava"
    ],
    "name:ron_x_preferred":[
        "Ki\u010dava"
    ],
    "name:slv_x_preferred":[
        "Ki\u010dava"
    ],
    "name:srp_x_preferred":[
        "\u041a\u0438\u0447\u0430\u0432\u0430"
    ],
    "name:und_x_variant":[
        "Ki\u010deva",
        "Ki\u010dava"
    ],
    "wof:name":"Kicava",
    "wof:placetype":"locality"
},
  "geometry": {"coordinates":[19.6675,43.16333],"type":"Point"}
}