{
  "type": "Feature",
  "properties": {
    "gn:admin1_code":"13.0",
    "gn:asciiname":"Volujnik",
    "gn:country_code":"ME",
    "gn:dem":1279,
    "gn:feature_class":"P",
    "gn:feature_code":"PPL",
    "gn:name":"Volujnik",
    "gn:population":0,
    "gn:timezone":"Europe/Podgorica",
    "iso:country":"ME",
    "name:srp_x_preferred":[
        "Volujnik"
    ],
    "wof:name":"Volujnik",
    "wof:placetype":"locality"
},
  "geometry": {"coordinates":[19.97972,42.6725],"type":"Point"}
}