{
  "type": "Feature",
  "properties": {
    "gn:admin1_code":"16.0",
    "gn:asciiname":"Malo Slacko",
    "gn:country_code":"ME",
    "gn:dem":1215,
    "gn:feature_class":"P",
    "gn:feature_code":"PPL",
    "gn:name":"Malo Slacko",
    "gn:population":0,
    "gn:timezone":"Europe/Podgorica",
    "iso:country":"ME",
    "name:srp_x_preferred":[
        "Malo Slacko"
    ],
    "wof:name":"Malo Slacko",
    "wof:placetype":"locality"
},
  "geometry": {"coordinates":[19.4575,42.65806],"type":"Point"}
}