{
  "type": "Feature",
  "properties": {
    "gn:admin1_code":"14.0",
    "gn:asciiname":"Vrba",
    "gn:country_code":"ME",
    "gn:dem":1150,
    "gn:feature_class":"P",
    "gn:feature_code":"PPL",
    "gn:name":"Vrba",
    "gn:population":0,
    "gn:timezone":"Europe/Podgorica",
    "iso:country":"ME",
    "name:srp_x_preferred":[
        "Vrba"
    ],
    "wof:name":"Vrba",
    "wof:placetype":"locality"
},
  "geometry": {"coordinates":[19.13306,43.345],"type":"Point"}
}