{
  "type": "Feature",
  "properties": {
    "gn:admin1_code":"16.0",
    "gn:asciiname":"Gornji Markovici",
    "gn:country_code":"ME",
    "gn:dem":467,
    "gn:feature_class":"P",
    "gn:feature_code":"PPL",
    "gn:name":"Gornji Markovi\u0107i",
    "gn:population":0,
    "gn:timezone":"Europe/Podgorica",
    "iso:country":"ME",
    "name:srp_x_preferred":[
        "Gornji Markovi\u0107i"
    ],
    "wof:name":"Gornji Markovici",
    "wof:placetype":"locality"
},
  "geometry": {"coordinates":[19.26528,42.51917],"type":"Point"}
}