{
  "type": "Feature",
  "properties": {
    "gn:admin1_code":"16.0",
    "gn:asciiname":"Kruscica",
    "gn:country_code":"ME",
    "gn:dem":813,
    "gn:feature_class":"P",
    "gn:feature_code":"PPL",
    "gn:name":"Kru\u0161\u010dica",
    "gn:population":0,
    "gn:timezone":"Europe/Podgorica",
    "iso:country":"ME",
    "name:srp_x_preferred":[
        "Kru\u0161\u010dica"
    ],
    "wof:name":"Kruscica",
    "wof:placetype":"locality"
},
  "geometry": {"coordinates":[19.37833,42.45361],"type":"Point"}
}