{
  "type": "Feature",
  "properties": {
    "gn:admin1_code":"7.0",
    "gn:asciiname":"Zagorak",
    "gn:country_code":"ME",
    "gn:dem":119,
    "gn:feature_class":"P",
    "gn:feature_code":"PPLL",
    "gn:name":"Zagorak",
    "gn:population":0,
    "gn:timezone":"Europe/Podgorica",
    "iso:country":"ME",
    "wof:name":"Zagorak",
    "wof:placetype":"locality"
},
  "geometry": {"coordinates":[19.0275,42.61583],"type":"Point"}
}