{
  "type": "Feature",
  "properties": {
    "gn:admin1_code":"14.0",
    "gn:asciiname":"Laniste",
    "gn:country_code":"ME",
    "gn:dem":1333,
    "gn:feature_class":"P",
    "gn:feature_code":"PPL",
    "gn:name":"Lani\u0161te",
    "gn:population":0,
    "gn:timezone":"Europe/Podgorica",
    "iso:country":"ME",
    "name:srp_x_preferred":[
        "Lani\u0161te"
    ],
    "wof:name":"Laniste",
    "wof:placetype":"locality"
},
  "geometry": {"coordinates":[19.39389,43.115],"type":"Point"}
}