{
  "type": "Feature",
  "properties": {
    "gn:admin1_code":"14.0",
    "gn:asciiname":"Ladana",
    "gn:country_code":"ME",
    "gn:dem":1006,
    "gn:feature_class":"P",
    "gn:feature_code":"PPLL",
    "gn:name":"La\u0111ana",
    "gn:population":0,
    "gn:timezone":"Europe/Podgorica",
    "iso:country":"ME",
    "name:und_x_variant":[
        "Ladjana",
        "La\u0111ana"
    ],
    "wof:name":"Ladana",
    "wof:placetype":"locality"
},
  "geometry": {"coordinates":[19.26917000000001,43.30556],"type":"Point"}
}