{
  "type": "Feature",
  "properties": {
    "gn:admin1_code":"14.0",
    "gn:asciiname":"Rosulje",
    "gn:country_code":"ME",
    "gn:dem":829,
    "gn:feature_class":"P",
    "gn:feature_code":"PPL",
    "gn:name":"Rosulje",
    "gn:population":0,
    "gn:timezone":"Europe/Podgorica",
    "iso:country":"ME",
    "name:srp_x_preferred":[
        "Rosulje"
    ],
    "wof:name":"Rosulje",
    "wof:placetype":"locality"
},
  "geometry": {"coordinates":[19.06917,43.44972],"type":"Point"}
}