{
  "type": "Feature",
  "properties": {
    "gn:country":"ME",
    "gn:fcode":"PPLL",
    "gn:pop":194,
    "iso:country":"ME",
    "qs:name":"Rva\u0161i",
    "qs:photos_9r":0,
    "qs:photos_sr":0,
    "qs:pop_sr":"1",
    "wof:name":"Rva\u0161i",
    "wof:placetype":"locality",
    "wof:population":194
},
  "geometry": {"coordinates":[19.08944,42.37139],"type":"Point"}
}