{
  "type": "Feature",
  "properties": {
    "gn:admin1_code":"4.0",
    "gn:asciiname":"Gudure",
    "gn:country_code":"ME",
    "gn:dem":1034,
    "gn:feature_class":"P",
    "gn:feature_code":"PPL",
    "gn:name":"Gudure",
    "gn:population":0,
    "gn:timezone":"Europe/Podgorica",
    "iso:country":"ME",
    "name:srp_x_preferred":[
        "Gudure"
    ],
    "wof:name":"Gudure",
    "wof:placetype":"locality"
},
  "geometry": {"coordinates":[19.67139,43.12944],"type":"Point"}
}