{
  "type": "Feature",
  "properties": {
    "gn:country":"ME",
    "gn:fcode":"PPL",
    "gn:pop":191,
    "iso:country":"ME",
    "qs:name":"Vu\u010dica",
    "qs:photos_9r":0,
    "qs:photos_sr":0,
    "qs:pop_sr":"1",
    "wof:name":"Vu\u010dica",
    "wof:placetype":"locality",
    "wof:population":191
},
  "geometry": {"coordinates":[19.10806,42.575],"type":"Point"}
}