{
  "type": "Feature",
  "properties": {
    "gn:admin1_code":"6.0",
    "gn:asciiname":"Pripor",
    "gn:country_code":"ME",
    "gn:dem":746,
    "gn:feature_class":"P",
    "gn:feature_code":"PPL",
    "gn:name":"Pripor",
    "gn:population":0,
    "gn:timezone":"Europe/Podgorica",
    "iso:country":"ME",
    "wof:name":"Pripor",
    "wof:placetype":"locality"
},
  "geometry": {"coordinates":[18.81833,42.52472],"type":"Point"}
}