{
  "type": "Feature",
  "properties": {
    "gn:admin1_code":"4.0",
    "gn:asciiname":"Pobrnjica",
    "gn:country_code":"ME",
    "gn:dem":782,
    "gn:feature_class":"P",
    "gn:feature_code":"PPL",
    "gn:name":"Pobrnjica",
    "gn:population":0,
    "gn:timezone":"Europe/Podgorica",
    "iso:country":"ME",
    "name:srp_x_preferred":[
        "Pobrnjica"
    ],
    "wof:name":"Pobrnjica",
    "wof:placetype":"locality"
},
  "geometry": {"coordinates":[19.72528,42.98],"type":"Point"}
}