{
  "type": "Feature",
  "properties": {
    "gn:admin1_code":"7.0",
    "gn:asciiname":"Lubovo",
    "gn:country_code":"ME",
    "gn:dem":263,
    "gn:feature_class":"P",
    "gn:feature_code":"PPL",
    "gn:name":"Lubovo",
    "gn:population":0,
    "gn:timezone":"Europe/Podgorica",
    "iso:country":"ME",
    "name:srp_x_preferred":[
        "Lubovo"
    ],
    "wof:name":"Lubovo",
    "wof:placetype":"locality"
},
  "geometry": {"coordinates":[19.12611,42.58583],"type":"Point"}
}