{
  "type": "Feature",
  "properties": {
    "gn:admin1_code":"12.0",
    "gn:asciiname":"Klicevo",
    "gn:country_code":"ME",
    "gn:dem":623,
    "gn:feature_class":"P",
    "gn:feature_code":"PPL",
    "gn:name":"Kli\u010devo",
    "gn:population":0,
    "gn:timezone":"Europe/Podgorica",
    "iso:country":"ME",
    "name:srp_x_preferred":[
        "Kli\u010devo"
    ],
    "wof:name":"Klicevo",
    "wof:placetype":"locality"
},
  "geometry": {"coordinates":[18.96028,42.75028],"type":"Point"}
}