{
  "type": "Feature",
  "properties": {
    "gn:admin1_code":"9.0",
    "gn:asciiname":"Manicevo",
    "gn:country_code":"ME",
    "gn:dem":949,
    "gn:feature_class":"P",
    "gn:feature_code":"PPL",
    "gn:name":"Mani\u010devo",
    "gn:population":0,
    "gn:timezone":"Europe/Podgorica",
    "iso:country":"ME",
    "name:srp_x_preferred":[
        "Mani\u010devo"
    ],
    "wof:name":"Manicevo",
    "wof:placetype":"locality"
},
  "geometry": {"coordinates":[19.32917,42.67917],"type":"Point"}
}