{
  "type": "Feature",
  "properties": {
    "gn:admin1_code":"16.0",
    "gn:asciiname":"Celj",
    "gn:country_code":"ME",
    "gn:dem":106,
    "gn:feature_class":"P",
    "gn:feature_code":"PPL",
    "gn:name":"\u010celj",
    "gn:population":0,
    "gn:timezone":"Europe/Podgorica",
    "iso:country":"ME",
    "name:srp_x_preferred":[
        "\u010celj"
    ],
    "wof:name":"Celj",
    "wof:placetype":"locality"
},
  "geometry": {"coordinates":[19.34944,42.52],"type":"Point"}
}