{
  "type": "Feature",
  "properties": {
    "gn:admin1_code":"9.0",
    "gn:asciiname":"Paljevine",
    "gn:country_code":"ME",
    "gn:dem":1399,
    "gn:feature_class":"P",
    "gn:feature_code":"PPL",
    "gn:name":"Paljevine",
    "gn:population":0,
    "gn:timezone":"Europe/Podgorica",
    "iso:country":"ME",
    "name:srp_x_preferred":[
        "Paljevine"
    ],
    "wof:name":"Paljevine",
    "wof:placetype":"locality"
},
  "geometry": {"coordinates":[19.62167,42.83167],"type":"Point"}
}