{
  "type": "Feature",
  "properties": {
    "gn:admin1_code":"20.0",
    "gn:asciiname":"Selita",
    "gn:country_code":"ME",
    "gn:dem":32,
    "gn:feature_class":"P",
    "gn:feature_code":"PPL",
    "gn:name":"Selita",
    "gn:population":0,
    "gn:timezone":"Europe/Podgorica",
    "iso:country":"ME",
    "name:srp_x_preferred":[
        "Selita"
    ],
    "wof:name":"Selita",
    "wof:placetype":"locality"
},
  "geometry": {"coordinates":[19.32694,42.00389000000001],"type":"Point"}
}