{
  "type": "Feature",
  "properties": {
    "gn:admin1_code":"14.0",
    "gn:asciiname":"Dragasi",
    "gn:country_code":"ME",
    "gn:dem":1102,
    "gn:feature_class":"P",
    "gn:feature_code":"PPL",
    "gn:name":"Draga\u0161i",
    "gn:population":0,
    "gn:timezone":"Europe/Podgorica",
    "iso:country":"ME",
    "name:srp_x_preferred":[
        "Draga\u0161i"
    ],
    "wof:name":"Dragasi",
    "wof:placetype":"locality"
},
  "geometry": {"coordinates":[19.25389,43.26639],"type":"Point"}
}