{
  "type": "Feature",
  "properties": {
    "gn:admin1_code":"4.0",
    "gn:asciiname":"Pozeginja",
    "gn:country_code":"ME",
    "gn:dem":1142,
    "gn:feature_class":"P",
    "gn:feature_code":"PPL",
    "gn:name":"Po\u017eeginja",
    "gn:population":0,
    "gn:timezone":"Europe/Podgorica",
    "iso:country":"ME",
    "name:fra_x_preferred":[
        "Po\u017eeginja"
    ],
    "name:ron_x_preferred":[
        "Po\u017eeginja"
    ],
    "name:slv_x_preferred":[
        "Po\u017eeginja"
    ],
    "name:srp_x_preferred":[
        "\u041f\u043e\u0436\u0435\u0433\u0438\u045a\u0430"
    ],
    "name:und_x_variant":[
        "Po\u017eeginje",
        "Po\u017eeginja"
    ],
    "wof:name":"Pozeginja",
    "wof:placetype":"locality"
},
  "geometry": {"coordinates":[19.87139,43.10222],"type":"Point"}
}