{
  "type": "Feature",
  "properties": {
    "gn:admin1_code":"6.0",
    "gn:asciiname":"Predojevica",
    "gn:country_code":"ME",
    "gn:dem":620,
    "gn:feature_class":"P",
    "gn:feature_code":"PPL",
    "gn:name":"Predojevica",
    "gn:population":0,
    "gn:timezone":"Europe/Podgorica",
    "iso:country":"ME",
    "name:srp_x_preferred":[
        "Predojevica"
    ],
    "wof:name":"Predojevica",
    "wof:placetype":"locality"
},
  "geometry": {"coordinates":[18.99167000000001,42.43972],"type":"Point"}
}