{
  "type": "Feature",
  "properties": {
    "gn:admin1_code":"12.0",
    "gn:asciiname":"Dragovoljici",
    "gn:country_code":"ME",
    "gn:dem":942,
    "gn:feature_class":"P",
    "gn:feature_code":"PPLL",
    "gn:name":"Dragovolji\u0107i",
    "gn:population":0,
    "gn:timezone":"Europe/Podgorica",
    "iso:country":"ME",
    "name:und_x_variant":[
        "Dobrovolji\u0107i",
        "Dragovolji\u0107i"
    ],
    "wof:name":"Dragovoljici",
    "wof:placetype":"locality"
},
  "geometry": {"coordinates":[19.0525,42.78167],"type":"Point"}
}