{
  "type": "Feature",
  "properties": {
    "gn:admin1_code":"12.0",
    "gn:asciiname":"Pisteta",
    "gn:country_code":"ME",
    "gn:dem":858,
    "gn:feature_class":"P",
    "gn:feature_code":"PPL",
    "gn:name":"Pi\u0161teta",
    "gn:population":0,
    "gn:timezone":"Europe/Podgorica",
    "iso:country":"ME",
    "name:srp_x_preferred":[
        "Pi\u0161teta"
    ],
    "wof:name":"Pisteta",
    "wof:placetype":"locality"
},
  "geometry": {"coordinates":[18.90944,42.895],"type":"Point"}
}