{
  "type": "Feature",
  "properties": {
    "gn:admin1_code":"18.0",
    "gn:asciiname":"Kosice",
    "gn:country_code":"ME",
    "gn:dem":1211,
    "gn:feature_class":"P",
    "gn:feature_code":"PPL",
    "gn:name":"Ko\u0161ice",
    "gn:population":0,
    "gn:timezone":"Europe/Podgorica",
    "iso:country":"ME",
    "name:ceb_x_preferred":[
        "Kosice"
    ],
    "name:ces_x_preferred":[
        "Ko\u0161ice"
    ],
    "name:deu_x_preferred":[
        "Ko\u0161ice"
    ],
    "name:epo_x_preferred":[
        "Ko\u0161ice"
    ],
    "name:fra_x_preferred":[
        "Kosice"
    ],
    "name:ita_x_preferred":[
        "Ko\u0161ice"
    ],
    "name:nld_x_preferred":[
        "Kosice"
    ],
    "name:pol_x_preferred":[
        "Kosice"
    ],
    "name:ron_x_preferred":[
        "Districtul Ko\u0161ice"
    ],
    "name:rus_x_preferred":[
        "\u041a\u043e\u0448\u0438\u0446\u0435"
    ],
    "name:slk_x_preferred":[
        "Kosice"
    ],
    "name:spa_x_preferred":[
        "Kosice"
    ],
    "name:srp_x_preferred":[
        "Ko\u0161ice"
    ],
    "name:swe_x_preferred":[
        "Kosice"
    ],
    "name:ukr_x_preferred":[
        "\u041a\u043e\u0448\u0438\u0446\u0435"
    ],
    "wof:name":"Kosice",
    "wof:placetype":"locality"
},
  "geometry": {"coordinates":[19.0075,43.00472],"type":"Point"}
}