{
  "type": "Feature",
  "properties": {
    "gn:admin1_code":"12.0",
    "gn:asciiname":"Biteljica",
    "gn:country_code":"ME",
    "gn:dem":1162,
    "gn:feature_class":"P",
    "gn:feature_code":"PPLL",
    "gn:name":"Biteljica",
    "gn:population":0,
    "gn:timezone":"Europe/Podgorica",
    "iso:country":"ME",
    "name:und_x_variant":[
        "Bitelica",
        "Biteljica"
    ],
    "wof:name":"Biteljica",
    "wof:placetype":"locality"
},
  "geometry": {"coordinates":[18.53167,43.01917],"type":"Point"}
}