{
  "type": "Feature",
  "properties": {
    "gn:admin1_code":"8.0",
    "gn:asciiname":"Marici",
    "gn:country_code":"ME",
    "gn:dem":26,
    "gn:feature_class":"P",
    "gn:feature_code":"PPL",
    "gn:name":"Mari\u0107i",
    "gn:population":0,
    "gn:timezone":"Europe/Podgorica",
    "iso:country":"ME",
    "name:srp_x_preferred":[
        "Mari\u0107i"
    ],
    "wof:name":"Marici",
    "wof:placetype":"locality"
},
  "geometry": {"coordinates":[18.58389,42.46472],"type":"Point"}
}