{
  "type": "Feature",
  "properties": {
    "gn:admin1_code":"12.0",
    "gn:asciiname":"Janjiliste",
    "gn:country_code":"ME",
    "gn:dem":1194,
    "gn:feature_class":"P",
    "gn:feature_code":"PPL",
    "gn:name":"Janjili\u0161te",
    "gn:population":0,
    "gn:timezone":"Europe/Podgorica",
    "iso:country":"ME",
    "name:srp_x_preferred":[
        "Janjili\u0161te"
    ],
    "wof:name":"Janjiliste",
    "wof:placetype":"locality"
},
  "geometry": {"coordinates":[18.59556,42.96],"type":"Point"}
}