{
  "type": "Feature",
  "properties": {
    "gn:admin1_code":"14.0",
    "gn:asciiname":"Sarancici",
    "gn:country_code":"ME",
    "gn:dem":1006,
    "gn:feature_class":"P",
    "gn:feature_code":"PPL",
    "gn:name":"\u0160aran\u010di\u0107i",
    "gn:population":0,
    "gn:timezone":"Europe/Podgorica",
    "iso:country":"ME",
    "name:srp_x_preferred":[
        "\u0160aran\u010di\u0107i"
    ],
    "wof:name":"Sarancici",
    "wof:placetype":"locality"
},
  "geometry": {"coordinates":[19.42056,43.33056],"type":"Point"}
}