{
  "type": "Feature",
  "properties": {
    "gn:admin1_code":"6.0",
    "gn:asciiname":"Izvori",
    "gn:country_code":"ME",
    "gn:dem":862,
    "gn:feature_class":"P",
    "gn:feature_code":"PPLL",
    "gn:name":"Izvori",
    "gn:population":0,
    "gn:timezone":"Europe/Podgorica",
    "iso:country":"ME",
    "wof:name":"Izvori",
    "wof:placetype":"locality"
},
  "geometry": {"coordinates":[18.77083,42.60639000000001],"type":"Point"}
}