{
  "type": "Feature",
  "properties": {
    "gn:admin1_code":"12.0",
    "gn:asciiname":"Zovaca",
    "gn:country_code":"ME",
    "gn:dem":835,
    "gn:feature_class":"P",
    "gn:feature_code":"PPL",
    "gn:name":"Zova\u010da",
    "gn:population":0,
    "gn:timezone":"Europe/Podgorica",
    "iso:country":"ME",
    "name:srp_x_preferred":[
        "Zova\u010da"
    ],
    "wof:name":"Zovaca",
    "wof:placetype":"locality"
},
  "geometry": {"coordinates":[19.06806,42.76361],"type":"Point"}
}