{
  "type": "Feature",
  "properties": {
    "gn:admin1_code":"17.0",
    "gn:asciiname":"Honcice",
    "gn:country_code":"ME",
    "gn:dem":1361,
    "gn:feature_class":"P",
    "gn:feature_code":"PPL",
    "gn:name":"Honci\u0107e",
    "gn:population":0,
    "gn:timezone":"Europe/Podgorica",
    "iso:country":"ME",
    "name:und_x_variant":[
        "Hondi\u0107e",
        "Honsi\u0107e",
        "Honci\u0107e"
    ],
    "wof:name":"Honcice",
    "wof:placetype":"locality"
},
  "geometry": {"coordinates":[20.10389,42.87722],"type":"Point"}
}