{
  "type": "Feature",
  "properties": {
    "gn:admin1_code":"7.0",
    "gn:asciiname":"Petrici",
    "gn:country_code":"ME",
    "gn:dem":202,
    "gn:feature_class":"P",
    "gn:feature_code":"PPL",
    "gn:name":"Petri\u0107i",
    "gn:population":0,
    "gn:timezone":"Europe/Podgorica",
    "iso:country":"ME",
    "name:srp_x_preferred":[
        "Petri\u0107i"
    ],
    "wof:name":"Petrici",
    "wof:placetype":"locality"
},
  "geometry": {"coordinates":[19.06028,42.62389],"type":"Point"}
}