{
  "type": "Feature",
  "properties": {
    "gn:admin1_code":"9.0",
    "gn:asciiname":"Krusev Lug",
    "gn:country_code":"ME",
    "gn:dem":631,
    "gn:feature_class":"P",
    "gn:feature_code":"PPL",
    "gn:name":"Kru\u0161ev Lug",
    "gn:population":0,
    "gn:timezone":"Europe/Podgorica",
    "iso:country":"ME",
    "name:srp_x_preferred":[
        "Kru\u0161ev Lug"
    ],
    "wof:name":"Krusev Lug",
    "wof:placetype":"locality"
},
  "geometry": {"coordinates":[19.31917,42.84833],"type":"Point"}
}