{
  "type": "Feature",
  "properties": {
    "gn:admin1_code":"6.0",
    "gn:asciiname":"Velestovo",
    "gn:country_code":"ME",
    "gn:dem":819,
    "gn:feature_class":"P",
    "gn:feature_code":"PPLL",
    "gn:name":"Velestovo",
    "gn:population":0,
    "gn:timezone":"Europe/Podgorica",
    "iso:country":"ME",
    "name:fra_x_preferred":[
        "Velestovo"
    ],
    "name:ron_x_preferred":[
        "Velestovo"
    ],
    "name:slv_x_preferred":[
        "Velestovo"
    ],
    "name:srp_x_preferred":[
        "\u0412\u0435\u043b\u0435\u0441\u0442\u043e\u0432\u043e"
    ],
    "wof:name":"Velestovo",
    "wof:placetype":"locality"
},
  "geometry": {"coordinates":[18.96472,42.52583],"type":"Point"}
}