{
  "type": "Feature",
  "properties": {
    "gn:admin1_code":"12.0",
    "gn:asciiname":"Donje Kunovo",
    "gn:country_code":"ME",
    "gn:dem":757,
    "gn:feature_class":"P",
    "gn:feature_code":"PPL",
    "gn:name":"Donje Kunovo",
    "gn:population":0,
    "gn:timezone":"Europe/Podgorica",
    "iso:country":"ME",
    "name:srp_x_preferred":[
        "Donje Kunovo"
    ],
    "wof:name":"Donje Kunovo",
    "wof:placetype":"locality"
},
  "geometry": {"coordinates":[19.01889,42.78639],"type":"Point"}
}