{
  "type": "Feature",
  "properties": {
    "gn:admin1_code":"17.0",
    "gn:asciiname":"Rijeka",
    "gn:country_code":"ME",
    "gn:dem":1206,
    "gn:feature_class":"P",
    "gn:feature_code":"PPL",
    "gn:name":"Rijeka",
    "gn:population":0,
    "gn:timezone":"Europe/Podgorica",
    "iso:country":"ME",
    "wof:name":"Rijeka",
    "wof:placetype":"locality"
},
  "geometry": {"coordinates":[20.16028,42.9625],"type":"Point"}
}