{
  "type": "Feature",
  "properties": {
    "gn:country":"ME",
    "gn:fcode":"PPL",
    "gn:pop":5,
    "iso:country":"ME",
    "name:srp_x_preferred":[
        "Maru\u010di\u0107i"
    ],
    "qs:name":"Maru\u010di\u0107i",
    "qs:photos_9r":0,
    "qs:photos_sr":0,
    "qs:pop_sr":"1",
    "wof:name":"Maru\u010di\u0107i",
    "wof:placetype":"locality",
    "wof:population":5
},
  "geometry": {"coordinates":[19.15278,42.17472],"type":"Point"}
}