{
  "type": "Feature",
  "properties": {
    "gn:admin1_code":"12.0",
    "gn:asciiname":"Brocanac Niksicki",
    "gn:country_code":"ME",
    "gn:dem":731,
    "gn:feature_class":"P",
    "gn:feature_code":"PPLL",
    "gn:name":"Bro\u0107anac Nik\u0161i\u0107ki",
    "gn:population":0,
    "gn:timezone":"Europe/Podgorica",
    "iso:country":"ME",
    "name:und_x_variant":[
        "Bro\u0107anac",
        "Bro\u0107anac Nik\u0161i\u0107ki"
    ],
    "wof:name":"Brocanac Niksicki",
    "wof:placetype":"locality"
},
  "geometry": {"coordinates":[18.85472,42.73],"type":"Point"}
}