{
  "type": "Feature",
  "properties": {
    "gn:admin1_code":"12.0",
    "gn:asciiname":"Rubezi",
    "gn:country_code":"ME",
    "gn:dem":675,
    "gn:feature_class":"P",
    "gn:feature_code":"PPL",
    "gn:name":"Rube\u017ei",
    "gn:population":0,
    "gn:timezone":"Europe/Podgorica",
    "iso:country":"ME",
    "name:und_x_variant":[
        "Rube\u017ea",
        "Rube\u017ei"
    ],
    "wof:name":"Rubezi",
    "wof:placetype":"locality"
},
  "geometry": {"coordinates":[18.99472,42.7775],"type":"Point"}
}