{
  "type": "Feature",
  "properties": {
    "gn:admin1_code":"7.0",
    "gn:asciiname":"Kosuci Do",
    "gn:country_code":"ME",
    "gn:dem":918,
    "gn:feature_class":"P",
    "gn:feature_code":"PPL",
    "gn:name":"Ko\u0161u\u0107i Do",
    "gn:population":0,
    "gn:timezone":"Europe/Podgorica",
    "iso:country":"ME",
    "name:srp_x_preferred":[
        "Ko\u0161u\u0107i Do"
    ],
    "wof:name":"Kosuci Do",
    "wof:placetype":"locality"
},
  "geometry": {"coordinates":[19.23472000000001,42.59111],"type":"Point"}
}