{
  "type": "Feature",
  "properties": {
    "gn:admin1_code":"9.0",
    "gn:asciiname":"Rijeka",
    "gn:country_code":"ME",
    "gn:dem":325,
    "gn:feature_class":"P",
    "gn:feature_code":"PPL",
    "gn:name":"Rijeka",
    "gn:population":0,
    "gn:timezone":"Europe/Podgorica",
    "iso:country":"ME",
    "name:srp_x_preferred":[
        "Rijeka"
    ],
    "wof:name":"Rijeka",
    "wof:placetype":"locality"
},
  "geometry": {"coordinates":[19.42111,42.71],"type":"Point"}
}