{
  "type": "Feature",
  "properties": {
    "gn:admin1_code":"12.0",
    "gn:asciiname":"Klacina",
    "gn:country_code":"ME",
    "gn:dem":1200,
    "gn:feature_class":"P",
    "gn:feature_code":"PPL",
    "gn:name":"Kla\u010dina",
    "gn:population":0,
    "gn:timezone":"Europe/Podgorica",
    "iso:country":"ME",
    "name:srp_x_preferred":[
        "Kla\u010dina"
    ],
    "wof:name":"Klacina",
    "wof:placetype":"locality"
},
  "geometry": {"coordinates":[18.67028,43.07611],"type":"Point"}
}