{
  "type": "Feature",
  "properties": {
    "gn:admin1_code":"6.0",
    "gn:asciiname":"Vrbica",
    "gn:country_code":"ME",
    "gn:dem":728,
    "gn:feature_class":"P",
    "gn:feature_code":"PPL",
    "gn:name":"Vrbica",
    "gn:population":0,
    "gn:timezone":"Europe/Podgorica",
    "iso:country":"ME",
    "name:srp_x_preferred":[
        "Vrbica"
    ],
    "wof:name":"Vrbica",
    "wof:placetype":"locality"
},
  "geometry": {"coordinates":[18.92028,42.40556],"type":"Point"}
}