{
  "type": "Feature",
  "properties": {
    "gn:admin1_code":"14.0",
    "gn:asciiname":"Borislavljevica",
    "gn:country_code":"ME",
    "gn:dem":1384,
    "gn:feature_class":"P",
    "gn:feature_code":"PPL",
    "gn:name":"Borislavljevica",
    "gn:population":0,
    "gn:timezone":"Europe/Podgorica",
    "iso:country":"ME",
    "wof:name":"Borislavljevica",
    "wof:placetype":"locality"
},
  "geometry": {"coordinates":[19.41278,43.10667],"type":"Point"}
}