{
  "type": "Feature",
  "properties": {
    "gn:admin1_code":"9.0",
    "gn:asciiname":"Donje Velje Duboko",
    "gn:country_code":"ME",
    "gn:dem":848,
    "gn:feature_class":"P",
    "gn:feature_code":"PPL",
    "gn:name":"Donje Velje Duboko",
    "gn:population":0,
    "gn:timezone":"Europe/Podgorica",
    "iso:country":"ME",
    "name:srp_x_preferred":[
        "Donje Velje Duboko"
    ],
    "wof:name":"Donje Velje Duboko",
    "wof:placetype":"locality"
},
  "geometry": {"coordinates":[19.27722,42.78028],"type":"Point"}
}