{
  "type": "Feature",
  "properties": {
    "gn:country":"ME",
    "gn:fcode":"PPLL",
    "gn:population":230,
    "iso:country":"ME",
    "name:und_x_variant":[
        "Seli\u0161te"
    ],
    "qs:name":"Seli\u0161ta",
    "qs:photos_9r":0,
    "qs:photos_sr":0,
    "qs:pop_sr":"2",
    "wof:name":"Seli\u0161ta",
    "wof:placetype":"locality",
    "wof:population":230
},
  "geometry": {"coordinates":[19.49139,42.73472],"type":"Point"}
}