{
  "type": "Feature",
  "properties": {
    "gn:admin1_code":"14.0",
    "gn:asciiname":"Gornji Dubac",
    "gn:country_code":"ME",
    "gn:dem":1149,
    "gn:feature_class":"P",
    "gn:feature_code":"PPL",
    "gn:name":"Gornji Dubac",
    "gn:population":0,
    "gn:timezone":"Europe/Podgorica",
    "iso:country":"ME",
    "name:ceb_x_preferred":[
        "Gornji Dubac"
    ],
    "name:fra_x_preferred":[
        "Gornji Dubac"
    ],
    "name:msa_x_preferred":[
        "Gornji Dubac"
    ],
    "name:por_x_preferred":[
        "Gornji Dubac"
    ],
    "name:slv_x_preferred":[
        "Gornji Dubac"
    ],
    "name:srp_x_preferred":[
        "Gornji Dubac"
    ],
    "name:srp_x_variant":[
        "\u0413\u043e\u0440\u045a\u0438 \u0414\u0443\u0431\u0430\u0446"
    ],
    "wof:name":"Gornji Dubac",
    "wof:placetype":"locality"
},
  "geometry": {"coordinates":[19.11389,43.47833],"type":"Point"}
}