{
  "type": "Feature",
  "properties": {
    "gn:admin1_code":"14.0",
    "gn:asciiname":"Gornji Dubac",
    "gn:country_code":"ME",
    "gn:dem":1149,
    "gn:feature_class":"P",
    "gn:feature_code":"PPL",
    "gn:name":"Gornji Dubac",
    "gn:population":0,
    "gn:timezone":"Europe/Podgorica",
    "iso:country":"ME",
    "name:srp_x_preferred":[
        "Gornji Dubac"
    ],
    "wof:name":"Gornji Dubac",
    "wof:placetype":"locality"
},
  "geometry": {"coordinates":[19.11389,43.47833],"type":"Point"}
}