{
  "type": "Feature",
  "properties": {
    "gn:admin1_code":"18.0",
    "gn:asciiname":"Lazine",
    "gn:country_code":"ME",
    "gn:dem":1447,
    "gn:feature_class":"P",
    "gn:feature_code":"PPL",
    "gn:name":"La\u017eine",
    "gn:population":0,
    "gn:timezone":"Europe/Podgorica",
    "iso:country":"ME",
    "wof:name":"Lazine",
    "wof:placetype":"locality"
},
  "geometry": {"coordinates":[19.13444,43.02333],"type":"Point"}
}