{
  "type": "Feature",
  "properties": {
    "gn:admin1_code":"16.0",
    "gn:asciiname":"Radovac",
    "gn:country_code":"ME",
    "gn:dem":823,
    "gn:feature_class":"P",
    "gn:feature_code":"PPL",
    "gn:name":"Radovac",
    "gn:population":0,
    "gn:timezone":"Europe/Podgorica",
    "iso:country":"ME",
    "name:srp_x_preferred":[
        "Radovac"
    ],
    "wof:name":"Radovac",
    "wof:placetype":"locality"
},
  "geometry": {"coordinates":[19.41611,42.46],"type":"Point"}
}