{
  "type": "Feature",
  "properties": {
    "gn:admin1_code":"12.0",
    "gn:asciiname":"Dubrave",
    "gn:country_code":"ME",
    "gn:dem":1044,
    "gn:feature_class":"P",
    "gn:feature_code":"PPL",
    "gn:name":"Dubrave",
    "gn:population":0,
    "gn:timezone":"Europe/Podgorica",
    "iso:country":"ME",
    "name:bos_x_preferred":[
        "Dubrave"
    ],
    "name:ceb_x_preferred":[
        "Dubrave"
    ],
    "name:fra_x_preferred":[
        "Dubrave"
    ],
    "name:hrv_x_preferred":[
        "Dubrave"
    ],
    "name:hun_x_preferred":[
        "Dubrave"
    ],
    "name:nld_x_preferred":[
        "Dubrave"
    ],
    "name:rus_x_preferred":[
        "\u0414\u0443\u0431\u0440\u0430\u0432\u0435"
    ],
    "name:slv_x_preferred":[
        "Dubrave"
    ],
    "name:srp_x_preferred":[
        "Dubrave"
    ],
    "name:srp_x_variant":[
        "\u0414\u0443\u0431\u0440\u0430\u0432\u0435"
    ],
    "name:swe_x_preferred":[
        "Dubrave"
    ],
    "name:ukr_x_preferred":[
        "\u0414\u0443\u0431\u0440\u0430\u0432\u0435"
    ],
    "wof:name":"Dubrave",
    "wof:placetype":"locality"
},
  "geometry": {"coordinates":[18.93972,42.88889],"type":"Point"}
}