{
  "type": "Feature",
  "properties": {
    "gn:admin1_code":"12.0",
    "gn:asciiname":"Dubrave",
    "gn:country_code":"ME",
    "gn:dem":1044,
    "gn:feature_class":"P",
    "gn:feature_code":"PPL",
    "gn:name":"Dubrave",
    "gn:population":0,
    "gn:timezone":"Europe/Podgorica",
    "iso:country":"ME",
    "name:srp_x_preferred":[
        "Dubrave"
    ],
    "wof:name":"Dubrave",
    "wof:placetype":"locality"
},
  "geometry": {"coordinates":[18.93972,42.88889],"type":"Point"}
}