{
  "type": "Feature",
  "properties": {
    "gn:admin1_code":"14.0",
    "gn:asciiname":"Krst",
    "gn:country_code":"ME",
    "gn:dem":1191,
    "gn:feature_class":"P",
    "gn:feature_code":"PPL",
    "gn:name":"Krst",
    "gn:population":0,
    "gn:timezone":"Europe/Podgorica",
    "iso:country":"ME",
    "name:srp_x_preferred":[
        "Krst"
    ],
    "wof:name":"Krst",
    "wof:placetype":"locality"
},
  "geometry": {"coordinates":[19.20056,43.47028],"type":"Point"}
}