{
  "type": "Feature",
  "properties": {
    "gn:admin1_code":"15.0",
    "gn:asciiname":"Gornje Krusevo",
    "gn:country_code":"ME",
    "gn:dem":521,
    "gn:feature_class":"P",
    "gn:feature_code":"PPL",
    "gn:name":"Gornje Kru\u0161evo",
    "gn:population":0,
    "gn:timezone":"Europe/Podgorica",
    "iso:country":"ME",
    "name:srp_x_preferred":[
        "Gornje Kru\u0161evo"
    ],
    "wof:name":"Gornje Krusevo",
    "wof:placetype":"locality"
},
  "geometry": {"coordinates":[18.85417,43.31917],"type":"Point"}
}