{
  "type": "Feature",
  "properties": {
    "gn:admin1_code":"2.0",
    "gn:asciiname":"Krute",
    "gn:country_code":"ME",
    "gn:dem":154,
    "gn:feature_class":"P",
    "gn:feature_code":"PPLL",
    "gn:name":"Krute",
    "gn:population":0,
    "gn:timezone":"Europe/Podgorica",
    "iso:country":"ME",
    "name:fra_x_preferred":[
        "Krute"
    ],
    "name:ron_x_preferred":[
        "Krute"
    ],
    "name:slv_x_preferred":[
        "Krute"
    ],
    "name:sqi_x_preferred":[
        "Krytha"
    ],
    "name:srp_x_preferred":[
        "\u041a\u0440\u0443\u0442\u0435"
    ],
    "name:ukr_x_preferred":[
        "\u041a\u0440\u0443\u0442\u0435"
    ],
    "wof:name":"Krute",
    "wof:placetype":"locality"
},
  "geometry": {"coordinates":[19.25194,42.01694000000001],"type":"Point"}
}