{
  "type": "Feature",
  "properties": {
    "gn:admin1_code":"19.0",
    "gn:asciiname":"Radovici",
    "gn:country_code":"ME",
    "gn:dem":71,
    "gn:feature_class":"P",
    "gn:feature_code":"PPL",
    "gn:name":"Radovi\u0107i",
    "gn:population":0,
    "gn:timezone":"Europe/Podgorica",
    "iso:country":"ME",
    "name:und_x_variant":[
        "Radovi\u0107",
        "Radovi\u0107i"
    ],
    "wof:name":"Radovici",
    "wof:placetype":"locality"
},
  "geometry": {"coordinates":[18.67034,42.39328],"type":"Point"}
}