{
  "type": "Feature",
  "properties": {
    "gn:admin1_code":"14.0",
    "gn:asciiname":"Gornje Mrcevo",
    "gn:country_code":"ME",
    "gn:dem":998,
    "gn:feature_class":"P",
    "gn:feature_code":"PPL",
    "gn:name":"Gornje Mr\u010devo",
    "gn:population":0,
    "gn:timezone":"Europe/Podgorica",
    "iso:country":"ME",
    "wof:name":"Gornje Mrcevo",
    "wof:placetype":"locality"
},
  "geometry": {"coordinates":[19.12389,43.42056],"type":"Point"}
}