{
  "type": "Feature",
  "properties": {
    "gn:admin1_code":"4.0",
    "gn:asciiname":"Sutivan",
    "gn:country_code":"ME",
    "gn:dem":554,
    "gn:feature_class":"P",
    "gn:feature_code":"PPL",
    "gn:name":"Sutivan",
    "gn:population":0,
    "gn:timezone":"Europe/Podgorica",
    "iso:country":"ME",
    "name:bos_x_preferred":[
        "Sutivan"
    ],
    "name:cat_x_preferred":[
        "Sutivan"
    ],
    "name:ceb_x_preferred":[
        "Sutivan"
    ],
    "name:ces_x_preferred":[
        "Sutivan"
    ],
    "name:fra_x_preferred":[
        "Sutivan"
    ],
    "name:hrv_x_preferred":[
        "Sutivan"
    ],
    "name:hun_x_preferred":[
        "Sutivan"
    ],
    "name:nld_x_preferred":[
        "Sutivan"
    ],
    "name:pol_x_preferred":[
        "Gmina Sutivan"
    ],
    "name:ron_x_preferred":[
        "Comuna Sutivan"
    ],
    "name:slk_x_preferred":[
        "Sutivan"
    ],
    "name:slv_x_preferred":[
        "Sutivan"
    ],
    "name:srp_x_preferred":[
        "Sutivan"
    ],
    "name:srp_x_variant":[
        "\u0421\u0443\u0442\u0438\u0432\u0430\u043d"
    ],
    "name:swe_x_preferred":[
        "Sutivan"
    ],
    "name:ukr_x_preferred":[
        "\u0421\u0443\u0442\u0438\u0432\u0430\u043d"
    ],
    "name:war_x_preferred":[
        "Sutivan"
    ],
    "wof:name":"Sutivan",
    "wof:placetype":"locality"
},
  "geometry": {"coordinates":[19.77111,43.09278],"type":"Point"}
}