{
  "type": "Feature",
  "properties": {
    "gn:admin1_code":"4.0",
    "gn:asciiname":"Sutivan",
    "gn:country_code":"ME",
    "gn:dem":554,
    "gn:feature_class":"P",
    "gn:feature_code":"PPL",
    "gn:name":"Sutivan",
    "gn:population":0,
    "gn:timezone":"Europe/Podgorica",
    "iso:country":"ME",
    "name:srp_x_preferred":[
        "Sutivan"
    ],
    "wof:name":"Sutivan",
    "wof:placetype":"locality"
},
  "geometry": {"coordinates":[19.77111,43.09278],"type":"Point"}
}