{
  "type": "Feature",
  "properties": {
    "gn:admin1_code":"9.0",
    "gn:asciiname":"Dobri Lug",
    "gn:country_code":"ME",
    "gn:dem":211,
    "gn:feature_class":"P",
    "gn:feature_code":"PPL",
    "gn:name":"Dobri Lug",
    "gn:population":0,
    "gn:timezone":"Europe/Podgorica",
    "iso:country":"ME",
    "name:srp_x_preferred":[
        "Dobri Lug"
    ],
    "wof:name":"Dobri Lug",
    "wof:placetype":"locality"
},
  "geometry": {"coordinates":[19.39139,42.71111],"type":"Point"}
}