{
  "type": "Feature",
  "properties": {
    "gn:admin1_code":"10.0",
    "gn:asciiname":"Granica",
    "gn:country_code":"ME",
    "gn:dem":671,
    "gn:feature_class":"P",
    "gn:feature_code":"PPL",
    "gn:name":"Granica",
    "gn:population":0,
    "gn:timezone":"Europe/Podgorica",
    "iso:country":"ME",
    "name:srp_x_preferred":[
        "Granica"
    ],
    "wof:name":"Granica",
    "wof:placetype":"locality"
},
  "geometry": {"coordinates":[18.68889,42.57194000000001],"type":"Point"}
}