{
  "type": "Feature",
  "properties": {
    "gn:admin1_code":"9.0",
    "gn:asciiname":"Melaja",
    "gn:country_code":"ME",
    "gn:dem":1595,
    "gn:feature_class":"P",
    "gn:feature_code":"PPL",
    "gn:name":"Melaja",
    "gn:population":0,
    "gn:timezone":"Europe/Podgorica",
    "iso:country":"ME",
    "name:srp_x_preferred":[
        "Melaja"
    ],
    "wof:name":"Melaja",
    "wof:placetype":"locality"
},
  "geometry": {"coordinates":[19.59667,42.86194],"type":"Point"}
}