{
  "type": "Feature",
  "properties": {
    "gn:admin1_code":"12.0",
    "gn:asciiname":"Gostojevici",
    "gn:country_code":"ME",
    "gn:dem":411,
    "gn:feature_class":"P",
    "gn:feature_code":"PPL",
    "gn:name":"Gostojevi\u0107i",
    "gn:population":0,
    "gn:timezone":"Europe/Podgorica",
    "iso:country":"ME",
    "name:srp_x_preferred":[
        "Gostojevi\u0107i"
    ],
    "wof:name":"Gostojevici",
    "wof:placetype":"locality"
},
  "geometry": {"coordinates":[18.97222,42.685],"type":"Point"}
}