{
  "type": "Feature",
  "properties": {
    "gn:admin1_code":"14.0",
    "gn:asciiname":"Vodno",
    "gn:country_code":"ME",
    "gn:dem":1184,
    "gn:feature_class":"P",
    "gn:feature_code":"PPL",
    "gn:name":"Vodno",
    "gn:population":0,
    "gn:timezone":"Europe/Podgorica",
    "iso:country":"ME",
    "name:srp_x_preferred":[
        "Vodno"
    ],
    "wof:name":"Vodno",
    "wof:placetype":"locality"
},
  "geometry": {"coordinates":[19.51056,43.17861],"type":"Point"}
}