{
  "type": "Feature",
  "properties": {
    "gn:admin1_code":"12.0",
    "gn:asciiname":"Osjecenica",
    "gn:country_code":"ME",
    "gn:dem":1010,
    "gn:feature_class":"P",
    "gn:feature_code":"PPLL",
    "gn:name":"Osje\u010denica",
    "gn:population":0,
    "gn:timezone":"Europe/Podgorica",
    "iso:country":"ME",
    "wof:name":"Osjecenica",
    "wof:placetype":"locality"
},
  "geometry": {"coordinates":[18.61528,42.70528],"type":"Point"}
}