{
  "type": "Feature",
  "properties": {
    "gn:admin1_code":"12.0",
    "gn:asciiname":"Nozdra",
    "gn:country_code":"ME",
    "gn:dem":1261,
    "gn:feature_class":"P",
    "gn:feature_code":"PPL",
    "gn:name":"Nozdra",
    "gn:population":0,
    "gn:timezone":"Europe/Podgorica",
    "iso:country":"ME",
    "name:und_x_variant":[
        "Nazdre",
        "Nozdra"
    ],
    "wof:name":"Nozdra",
    "wof:placetype":"locality"
},
  "geometry": {"coordinates":[18.84028,42.94167],"type":"Point"}
}