{
  "type": "Feature",
  "properties": {
    "gn:admin1_code":"19.0",
    "gn:asciiname":"Nikolici",
    "gn:country_code":"ME",
    "gn:dem":334,
    "gn:feature_class":"P",
    "gn:feature_code":"PPL",
    "gn:name":"Nikoli\u0107i",
    "gn:population":0,
    "gn:timezone":"Europe/Podgorica",
    "iso:country":"ME",
    "name:srp_x_preferred":[
        "Nikoli\u0107i"
    ],
    "wof:name":"Nikolici",
    "wof:placetype":"locality"
},
  "geometry": {"coordinates":[18.71139,42.45389],"type":"Point"}
}