{
  "type": "Feature",
  "properties": {
    "gn:admin1_code":"11.0",
    "gn:asciiname":"Podbrezovici",
    "gn:country_code":"ME",
    "gn:dem":1347,
    "gn:feature_class":"P",
    "gn:feature_code":"PPL",
    "gn:name":"Podbrezovi\u0107i",
    "gn:population":0,
    "gn:timezone":"Europe/Podgorica",
    "iso:country":"ME",
    "name:srp_x_preferred":[
        "Podbrezovi\u0107i"
    ],
    "wof:name":"Podbrezovici",
    "wof:placetype":"locality"
},
  "geometry": {"coordinates":[19.54333,43.00444],"type":"Point"}
}