{
  "type": "Feature",
  "properties": {
    "gn:admin1_code":"8.0",
    "gn:asciiname":"Lepetici",
    "gn:country_code":"ME",
    "gn:dem":543,
    "gn:feature_class":"P",
    "gn:feature_code":"PPL",
    "gn:name":"Lepeti\u0107i",
    "gn:population":0,
    "gn:timezone":"Europe/Podgorica",
    "iso:country":"ME",
    "name:srp_x_preferred":[
        "Lepeti\u0107i"
    ],
    "wof:name":"Lepetici",
    "wof:placetype":"locality"
},
  "geometry": {"coordinates":[18.50083,42.50278],"type":"Point"}
}