{
  "type": "Feature",
  "properties": {
    "gn:admin1_code":"17.0",
    "gn:asciiname":"Plumci",
    "gn:country_code":"ME",
    "gn:dem":1137,
    "gn:feature_class":"P",
    "gn:feature_code":"PPL",
    "gn:name":"Plumci",
    "gn:population":0,
    "gn:timezone":"Europe/Podgorica",
    "iso:country":"ME",
    "name:und_x_variant":[
        "Plunci",
        "Plumci"
    ],
    "wof:name":"Plumci",
    "wof:placetype":"locality"
},
  "geometry": {"coordinates":[20.19361,42.8375],"type":"Point"}
}