{
  "type": "Feature",
  "properties": {
    "gn:admin1_code":"14.0",
    "gn:asciiname":"Ametovina",
    "gn:country_code":"ME",
    "gn:dem":936,
    "gn:feature_class":"P",
    "gn:feature_code":"PPL",
    "gn:name":"Ametovina",
    "gn:population":0,
    "gn:timezone":"Europe/Podgorica",
    "iso:country":"ME",
    "name:srp_x_preferred":[
        "Ametovina"
    ],
    "wof:name":"Ametovina",
    "wof:placetype":"locality"
},
  "geometry": {"coordinates":[19.27361,43.34778],"type":"Point"}
}