{
  "type": "Feature",
  "properties": {
    "gn:country":"ME",
    "gn:fcode":"PPL",
    "gn:pop":633,
    "iso:country":"ME",
    "name:bos_x_preferred":[
        "\u0160avnik"
    ],
    "name:bul_x_preferred":[
        "\u0428\u0430\u0432\u043d\u0438\u043a"
    ],
    "name:ces_x_preferred":[
        "\u0160avnik"
    ],
    "name:deu_x_preferred":[
        "\u0160avnik"
    ],
    "name:eng_x_preferred":[
        "\u0160avnik"
    ],
    "name:est_x_preferred":[
        "\u0160avnik"
    ],
    "name:fas_x_preferred":[
        "\u0634\u0627\u0648\u0646\u06cc\u06a9"
    ],
    "name:fin_x_preferred":[
        "\u0160avnik"
    ],
    "name:fra_x_preferred":[
        "\u0160avnik"
    ],
    "name:hrv_x_preferred":[
        "\u0160avnik"
    ],
    "name:ita_x_preferred":[
        "\u0160avnik"
    ],
    "name:jpn_x_preferred":[
        "\u30b7\u30e3\u30f4\u30cb\u30af"
    ],
    "name:kat_x_preferred":[
        "\u10e8\u10d0\u10d5\u10dc\u10d8\u10d9\u10d8"
    ],
    "name:kor_x_preferred":[
        "\uc0e4\ube0c\ub2c8\ud06c"
    ],
    "name:lit_x_preferred":[
        "\u0160avnikas"
    ],
    "name:nld_x_preferred":[
        "\u0160avnik"
    ],
    "name:nob_x_preferred":[
        "\u0160avnik"
    ],
    "name:pol_x_preferred":[
        "\u0160avnik"
    ],
    "name:por_x_preferred":[
        "\u0160avnik"
    ],
    "name:ron_x_preferred":[
        "\u0160avnik"
    ],
    "name:rus_x_preferred":[
        "\u0428\u0430\u0432\u043d\u0438\u043a"
    ],
    "name:slv_x_preferred":[
        "\u0160avnik"
    ],
    "name:spa_x_preferred":[
        "\u0160avnik"
    ],
    "name:sqi_x_preferred":[
        "Shavniku"
    ],
    "name:srp_x_preferred":[
        "\u0428\u0430\u0432\u043d\u0438\u043a"
    ],
    "name:ukr_x_preferred":[
        "\u0428\u0430\u0432\u043d\u0456\u043a"
    ],
    "name:unk_x_variant":[
        "\u0428\u0430\u0432\u043d\u0438\u043a"
    ],
    "name:zho_x_preferred":[
        "\u6c99\u592b\u5c3c\u514b"
    ],
    "qs:name":"\u0160avnik",
    "qs:photos_9r":0,
    "qs:photos_sr":0,
    "qs:pop_sr":"2",
    "wd:wordcount":31,
    "wof:name":"\u0160avnik",
    "wof:placetype":"locality",
    "wof:population":633
},
  "geometry": {"coordinates":[19.09667,42.95639],"type":"Point"}
}