{
  "type": "Feature",
  "properties": {
    "gn:admin1_code":"16.0",
    "gn:asciiname":"Seostica",
    "gn:country_code":"ME",
    "gn:dem":960,
    "gn:feature_class":"P",
    "gn:feature_code":"PPL",
    "gn:name":"Seo\u0161tica",
    "gn:population":0,
    "gn:timezone":"Europe/Podgorica",
    "iso:country":"ME",
    "name:srp_x_preferred":[
        "Seo\u0161tica"
    ],
    "wof:name":"Seostica",
    "wof:placetype":"locality"
},
  "geometry": {"coordinates":[19.42389,42.57528],"type":"Point"}
}