{
  "type": "Feature",
  "properties": {
    "gn:country":"ME",
    "gn:fcode":"PPL",
    "gn:population":82,
    "iso:country":"ME",
    "name:und_x_variant":[
        "Dabojevi\u010di"
    ],
    "qs:name":"Dabovi\u0107i",
    "qs:photos_9r":0,
    "qs:photos_sr":0,
    "qs:pop_sr":"1",
    "wof:name":"Dabovi\u0107i",
    "wof:placetype":"locality",
    "wof:population":82
},
  "geometry": {"coordinates":[19.01722,42.67333],"type":"Point"}
}