{
  "type": "Feature",
  "properties": {
    "gn:admin1_code":"18.0",
    "gn:asciiname":"Krusevice",
    "gn:country_code":"ME",
    "gn:dem":1199,
    "gn:feature_class":"P",
    "gn:feature_code":"PPL",
    "gn:name":"Kru\u0161evice",
    "gn:population":0,
    "gn:timezone":"Europe/Podgorica",
    "iso:country":"ME",
    "name:und_x_variant":[
        "Kru\u0161evica",
        "Kru\u0161evice"
    ],
    "wof:name":"Krusevice",
    "wof:placetype":"locality"
},
  "geometry": {"coordinates":[19.09083,42.91444],"type":"Point"}
}