{
  "type": "Feature",
  "properties": {
    "gn:admin1_code":"18.0",
    "gn:asciiname":"Opcine",
    "gn:country_code":"ME",
    "gn:dem":1353,
    "gn:feature_class":"P",
    "gn:feature_code":"PPL",
    "gn:name":"Op\u010dine",
    "gn:population":0,
    "gn:timezone":"Europe/Podgorica",
    "iso:country":"ME",
    "wof:name":"Opcine",
    "wof:placetype":"locality"
},
  "geometry": {"coordinates":[19.13639,43.04417],"type":"Point"}
}