{
  "type": "Feature",
  "properties": {
    "gn:admin1_code":"21.0",
    "gn:asciiname":"Studenci",
    "gn:country_code":"ME",
    "gn:dem":1591,
    "gn:feature_class":"P",
    "gn:feature_code":"PPL",
    "gn:name":"Studenci",
    "gn:population":0,
    "gn:timezone":"Europe/Podgorica",
    "iso:country":"ME",
    "name:srp_x_preferred":[
        "Studenci"
    ],
    "wof:name":"Studenci",
    "wof:placetype":"locality"
},
  "geometry": {"coordinates":[19.30333,43.07],"type":"Point"}
}