{
  "type": "Feature",
  "properties": {
    "gn:admin1_code":"21.0",
    "gn:asciiname":"Studenci",
    "gn:country_code":"ME",
    "gn:dem":1591,
    "gn:feature_class":"P",
    "gn:feature_code":"PPL",
    "gn:name":"Studenci",
    "gn:population":0,
    "gn:timezone":"Europe/Podgorica",
    "iso:country":"ME",
    "name:bos_x_preferred":[
        "Studenci"
    ],
    "name:ceb_x_preferred":[
        "Studenci"
    ],
    "name:fra_x_preferred":[
        "Studenci"
    ],
    "name:hrv_x_preferred":[
        "Studenci"
    ],
    "name:hun_x_preferred":[
        "Studenci"
    ],
    "name:ita_x_preferred":[
        "Studenci"
    ],
    "name:nld_x_preferred":[
        "Studenci"
    ],
    "name:pol_x_preferred":[
        "Studenci"
    ],
    "name:slv_x_preferred":[
        "Studenci"
    ],
    "name:srp_x_preferred":[
        "Studenci"
    ],
    "name:srp_x_variant":[
        "\u0421\u0442\u0443\u0434\u0435\u043d\u0446\u0438"
    ],
    "name:swe_x_preferred":[
        "Studenci"
    ],
    "wof:name":"Studenci",
    "wof:placetype":"locality"
},
  "geometry": {"coordinates":[19.30333,43.07],"type":"Point"}
}