{
  "type": "Feature",
  "properties": {
    "gn:admin1_code":"16.0",
    "gn:asciiname":"Balabani",
    "gn:country_code":"ME",
    "gn:dem":11,
    "gn:feature_class":"P",
    "gn:feature_code":"PPL",
    "gn:name":"Balabani",
    "gn:population":0,
    "gn:timezone":"Europe/Podgorica",
    "iso:country":"ME",
    "name:srp_x_preferred":[
        "Balabani"
    ],
    "wof:name":"Balabani",
    "wof:placetype":"locality"
},
  "geometry": {"coordinates":[19.23389,42.325],"type":"Point"}
}