{
  "type": "Feature",
  "properties": {
    "gn:admin1_code":"14.0",
    "gn:asciiname":"Podgradina",
    "gn:country_code":"ME",
    "gn:dem":1251,
    "gn:feature_class":"P",
    "gn:feature_code":"PPL",
    "gn:name":"Podgradina",
    "gn:population":0,
    "gn:timezone":"Europe/Podgorica",
    "iso:country":"ME",
    "name:srp_x_preferred":[
        "Podgradina"
    ],
    "wof:name":"Podgradina",
    "wof:placetype":"locality"
},
  "geometry": {"coordinates":[19.15972,43.49694],"type":"Point"}
}