{
  "type": "Feature",
  "properties": {
    "gn:admin1_code":"14.0",
    "gn:asciiname":"Klade",
    "gn:country_code":"ME",
    "gn:dem":1192,
    "gn:feature_class":"P",
    "gn:feature_code":"PPL",
    "gn:name":"Kla\u0111e",
    "gn:population":0,
    "gn:timezone":"Europe/Podgorica",
    "iso:country":"ME",
    "name:srp_x_preferred":[
        "Kla\u0111e"
    ],
    "wof:name":"Klade",
    "wof:placetype":"locality"
},
  "geometry": {"coordinates":[19.48667,43.25472],"type":"Point"}
}