{
  "type": "Feature",
  "properties": {
    "gn:admin1_code":"2.0",
    "gn:asciiname":"Mali Ostros",
    "gn:country_code":"ME",
    "gn:dem":211,
    "gn:feature_class":"P",
    "gn:feature_code":"PPL",
    "gn:name":"Mali Ostros",
    "gn:population":0,
    "gn:timezone":"Europe/Podgorica",
    "iso:country":"ME",
    "name:srp_x_preferred":[
        "Mali Ostros"
    ],
    "wof:name":"Mali Ostros",
    "wof:placetype":"locality"
},
  "geometry": {"coordinates":[19.31139,42.08667],"type":"Point"}
}