{
  "type": "Feature",
  "properties": {
    "gn:admin1_code":"9.0",
    "gn:asciiname":"Smrcje",
    "gn:country_code":"ME",
    "gn:dem":1170,
    "gn:feature_class":"P",
    "gn:feature_code":"PPL",
    "gn:name":"Smr\u010dje",
    "gn:population":0,
    "gn:timezone":"Europe/Podgorica",
    "iso:country":"ME",
    "name:srp_x_preferred":[
        "Smr\u010dje"
    ],
    "wof:name":"Smrcje",
    "wof:placetype":"locality"
},
  "geometry": {"coordinates":[19.57361,42.79528],"type":"Point"}
}