{
  "type": "Feature",
  "properties": {
    "gn:admin1_code":"14.0",
    "gn:asciiname":"Sljivansko",
    "gn:country_code":"ME",
    "gn:dem":1077,
    "gn:feature_class":"P",
    "gn:feature_code":"PPLL",
    "gn:name":"\u0160ljivansko",
    "gn:population":0,
    "gn:timezone":"Europe/Podgorica",
    "iso:country":"ME",
    "name:fra_x_preferred":[
        "\u0160ljivansko"
    ],
    "name:ron_x_preferred":[
        "\u0160ljivansko"
    ],
    "name:slv_x_preferred":[
        "\u0160ljivansko"
    ],
    "name:srp_x_preferred":[
        "\u0428\u0459\u0438\u0432\u0430\u043d\u0441\u043a\u043e"
    ],
    "name:und_x_variant":[
        "\u0160ljivensko"
    ],
    "wof:name":"Sljivansko",
    "wof:placetype":"locality"
},
  "geometry": {"coordinates":[19.21278,43.32167000000001],"type":"Point"}
}