{
  "type": "Feature",
  "properties": {
    "gn:admin1_code":"14.0",
    "gn:asciiname":"Dolinice",
    "gn:country_code":"ME",
    "gn:dem":1121,
    "gn:feature_class":"P",
    "gn:feature_code":"PPL",
    "gn:name":"Dolinice",
    "gn:population":0,
    "gn:timezone":"Europe/Podgorica",
    "iso:country":"ME",
    "name:und_x_variant":[
        "Mihajlovi\u0107i",
        "Dolinice"
    ],
    "wof:name":"Dolinice",
    "wof:placetype":"locality"
},
  "geometry": {"coordinates":[19.43833,43.33833],"type":"Point"}
}