{
  "type": "Feature",
  "properties": {
    "gn:admin1_code":"6.0",
    "gn:asciiname":"Gornji Izvor",
    "gn:country_code":"ME",
    "gn:dem":845,
    "gn:feature_class":"P",
    "gn:feature_code":"PPL",
    "gn:name":"Gornji Izvor",
    "gn:population":0,
    "gn:timezone":"Europe/Podgorica",
    "iso:country":"ME",
    "name:srp_x_preferred":[
        "Gornji Izvor"
    ],
    "wof:name":"Gornji Izvor",
    "wof:placetype":"locality"
},
  "geometry": {"coordinates":[18.7775,42.60528],"type":"Point"}
}