{
  "type": "Feature",
  "properties": {
    "gn:admin1_code":"4.0",
    "gn:asciiname":"Draskovina",
    "gn:country_code":"ME",
    "gn:dem":860,
    "gn:feature_class":"P",
    "gn:feature_code":"PPL",
    "gn:name":"Dra\u0161kovina",
    "gn:population":0,
    "gn:timezone":"Europe/Podgorica",
    "iso:country":"ME",
    "name:srp_x_preferred":[
        "Dra\u0161kovina"
    ],
    "wof:name":"Draskovina",
    "wof:placetype":"locality"
},
  "geometry": {"coordinates":[19.62778,43.16694],"type":"Point"}
}