{
  "type": "Feature",
  "properties": {
    "gn:admin1_code":"21.0",
    "gn:asciiname":"Donja Dobrilovina",
    "gn:country_code":"ME",
    "gn:dem":805,
    "gn:feature_class":"P",
    "gn:feature_code":"PPL",
    "gn:name":"Donja Dobrilovina",
    "gn:population":0,
    "gn:timezone":"Europe/Podgorica",
    "iso:country":"ME",
    "name:srp_x_preferred":[
        "Donja Dobrilovina"
    ],
    "wof:name":"Donja Dobrilovina",
    "wof:placetype":"locality"
},
  "geometry": {"coordinates":[19.38389,43.05444],"type":"Point"}
}