{
  "type": "Feature",
  "properties": {
    "gn:admin1_code":"3.0",
    "gn:asciiname":"Maslari",
    "gn:country_code":"ME",
    "gn:dem":1284,
    "gn:feature_class":"P",
    "gn:feature_code":"PPL",
    "gn:name":"Maslari",
    "gn:population":0,
    "gn:timezone":"Europe/Podgorica",
    "iso:country":"ME",
    "wof:name":"Maslari",
    "wof:placetype":"locality"
},
  "geometry": {"coordinates":[19.9125,42.75389000000001],"type":"Point"}
}