{
  "type": "Feature",
  "properties": {
    "gn:admin1_code":"9.0",
    "gn:asciiname":"Mijoska",
    "gn:country_code":"ME",
    "gn:dem":882,
    "gn:feature_class":"P",
    "gn:feature_code":"PPL",
    "gn:name":"Mijoska",
    "gn:population":0,
    "gn:timezone":"Europe/Podgorica",
    "iso:country":"ME",
    "name:und_x_variant":[
        "Mioska",
        "Mijoska"
    ],
    "wof:name":"Mijoska",
    "wof:placetype":"locality"
},
  "geometry": {"coordinates":[19.4125,42.815],"type":"Point"}
}