{
  "type": "Feature",
  "properties": {
    "gn:admin1_code":"9.0",
    "gn:asciiname":"Mijoska",
    "gn:country_code":"ME",
    "gn:dem":882,
    "gn:feature_class":"P",
    "gn:feature_code":"PPL",
    "gn:name":"Mijoska",
    "gn:population":0,
    "gn:timezone":"Europe/Podgorica",
    "iso:country":"ME",
    "name:ceb_x_preferred":[
        "Mioska"
    ],
    "name:fra_x_preferred":[
        "Mijoska"
    ],
    "name:msa_x_preferred":[
        "Mijoska"
    ],
    "name:nld_x_preferred":[
        "Mijoska"
    ],
    "name:por_x_preferred":[
        "Mijoska"
    ],
    "name:slv_x_preferred":[
        "Mijoska"
    ],
    "name:srp_x_preferred":[
        "\u041c\u0438\u0458\u043e\u0441\u043a\u0430"
    ],
    "wof:name":"Mijoska",
    "wof:placetype":"locality"
},
  "geometry": {"coordinates":[19.4125,42.815],"type":"Point"}
}