{
  "type": "Feature",
  "properties": {
    "gn:country":"ME",
    "gn:fcode":"PPL",
    "gn:population":5,
    "iso:country":"ME",
    "name:srp_x_preferred":[
        "Gornja Kostanjica"
    ],
    "qs:name":"Gornja Kostanjica",
    "qs:photos_9r":0,
    "qs:photos_sr":0,
    "qs:pop_sr":"1",
    "wof:name":"Gornja Kostanjica",
    "wof:placetype":"locality",
    "wof:population":5
},
  "geometry": {"coordinates":[18.66389,42.48306],"type":"Point"}
}