{
  "type": "Feature",
  "properties": {
    "gn:admin1_code":"9.0",
    "gn:asciiname":"Istace",
    "gn:country_code":"ME",
    "gn:dem":767,
    "gn:feature_class":"P",
    "gn:feature_code":"PPL",
    "gn:name":"Ista\u0107e",
    "gn:population":0,
    "gn:timezone":"Europe/Podgorica",
    "iso:country":"ME",
    "name:srp_x_preferred":[
        "Ista\u0107e"
    ],
    "wof:name":"Istace",
    "wof:placetype":"locality"
},
  "geometry": {"coordinates":[19.36361,42.74444],"type":"Point"}
}