{
  "type": "Feature",
  "properties": {
    "gn:country":"ME",
    "gn:fcode":"PPL",
    "gn:population":965,
    "iso:country":"ME",
    "name:ara_x_preferred":[
        "\u0628\u0631\u0646\u062c\u0627\u0641\u0648\u0631"
    ],
    "name:bos_x_preferred":[
        "Prnjavor"
    ],
    "name:ceb_x_preferred":[
        "Prnjavor"
    ],
    "name:deu_x_preferred":[
        "Prnjavor"
    ],
    "name:fra_x_preferred":[
        "Prnjavor"
    ],
    "name:hrv_x_preferred":[
        "Prnjavor"
    ],
    "name:hun_x_preferred":[
        "Prnjavor"
    ],
    "name:nld_x_preferred":[
        "Prnjavor"
    ],
    "name:slv_x_preferred":[
        "Prnjavor"
    ],
    "name:srp_x_preferred":[
        "Prnjavor"
    ],
    "name:srp_x_variant":[
        "\u041f\u0440\u045a\u0430\u0432\u043e\u0440"
    ],
    "name:swe_x_preferred":[
        "Prnjavor"
    ],
    "name:ukr_x_preferred":[
        "\u041f\u0440\u043d\u044f\u0432\u043e\u0440"
    ],
    "qs_pg:aaroncc":"ME",
    "qs_pg:gn_country":"ME",
    "qs_pg:gn_fcode":"PPL",
    "qs_pg:gn_pop":965,
    "qs_pg:name":"Prnjavor",
    "qs_pg:photos_9r":0,
    "qs_pg:photos_sr":0,
    "qs_pg:pop_sr":2,
    "qs_pg:qs_pg_placetype":"locality",
    "wof:name":"Prnjavor",
    "wof:placetype":"locality",
    "wof:population":965
},
  "geometry": {"coordinates":[19.95056,42.59806],"type":"Point"}
}