{
  "type": "Feature",
  "properties": {
    "gn:gn_country":"ME",
    "gn:gn_fcode":"PPL",
    "gn:gn_pop":965,
    "gn:population":965,
    "iso:country":"ME",
    "name:srp_x_preferred":[
        "Prnjavor"
    ],
    "qs_pg:aaroncc":"ME",
    "qs_pg:gn_country":"ME",
    "qs_pg:gn_fcode":"PPL",
    "qs_pg:gn_pop":965,
    "qs_pg:name":"Prnjavor",
    "qs_pg:photos_9r":0,
    "qs_pg:photos_sr":0,
    "qs_pg:pop_sr":2,
    "qs_pg:qs_pg_placetype":"locality",
    "wof:name":"Prnjavor",
    "wof:placetype":"locality",
    "wof:population":965
},
  "geometry": {"coordinates":[19.95056,42.59806],"type":"Point"}
}