{
  "type": "Feature",
  "properties": {
    "gn:admin1_code":"20.0",
    "gn:asciiname":"Draginje",
    "gn:country_code":"ME",
    "gn:dem":18,
    "gn:feature_class":"P",
    "gn:feature_code":"PPLL",
    "gn:name":"Draginje",
    "gn:population":0,
    "gn:timezone":"Europe/Podgorica",
    "iso:country":"ME",
    "name:ceb_x_preferred":[
        "Draginje"
    ],
    "name:fra_x_preferred":[
        "Draginje"
    ],
    "name:msa_x_preferred":[
        "Draginje"
    ],
    "name:nld_x_preferred":[
        "Draginje"
    ],
    "name:por_x_preferred":[
        "Draginje"
    ],
    "name:slv_x_preferred":[
        "Draginje"
    ],
    "name:srp_x_preferred":[
        "\u0414\u0440\u0430\u0433\u0438\u045a\u0435"
    ],
    "name:und_x_variant":[
        "Draginja",
        "Draginje"
    ],
    "wof:name":"Draginje",
    "wof:placetype":"locality"
},
  "geometry": {"coordinates":[19.34694,42.01417],"type":"Point"}
}