{
  "type": "Feature",
  "properties": {
    "gn:admin1_code":"20.0",
    "gn:asciiname":"Kosici",
    "gn:country_code":"ME",
    "gn:dem":127,
    "gn:feature_class":"P",
    "gn:feature_code":"PPLL",
    "gn:name":"Kosi\u0107i",
    "gn:population":0,
    "gn:timezone":"Europe/Podgorica",
    "iso:country":"ME",
    "name:und_x_variant":[
        "Kosi\u0107",
        "Kosi\u0107i"
    ],
    "wof:name":"Kosici",
    "wof:placetype":"locality"
},
  "geometry": {"coordinates":[19.27306,42.02583],"type":"Point"}
}