{
  "type": "Feature",
  "properties": {
    "gn:admin1_code":"16.0",
    "gn:asciiname":"Sipcanik",
    "gn:country_code":"ME",
    "gn:dem":51,
    "gn:feature_class":"P",
    "gn:feature_code":"PPL",
    "gn:name":"\u0160ip\u010danik",
    "gn:population":0,
    "gn:timezone":"Europe/Podgorica",
    "iso:country":"ME",
    "name:srp_x_preferred":[
        "\u0160ip\u010danik"
    ],
    "wof:name":"Sipcanik",
    "wof:placetype":"locality"
},
  "geometry": {"coordinates":[19.31806,42.36889],"type":"Point"}
}