{
  "type": "Feature",
  "properties": {
    "gn:country":"ME",
    "gn:fcode":"PPL",
    "gn:pop":5,
    "iso:country":"ME",
    "name:srp_x_preferred":[
        "Kanjo\u0161i"
    ],
    "qs:name":"Kanjo\u0161i",
    "qs:photos_9r":0,
    "qs:photos_sr":0,
    "qs:pop_sr":"1",
    "wof:name":"Kanjo\u0161i",
    "wof:placetype":"locality",
    "wof:population":5
},
  "geometry": {"coordinates":[18.98722,42.18222],"type":"Point"}
}