{
  "type": "Feature",
  "properties": {
    "gn:admin1_code":"2.0",
    "gn:asciiname":"Krnjice",
    "gn:country_code":"ME",
    "gn:dem":117,
    "gn:feature_class":"P",
    "gn:feature_code":"PPL",
    "gn:name":"Krnjice",
    "gn:population":0,
    "gn:timezone":"Europe/Podgorica",
    "iso:country":"ME",
    "name:srp_x_preferred":[
        "Krnjice"
    ],
    "wof:name":"Krnjice",
    "wof:placetype":"locality"
},
  "geometry": {"coordinates":[19.1775,42.21389],"type":"Point"}
}