{
  "type": "Feature",
  "properties": {
    "gn:admin1_code":"14.0",
    "gn:asciiname":"Kleke",
    "gn:country_code":"ME",
    "gn:dem":1065,
    "gn:feature_class":"P",
    "gn:feature_code":"PPL",
    "gn:name":"Kleke",
    "gn:population":0,
    "gn:timezone":"Europe/Podgorica",
    "iso:country":"ME",
    "name:srp_x_preferred":[
        "Kleke"
    ],
    "wof:name":"Kleke",
    "wof:placetype":"locality"
},
  "geometry": {"coordinates":[19.46722,43.24222],"type":"Point"}
}