{
  "type": "Feature",
  "properties": {
    "gn:admin1_code":"6.0",
    "gn:asciiname":"Vojkovici",
    "gn:country_code":"ME",
    "gn:dem":851,
    "gn:feature_class":"P",
    "gn:feature_code":"PPL",
    "gn:name":"Vojkovi\u0107i",
    "gn:population":0,
    "gn:timezone":"Europe/Podgorica",
    "iso:country":"ME",
    "name:srp_x_preferred":[
        "Vojkovi\u0107i"
    ],
    "wof:name":"Vojkovici",
    "wof:placetype":"locality"
},
  "geometry": {"coordinates":[18.87444,42.45806],"type":"Point"}
}