{
  "type": "Feature",
  "properties": {
    "gn:admin1_code":"4.0",
    "gn:asciiname":"Crnionica",
    "gn:country_code":"ME",
    "gn:dem":872,
    "gn:feature_class":"P",
    "gn:feature_code":"PPL",
    "gn:name":"Crnionica",
    "gn:population":0,
    "gn:timezone":"Europe/Podgorica",
    "iso:country":"ME",
    "name:und_x_variant":[
        "Crnjonica",
        "Crnionica"
    ],
    "wof:name":"Crnionica",
    "wof:placetype":"locality"
},
  "geometry": {"coordinates":[19.72528,43.00278],"type":"Point"}
}