{
  "type": "Feature",
  "properties": {
    "gn:admin1_code":"4.0",
    "gn:asciiname":"Pozar",
    "gn:country_code":"ME",
    "gn:dem":795,
    "gn:feature_class":"P",
    "gn:feature_code":"PPL",
    "gn:name":"Po\u017ear",
    "gn:population":0,
    "gn:timezone":"Europe/Podgorica",
    "iso:country":"ME",
    "name:srp_x_preferred":[
        "Po\u017ear"
    ],
    "wof:name":"Pozar",
    "wof:placetype":"locality"
},
  "geometry": {"coordinates":[19.61417,43.01639],"type":"Point"}
}