{
  "type": "Feature",
  "properties": {
    "gn:admin1_code":"14.0",
    "gn:asciiname":"Zabrde",
    "gn:country_code":"ME",
    "gn:dem":786,
    "gn:feature_class":"P",
    "gn:feature_code":"PPL",
    "gn:name":"Zabr\u0111e",
    "gn:population":0,
    "gn:timezone":"Europe/Podgorica",
    "iso:country":"ME",
    "name:srp_x_preferred":[
        "Zabr\u0111e"
    ],
    "wof:name":"Zabrde",
    "wof:placetype":"locality"
},
  "geometry": {"coordinates":[19.33028,43.31778],"type":"Point"}
}