{
  "type": "Feature",
  "properties": {
    "gn:admin1_code":"15.0",
    "gn:asciiname":"Belusevac",
    "gn:country_code":"ME",
    "gn:dem":1453,
    "gn:feature_class":"P",
    "gn:feature_code":"PPL",
    "gn:name":"Belu\u0161evac",
    "gn:population":0,
    "gn:timezone":"Europe/Podgorica",
    "iso:country":"ME",
    "wof:name":"Belusevac",
    "wof:placetype":"locality"
},
  "geometry": {"coordinates":[18.93333,43.31917],"type":"Point"}
}