{
  "type": "Feature",
  "properties": {
    "gn:admin1_code":"5.0",
    "gn:asciiname":"Zecevo Selo",
    "gn:country_code":"ME",
    "gn:dem":518,
    "gn:feature_class":"P",
    "gn:feature_code":"PPL",
    "gn:name":"Ze\u010devo Selo",
    "gn:population":0,
    "gn:timezone":"Europe/Podgorica",
    "iso:country":"ME",
    "name:srp_x_preferred":[
        "Ze\u010devo Selo"
    ],
    "wof:name":"Zecevo Selo",
    "wof:placetype":"locality"
},
  "geometry": {"coordinates":[18.82944,42.32389000000001],"type":"Point"}
}