{
  "type": "Feature",
  "properties": {
    "gn:admin1_code":"9.0",
    "gn:asciiname":"Zavraca",
    "gn:country_code":"ME",
    "gn:dem":753,
    "gn:feature_class":"P",
    "gn:feature_code":"PPLL",
    "gn:name":"Zavraca",
    "gn:population":0,
    "gn:timezone":"Europe/Podgorica",
    "iso:country":"ME",
    "name:und_x_variant":[
        "Zavraci",
        "Zavraca"
    ],
    "wof:name":"Zavraca",
    "wof:placetype":"locality"
},
  "geometry": {"coordinates":[19.305,42.84333],"type":"Point"}
}