{
  "type": "Feature",
  "properties": {
    "gn:admin1_code":"16.0",
    "gn:asciiname":"Gornja Gorica",
    "gn:country_code":"ME",
    "gn:dem":35,
    "gn:feature_class":"P",
    "gn:feature_code":"PPL",
    "gn:name":"Gornja Gorica",
    "gn:population":0,
    "gn:timezone":"Europe/Podgorica",
    "iso:country":"ME",
    "name:srp_x_preferred":[
        "Gornja Gorica"
    ],
    "wof:name":"Gornja Gorica",
    "wof:placetype":"locality"
},
  "geometry": {"coordinates":[19.21583,42.43861],"type":"Point"}
}