{
  "type": "Feature",
  "properties": {
    "gn:admin1_code":"4.0",
    "gn:asciiname":"Saruljevac",
    "gn:country_code":"ME",
    "gn:dem":567,
    "gn:feature_class":"P",
    "gn:feature_code":"PPL",
    "gn:name":"\u0160aruljevac",
    "gn:population":0,
    "gn:timezone":"Europe/Podgorica",
    "iso:country":"ME",
    "wof:name":"Saruljevac",
    "wof:placetype":"locality"
},
  "geometry": {"coordinates":[19.76028,43.13944],"type":"Point"}
}