{
  "type": "Feature",
  "properties": {
    "gn:admin1_code":"6.0",
    "gn:asciiname":"Donji Ulici",
    "gn:country_code":"ME",
    "gn:dem":427,
    "gn:feature_class":"P",
    "gn:feature_code":"PPL",
    "gn:name":"Donji Uli\u0107i",
    "gn:population":0,
    "gn:timezone":"Europe/Podgorica",
    "iso:country":"ME",
    "name:und_x_variant":[
        "Uli\u0107i",
        "Donji Uli\u0107i"
    ],
    "wof:name":"Donji Ulici",
    "wof:placetype":"locality"
},
  "geometry": {"coordinates":[18.98889,42.37917],"type":"Point"}
}