{
  "type": "Feature",
  "properties": {
    "gn:admin1_code":"12.0",
    "gn:asciiname":"Sake",
    "gn:country_code":"ME",
    "gn:dem":989,
    "gn:feature_class":"P",
    "gn:feature_code":"PPL",
    "gn:name":"\u0160ake",
    "gn:population":0,
    "gn:timezone":"Europe/Podgorica",
    "iso:country":"ME",
    "name:srp_x_preferred":[
        "\u0160ake"
    ],
    "wof:name":"Sake",
    "wof:placetype":"locality"
},
  "geometry": {"coordinates":[18.60028,42.86028],"type":"Point"}
}