{
  "type": "Feature",
  "properties": {
    "gn:admin1_code":"21.0",
    "gn:asciiname":"Zauglina",
    "gn:country_code":"ME",
    "gn:dem":1346,
    "gn:feature_class":"P",
    "gn:feature_code":"PPLL",
    "gn:name":"Zauglina",
    "gn:population":0,
    "gn:timezone":"Europe/Podgorica",
    "iso:country":"ME",
    "wof:name":"Zauglina",
    "wof:placetype":"locality"
},
  "geometry": {"coordinates":[19.24972,43.11639],"type":"Point"}
}