{
  "type": "Feature",
  "properties": {
    "gn:country":"ME",
    "gn:fcode":"PPL",
    "gn:pop":70,
    "iso:country":"ME",
    "name:srp_x_preferred":[
        "Zagora"
    ],
    "qs:name":"Zagora",
    "qs:photos_9r":0,
    "qs:photos_sr":0,
    "qs:pop_sr":"1",
    "wd:wordcount":112,
    "wof:name":"Zagora",
    "wof:placetype":"locality",
    "wof:population":70
},
  "geometry": {"coordinates":[19.06528,42.40917],"type":"Point"}
}