{
  "type": "Feature",
  "properties": {
    "gn:country":"ME",
    "gn:fcode":"PPL",
    "gn:population":70,
    "iso:country":"ME",
    "name:bar_x_preferred":[
        "Zagora"
    ],
    "name:bos_x_preferred":[
        "Zagora"
    ],
    "name:bul_x_preferred":[
        "\u0417\u0430\u0433\u043e\u0440\u0430"
    ],
    "name:cat_x_preferred":[
        "Zagora"
    ],
    "name:ceb_x_preferred":[
        "Zagora"
    ],
    "name:ces_x_preferred":[
        "Zagora"
    ],
    "name:cym_x_preferred":[
        "Zagora"
    ],
    "name:dan_x_preferred":[
        "Zagora"
    ],
    "name:deu_x_preferred":[
        "Zagora"
    ],
    "name:eng_x_preferred":[
        "Zagora"
    ],
    "name:epo_x_preferred":[
        "Zagora"
    ],
    "name:fin_x_preferred":[
        "Zagora"
    ],
    "name:fra_x_preferred":[
        "Zagora"
    ],
    "name:gla_x_preferred":[
        "Zagora"
    ],
    "name:glg_x_preferred":[
        "Zagora"
    ],
    "name:gsw_x_preferred":[
        "Zagora"
    ],
    "name:hrv_x_preferred":[
        "Zagora"
    ],
    "name:hun_x_preferred":[
        "Zagora"
    ],
    "name:ind_x_preferred":[
        "Zagora"
    ],
    "name:isl_x_preferred":[
        "Zagora"
    ],
    "name:ita_x_preferred":[
        "Zagora"
    ],
    "name:kab_x_preferred":[
        "Tazaggurt"
    ],
    "name:lit_x_preferred":[
        "Zagora"
    ],
    "name:ltz_x_preferred":[
        "Zagora"
    ],
    "name:min_x_preferred":[
        "Zagora"
    ],
    "name:msa_x_preferred":[
        "Zagora"
    ],
    "name:nds_x_preferred":[
        "Zagora"
    ],
    "name:nld_x_preferred":[
        "Zagora"
    ],
    "name:nno_x_preferred":[
        "Zagora"
    ],
    "name:nob_x_preferred":[
        "Zagora"
    ],
    "name:pol_x_preferred":[
        "Zagora"
    ],
    "name:por_x_preferred":[
        "Zagora"
    ],
    "name:ron_x_preferred":[
        "Zagora"
    ],
    "name:rus_x_preferred":[
        "\u0417\u0430\u0433\u043e\u0440\u0430"
    ],
    "name:sco_x_preferred":[
        "Zagora"
    ],
    "name:slk_x_preferred":[
        "Zagora"
    ],
    "name:slv_x_preferred":[
        "Zagora"
    ],
    "name:spa_x_preferred":[
        "Zagora"
    ],
    "name:srp_x_preferred":[
        "Zagora"
    ],
    "name:srp_x_variant":[
        "\u0417\u0430\u0433\u043e\u0440\u0430"
    ],
    "name:swe_x_preferred":[
        "Zagora"
    ],
    "name:ukr_x_preferred":[
        "\u0417\u0430\u0433\u043e\u0440\u0430"
    ],
    "qs:name":"Zagora",
    "qs:photos_9r":0,
    "qs:photos_sr":0,
    "qs:pop_sr":"1",
    "wd:wordcount":112,
    "wof:name":"Zagora",
    "wof:placetype":"locality",
    "wof:population":70
},
  "geometry": {"coordinates":[19.06528,42.40917],"type":"Point"}
}