{
  "type": "Feature",
  "properties": {
    "gn:country":"ME",
    "gn:fcode":"PPL",
    "gn:pop":5,
    "iso:country":"ME",
    "name:srp_x_preferred":[
        "\u010canj"
    ],
    "qs:name":"\u010canj",
    "qs:photos_9r":0,
    "qs:photos_sr":0,
    "qs:pop_sr":"1",
    "wd:wordcount":3828,
    "wof:name":"\u010canj",
    "wof:placetype":"locality",
    "wof:population":5
},
  "geometry": {"coordinates":[18.99806,42.16278],"type":"Point"}
}