{
  "type": "Feature",
  "properties": {
    "gn:country":"ME",
    "gn:fcode":"PPL",
    "gn:population":5,
    "iso:country":"ME",
    "name:ara_x_preferred":[
        "\u0628\u0627\u0631"
    ],
    "name:bel_x_preferred":[
        "\u0411\u0430\u0440"
    ],
    "name:bos_x_preferred":[
        "Bar"
    ],
    "name:bul_x_preferred":[
        "\u0411\u0430\u0440"
    ],
    "name:cat_x_preferred":[
        "Bar"
    ],
    "name:ceb_x_preferred":[
        "Bar"
    ],
    "name:ces_x_preferred":[
        "Bar"
    ],
    "name:che_x_preferred":[
        "\u0411\u0430\u0440"
    ],
    "name:dan_x_preferred":[
        "Bar"
    ],
    "name:deu_x_preferred":[
        "Bar"
    ],
    "name:ell_x_preferred":[
        "\u039c\u03c0\u03b1\u03c1"
    ],
    "name:eng_x_preferred":[
        "Bar"
    ],
    "name:est_x_preferred":[
        "Bar"
    ],
    "name:eus_x_preferred":[
        "Bar"
    ],
    "name:fao_x_preferred":[
        "Bar"
    ],
    "name:fas_x_preferred":[
        "\u0628\u0627\u0631"
    ],
    "name:fin_x_preferred":[
        "Bar"
    ],
    "name:fra_x_preferred":[
        "Bar"
    ],
    "name:gag_x_preferred":[
        "Bar"
    ],
    "name:glg_x_preferred":[
        "Bar"
    ],
    "name:heb_x_preferred":[
        "\u05d1\u05e8"
    ],
    "name:hrv_x_preferred":[
        "Bar"
    ],
    "name:hun_x_preferred":[
        "Bar"
    ],
    "name:ind_x_preferred":[
        "Bar"
    ],
    "name:isl_x_preferred":[
        "Bar"
    ],
    "name:ita_x_preferred":[
        "Antivari"
    ],
    "name:jpn_x_preferred":[
        "\u30d0\u30fc\u30eb"
    ],
    "name:kal_x_preferred":[
        "Bar"
    ],
    "name:kat_x_preferred":[
        "\u10d1\u10d0\u10e0\u10d8"
    ],
    "name:kor_x_preferred":[
        "\ubc14\ub974"
    ],
    "name:lat_x_preferred":[
        "Antibarium"
    ],
    "name:lit_x_preferred":[
        "Baras"
    ],
    "name:mkd_x_preferred":[
        "\u0411\u0430\u0440"
    ],
    "name:nld_x_preferred":[
        "Bar"
    ],
    "name:nno_x_preferred":[
        "Bar"
    ],
    "name:nob_x_preferred":[
        "Bar"
    ],
    "name:oci_x_preferred":[
        "Bar"
    ],
    "name:pol_x_preferred":[
        "Bar"
    ],
    "name:por_x_preferred":[
        "Bar"
    ],
    "name:ron_x_preferred":[
        "Bar"
    ],
    "name:rus_x_preferred":[
        "\u0411\u0430\u0440"
    ],
    "name:sco_x_preferred":[
        "Bar"
    ],
    "name:slk_x_preferred":[
        "Bar"
    ],
    "name:slv_x_preferred":[
        "Bar"
    ],
    "name:spa_x_preferred":[
        "Bar"
    ],
    "name:sqi_x_preferred":[
        "Tivari"
    ],
    "name:srp_x_preferred":[
        "\u010canj"
    ],
    "name:srp_x_variant":[
        "\u0411\u0430\u0440"
    ],
    "name:swe_x_preferred":[
        "Bar"
    ],
    "name:tha_x_preferred":[
        "\u0e1a\u0e32\u0e23\u0e4c"
    ],
    "name:tur_x_preferred":[
        "Bar"
    ],
    "name:ukr_x_preferred":[
        "\u0411\u0430\u0440"
    ],
    "name:urd_x_preferred":[
        "\u0628\u0627\u0631"
    ],
    "name:zho_x_preferred":[
        "\u5df4\u5c14"
    ],
    "qs:name":"\u010canj",
    "qs:photos_9r":0,
    "qs:photos_sr":0,
    "qs:pop_sr":"1",
    "wd:wordcount":3828,
    "wof:name":"\u010canj",
    "wof:placetype":"locality",
    "wof:population":5
},
  "geometry": {"coordinates":[18.99806,42.16278],"type":"Point"}
}