{
  "type": "Feature",
  "properties": {
    "gn:admin1_code":"3.0",
    "gn:asciiname":"Delevici",
    "gn:country_code":"ME",
    "gn:dem":884,
    "gn:feature_class":"P",
    "gn:feature_code":"PPL",
    "gn:name":"Delevi\u0107i",
    "gn:population":0,
    "gn:timezone":"Europe/Podgorica",
    "iso:country":"ME",
    "name:und_x_variant":[
        "Jariste",
        "Delevi\u0107i"
    ],
    "wof:name":"Delevici",
    "wof:placetype":"locality"
},
  "geometry": {"coordinates":[19.92889,42.87222],"type":"Point"}
}