{
  "type": "Feature",
  "properties": {
    "gn:admin1_code":"7.0",
    "gn:asciiname":"Kopito",
    "gn:country_code":"ME",
    "gn:dem":48,
    "gn:feature_class":"P",
    "gn:feature_code":"PPL",
    "gn:name":"Kopito",
    "gn:population":0,
    "gn:timezone":"Europe/Podgorica",
    "iso:country":"ME",
    "name:und_x_variant":[
        "Kopito Petrovi\u0107a",
        "Kopito"
    ],
    "wof:name":"Kopito",
    "wof:placetype":"locality"
},
  "geometry": {"coordinates":[19.13667,42.54417],"type":"Point"}
}