{
  "type": "Feature",
  "properties": {
    "gn:admin1_code":"4.0",
    "gn:asciiname":"Kitine Lazi",
    "gn:country_code":"ME",
    "gn:dem":801,
    "gn:feature_class":"P",
    "gn:feature_code":"PPL",
    "gn:name":"Kitine Lazi",
    "gn:population":0,
    "gn:timezone":"Europe/Podgorica",
    "iso:country":"ME",
    "name:srp_x_preferred":[
        "Kitine Lazi"
    ],
    "wof:name":"Kitine Lazi",
    "wof:placetype":"locality"
},
  "geometry": {"coordinates":[19.80917,43.01111],"type":"Point"}
}