{
  "type": "Feature",
  "properties": {
    "gn:admin1_code":"2.0",
    "gn:asciiname":"Zankovici",
    "gn:country_code":"ME",
    "gn:dem":154,
    "gn:feature_class":"P",
    "gn:feature_code":"PPL",
    "gn:name":"Zankovi\u0107i",
    "gn:population":0,
    "gn:timezone":"Europe/Podgorica",
    "iso:country":"ME",
    "name:und_x_variant":[
        "Zankovi\u0107",
        "Zankovi\u0107i"
    ],
    "wof:name":"Zankovici",
    "wof:placetype":"locality"
},
  "geometry": {"coordinates":[19.0525,42.1475],"type":"Point"}
}