{
  "type": "Feature",
  "properties": {
    "gn:admin1_code":"1.0",
    "gn:asciiname":"Salevici",
    "gn:country_code":"ME",
    "gn:dem":882,
    "gn:feature_class":"P",
    "gn:feature_code":"PPL",
    "gn:name":"Salevi\u0107i",
    "gn:population":0,
    "gn:timezone":"Europe/Podgorica",
    "iso:country":"ME",
    "name:srp_x_preferred":[
        "Salevi\u0107i"
    ],
    "wof:name":"Salevici",
    "wof:placetype":"locality"
},
  "geometry": {"coordinates":[19.77861,42.745],"type":"Point"}
}