{
  "type": "Feature",
  "properties": {
    "gn:admin1_code":"14.0",
    "gn:asciiname":"Strazice",
    "gn:country_code":"ME",
    "gn:dem":899,
    "gn:feature_class":"P",
    "gn:feature_code":"PPL",
    "gn:name":"Stra\u017eice",
    "gn:population":0,
    "gn:timezone":"Europe/Podgorica",
    "iso:country":"ME",
    "name:srp_x_preferred":[
        "Stra\u017eice"
    ],
    "wof:name":"Strazice",
    "wof:placetype":"locality"
},
  "geometry": {"coordinates":[19.00444,43.50944000000001],"type":"Point"}
}