{
  "type": "Feature",
  "properties": {
    "gn:admin1_code":"15.0",
    "gn:asciiname":"Stubica",
    "gn:country_code":"ME",
    "gn:dem":1290,
    "gn:feature_class":"P",
    "gn:feature_code":"PPL",
    "gn:name":"Stubica",
    "gn:population":0,
    "gn:timezone":"Europe/Podgorica",
    "iso:country":"ME",
    "name:srp_x_preferred":[
        "Stubica"
    ],
    "wof:name":"Stubica",
    "wof:placetype":"locality"
},
  "geometry": {"coordinates":[18.71778,43.17667],"type":"Point"}
}