{
  "type": "Feature",
  "properties": {
    "gn:admin1_code":"19.0",
    "gn:asciiname":"Gosici",
    "gn:country_code":"ME",
    "gn:dem":107,
    "gn:feature_class":"P",
    "gn:feature_code":"PPL",
    "gn:name":"Go\u0161i\u0107i",
    "gn:population":0,
    "gn:timezone":"Europe/Podgorica",
    "iso:country":"ME",
    "name:und_x_variant":[
        "Go\u0161i\u0107",
        "Go\u0161i\u0107i"
    ],
    "wof:name":"Gosici",
    "wof:placetype":"locality"
},
  "geometry": {"coordinates":[18.66139,42.39806],"type":"Point"}
}