{
  "type": "Feature",
  "properties": {
    "gn:admin1_code":"6.0",
    "gn:asciiname":"Erakovici",
    "gn:country_code":"ME",
    "gn:dem":857,
    "gn:feature_class":"P",
    "gn:feature_code":"PPL",
    "gn:name":"Erakovi\u0107i",
    "gn:population":0,
    "gn:timezone":"Europe/Podgorica",
    "iso:country":"ME",
    "name:und_x_variant":[
        "Niego\u0161",
        "Erakovi\u0107i"
    ],
    "wof:name":"Erakovici",
    "wof:placetype":"locality"
},
  "geometry": {"coordinates":[18.83,42.43472],"type":"Point"}
}