{
  "type": "Feature",
  "properties": {
    "gn:admin1_code":"9.0",
    "gn:asciiname":"Orovac",
    "gn:country_code":"ME",
    "gn:dem":913,
    "gn:feature_class":"P",
    "gn:feature_code":"PPL",
    "gn:name":"Orovac",
    "gn:population":0,
    "gn:timezone":"Europe/Podgorica",
    "iso:country":"ME",
    "name:srp_x_preferred":[
        "Orovac"
    ],
    "wof:name":"Orovac",
    "wof:placetype":"locality"
},
  "geometry": {"coordinates":[19.35472,42.84111],"type":"Point"}
}