{
  "type": "Feature",
  "properties": {
    "gn:admin1_code":"8.0",
    "gn:asciiname":"Grabe",
    "gn:country_code":"ME",
    "gn:dem":21,
    "gn:feature_class":"P",
    "gn:feature_code":"PPL",
    "gn:name":"Grabe",
    "gn:population":0,
    "gn:timezone":"Europe/Podgorica",
    "iso:country":"ME",
    "name:bos_x_preferred":[
        "Grabe"
    ],
    "name:ceb_x_preferred":[
        "Grabe"
    ],
    "name:deu_x_preferred":[
        "Grabe"
    ],
    "name:hrv_x_preferred":[
        "Grabe"
    ],
    "name:nld_x_preferred":[
        "Grabe"
    ],
    "name:slv_x_preferred":[
        "Grabe"
    ],
    "name:srp_x_preferred":[
        "\u0413\u0440\u0430\u0431\u0435"
    ],
    "name:swe_x_preferred":[
        "Grabe"
    ],
    "wof:name":"Grabe",
    "wof:placetype":"locality"
},
  "geometry": {"coordinates":[18.64194,42.44667000000001],"type":"Point"}
}