{
  "type": "Feature",
  "properties": {
    "gn:admin1_code":"8.0",
    "gn:asciiname":"Grabe",
    "gn:country_code":"ME",
    "gn:dem":21,
    "gn:feature_class":"P",
    "gn:feature_code":"PPL",
    "gn:name":"Grabe",
    "gn:population":0,
    "gn:timezone":"Europe/Podgorica",
    "iso:country":"ME",
    "wof:name":"Grabe",
    "wof:placetype":"locality"
},
  "geometry": {"coordinates":[18.64194,42.44667000000001],"type":"Point"}
}