{
  "type": "Feature",
  "properties": {
    "gn:admin1_code":"4.0",
    "gn:asciiname":"Rasovo",
    "gn:country_code":"ME",
    "gn:dem":562,
    "gn:feature_class":"P",
    "gn:feature_code":"PPLL",
    "gn:name":"Rasovo",
    "gn:population":0,
    "gn:timezone":"Europe/Podgorica",
    "iso:country":"ME",
    "wof:name":"Rasovo",
    "wof:placetype":"locality"
},
  "geometry": {"coordinates":[19.78361,43.06083],"type":"Point"}
}