{
  "type": "Feature",
  "properties": {
    "gn:admin1_code":"4.0",
    "gn:asciiname":"Dalovici",
    "gn:country_code":"ME",
    "gn:dem":1109,
    "gn:feature_class":"P",
    "gn:feature_code":"PPL",
    "gn:name":"\u00d0alovi\u0107i",
    "gn:population":0,
    "gn:timezone":"Europe/Podgorica",
    "iso:country":"ME",
    "name:srp_x_preferred":[
        "\u00d0alovi\u0107i"
    ],
    "wof:name":"Dalovici",
    "wof:placetype":"locality"
},
  "geometry": {"coordinates":[19.9475,43.07417],"type":"Point"}
}