{
  "type": "Feature",
  "properties": {
    "gn:admin1_code":"4.0",
    "gn:asciiname":"Stube",
    "gn:country_code":"ME",
    "gn:dem":1023,
    "gn:feature_class":"P",
    "gn:feature_code":"PPL",
    "gn:name":"Stube",
    "gn:population":0,
    "gn:timezone":"Europe/Podgorica",
    "iso:country":"ME",
    "name:fra_x_preferred":[
        "Stubo"
    ],
    "name:ron_x_preferred":[
        "Stubo"
    ],
    "name:slv_x_preferred":[
        "Stubo"
    ],
    "name:srp_x_preferred":[
        "\u0421\u0442\u0443\u0431\u043e"
    ],
    "name:und_x_variant":[
        "Stubao",
        "Stubo",
        "Stublo",
        "Stube"
    ],
    "wof:name":"Stube",
    "wof:placetype":"locality"
},
  "geometry": {"coordinates":[19.87778,43.03806],"type":"Point"}
}