{
  "type": "Feature",
  "properties": {
    "gn:admin1_code":"14.0",
    "gn:asciiname":"Vukasovici",
    "gn:country_code":"ME",
    "gn:dem":813,
    "gn:feature_class":"P",
    "gn:feature_code":"PPL",
    "gn:name":"Vukasovi\u0107i",
    "gn:population":0,
    "gn:timezone":"Europe/Podgorica",
    "iso:country":"ME",
    "name:srp_x_preferred":[
        "Vukasovi\u0107i"
    ],
    "wof:name":"Vukasovici",
    "wof:placetype":"locality"
},
  "geometry": {"coordinates":[18.98833,43.47],"type":"Point"}
}