{
  "type": "Feature",
  "properties": {
    "gn:admin1_code":"12.0",
    "gn:asciiname":"Kocane",
    "gn:country_code":"ME",
    "gn:dem":618,
    "gn:feature_class":"P",
    "gn:feature_code":"PPL",
    "gn:name":"Ko\u010dane",
    "gn:population":0,
    "gn:timezone":"Europe/Podgorica",
    "iso:country":"ME",
    "name:srp_x_preferred":[
        "Ko\u010dane"
    ],
    "wof:name":"Kocane",
    "wof:placetype":"locality"
},
  "geometry": {"coordinates":[18.91139,42.78972],"type":"Point"}
}