{
  "type": "Feature",
  "properties": {
    "gn:admin1_code":"6.0",
    "gn:asciiname":"Nerim",
    "gn:country_code":"ME",
    "gn:dem":739,
    "gn:feature_class":"P",
    "gn:feature_code":"PPL",
    "gn:name":"Nerim",
    "gn:population":0,
    "gn:timezone":"Europe/Podgorica",
    "iso:country":"ME",
    "name:srp_x_preferred":[
        "Nerim"
    ],
    "wof:name":"Nerim",
    "wof:placetype":"locality"
},
  "geometry": {"coordinates":[18.81139,42.56389],"type":"Point"}
}