{
  "type": "Feature",
  "properties": {
    "gn:admin1_code":"9.0",
    "gn:asciiname":"Liplja",
    "gn:country_code":"ME",
    "gn:dem":524,
    "gn:feature_class":"P",
    "gn:feature_code":"PPL",
    "gn:name":"Liplja",
    "gn:population":0,
    "gn:timezone":"Europe/Podgorica",
    "iso:country":"ME",
    "name:srp_x_preferred":[
        "Liplja"
    ],
    "wof:name":"Liplja",
    "wof:placetype":"locality"
},
  "geometry": {"coordinates":[19.37222,42.73528],"type":"Point"}
}