{
  "type": "Feature",
  "properties": {
    "gn:admin1_code":"14.0",
    "gn:asciiname":"Ulica",
    "gn:country_code":"ME",
    "gn:dem":1185,
    "gn:feature_class":"P",
    "gn:feature_code":"PPL",
    "gn:name":"Ulica",
    "gn:population":0,
    "gn:timezone":"Europe/Podgorica",
    "iso:country":"ME",
    "name:hrv_x_preferred":[
        "Ulica"
    ],
    "name:pol_x_preferred":[
        "Ulica"
    ],
    "name:slv_x_preferred":[
        "Ulica"
    ],
    "name:und_x_variant":[
        "Ulice",
        "Ulica"
    ],
    "wof:name":"Ulica",
    "wof:placetype":"locality"
},
  "geometry": {"coordinates":[19.12889,43.49694],"type":"Point"}
}