{
  "type": "Feature",
  "properties": {
    "gn:admin1_code":"9.0",
    "gn:asciiname":"Kozda",
    "gn:country_code":"ME",
    "gn:dem":258,
    "gn:feature_class":"P",
    "gn:feature_code":"PPL",
    "gn:name":"Ko\u017e\u0111a",
    "gn:population":0,
    "gn:timezone":"Europe/Podgorica",
    "iso:country":"ME",
    "name:srp_x_preferred":[
        "Ko\u017e\u0111a"
    ],
    "wof:name":"Kozda",
    "wof:placetype":"locality"
},
  "geometry": {"coordinates":[19.37778,42.72361],"type":"Point"}
}