{
  "type": "Feature",
  "properties": {
    "gn:admin1_code":"9.0",
    "gn:asciiname":"Kupusista",
    "gn:country_code":"ME",
    "gn:dem":715,
    "gn:feature_class":"P",
    "gn:feature_code":"PPL",
    "gn:name":"Kupusi\u0161ta",
    "gn:population":0,
    "gn:timezone":"Europe/Podgorica",
    "iso:country":"ME",
    "name:srp_x_preferred":[
        "Kupusi\u0161ta"
    ],
    "wof:name":"Kupusista",
    "wof:placetype":"locality"
},
  "geometry": {"coordinates":[19.43222,42.70278],"type":"Point"}
}