{
  "type": "Feature",
  "properties": {
    "gn:admin1_code":"9.0",
    "gn:asciiname":"Jabuka",
    "gn:country_code":"ME",
    "gn:dem":227,
    "gn:feature_class":"P",
    "gn:feature_code":"PPL",
    "gn:name":"Jabuka",
    "gn:population":0,
    "gn:timezone":"Europe/Podgorica",
    "iso:country":"ME",
    "name:srp_x_preferred":[
        "Jabuka"
    ],
    "wof:name":"Jabuka",
    "wof:placetype":"locality"
},
  "geometry": {"coordinates":[19.40111,42.71583],"type":"Point"}
}