{
  "type": "Feature",
  "properties": {
    "gn:admin1_code":"23.0",
    "gn:asciiname":"Kalica",
    "gn:country_code":"ME",
    "gn:dem":1219,
    "gn:feature_class":"P",
    "gn:feature_code":"PPL",
    "gn:name":"Kalica",
    "gn:population":0,
    "gn:timezone":"Europe/Podgorica",
    "iso:country":"ME",
    "name:srp_x_preferred":[
        "Kalica"
    ],
    "wof:name":"Kalica",
    "wof:placetype":"locality"
},
  "geometry": {"coordinates":[20.03722,42.89028],"type":"Point"}
}