{
  "type": "Feature",
  "properties": {
    "gn:admin1_code":"8.0",
    "gn:asciiname":"Lucici",
    "gn:country_code":"ME",
    "gn:dem":120,
    "gn:feature_class":"P",
    "gn:feature_code":"PPL",
    "gn:name":"Lu\u010di\u0107i",
    "gn:population":0,
    "gn:timezone":"Europe/Podgorica",
    "iso:country":"ME",
    "name:srp_x_preferred":[
        "Lu\u010di\u0107i"
    ],
    "wof:name":"Lucici",
    "wof:placetype":"locality"
},
  "geometry": {"coordinates":[18.47528,42.48056],"type":"Point"}
}