{
  "type": "Feature",
  "properties": {
    "gn:admin1_code":"16.0",
    "gn:asciiname":"Podgrad",
    "gn:country_code":"ME",
    "gn:dem":866,
    "gn:feature_class":"P",
    "gn:feature_code":"PPL",
    "gn:name":"Podgrad",
    "gn:population":0,
    "gn:timezone":"Europe/Podgorica",
    "iso:country":"ME",
    "name:srp_x_preferred":[
        "Podgrad"
    ],
    "wof:name":"Podgrad",
    "wof:placetype":"locality"
},
  "geometry": {"coordinates":[19.44611,42.48167],"type":"Point"}
}