{
  "type": "Feature",
  "properties": {
    "gn:country":"ME",
    "gn:fcode":"PPLL",
    "gn:population":106,
    "iso:country":"ME",
    "qs_pg:aaroncc":"ME",
    "qs_pg:gn_country":"ME",
    "qs_pg:gn_fcode":"PPLL",
    "qs_pg:gn_pop":106,
    "qs_pg:name":"Meterizi",
    "qs_pg:photos_9r":0,
    "qs_pg:photos_sr":0,
    "qs_pg:pop_sr":1,
    "qs_pg:qs_pg_placetype":"locality",
    "wof:name":"Meterizi",
    "wof:placetype":"locality",
    "wof:population":106
},
  "geometry": {"coordinates":[19.05611,42.37778],"type":"Point"}
}