{
  "type": "Feature",
  "properties": {
    "gn:admin1_code":"18.0",
    "gn:asciiname":"Seoca",
    "gn:country_code":"ME",
    "gn:dem":1188,
    "gn:feature_class":"P",
    "gn:feature_code":"PPL",
    "gn:name":"Seoca",
    "gn:population":0,
    "gn:timezone":"Europe/Podgorica",
    "iso:country":"ME",
    "name:bos_x_preferred":[
        "Seoca"
    ],
    "name:deu_x_preferred":[
        "Seoca"
    ],
    "name:fra_x_preferred":[
        "Seoca"
    ],
    "name:hrv_x_preferred":[
        "Seoca"
    ],
    "name:hun_x_preferred":[
        "Seoca"
    ],
    "name:nld_x_preferred":[
        "Seoca"
    ],
    "name:slv_x_preferred":[
        "Seoca"
    ],
    "name:srp_x_preferred":[
        "Seoca"
    ],
    "name:srp_x_variant":[
        "\u0421\u0435\u043e\u0446\u0430"
    ],
    "wof:name":"Seoca",
    "wof:placetype":"locality"
},
  "geometry": {"coordinates":[19.20167,42.93694],"type":"Point"}
}