{
  "type": "Feature",
  "properties": {
    "gn:admin1_code":"8.0",
    "gn:asciiname":"Kabala",
    "gn:country_code":"ME",
    "gn:dem":191,
    "gn:feature_class":"P",
    "gn:feature_code":"PPL",
    "gn:name":"Kabala",
    "gn:population":0,
    "gn:timezone":"Europe/Podgorica",
    "iso:country":"ME",
    "name:srp_x_preferred":[
        "Kabala"
    ],
    "wof:name":"Kabala",
    "wof:placetype":"locality"
},
  "geometry": {"coordinates":[18.56278,42.42417],"type":"Point"}
}