{
  "type": "Feature",
  "properties": {
    "gn:admin1_code":"14.0",
    "gn:asciiname":"Oglavina",
    "gn:country_code":"ME",
    "gn:dem":1070,
    "gn:feature_class":"P",
    "gn:feature_code":"PPL",
    "gn:name":"Oglavina",
    "gn:population":0,
    "gn:timezone":"Europe/Podgorica",
    "iso:country":"ME",
    "name:srp_x_preferred":[
        "Oglavina"
    ],
    "wof:name":"Oglavina",
    "wof:placetype":"locality"
},
  "geometry": {"coordinates":[19.12972,43.4675],"type":"Point"}
}