{
  "type": "Feature",
  "properties": {
    "iso:country":"ME",
    "name:bos_x_preferred":[
        "Popovi\u0107i"
    ],
    "name:fra_x_preferred":[
        "Popovi\u0107i"
    ],
    "name:hbs_x_preferred":[
        "\u041f\u043e\u043f\u043e\u0432\u0438\u045b\u0438"
    ],
    "name:hrv_x_preferred":[
        "Popovi\u0107i"
    ],
    "name:hun_x_preferred":[
        "Popovi\u0107i"
    ],
    "name:slv_x_preferred":[
        "Popovi\u0107i"
    ],
    "name:srp_x_preferred":[
        "\u041f\u043e\u043f\u043e\u0432\u0438\u045b\u0438"
    ],
    "name:srp_x_variant":[
        "Popovi\u0107i"
    ],
    "qs:gn_country":"ME",
    "qs:gn_fcode":"PPL",
    "qs:gn_pop":5,
    "qs:name":"Popovi\u0107i",
    "qs:name_adm0":"Hrvatska",
    "qs:name_adm1":"Dubrova\u010dko-neretvanska",
    "qs:photos":0,
    "qs:photos_1k":0,
    "qs:photos_9k":1,
    "qs:photos_9r":1,
    "qs:photos_all":1,
    "qs:photos_sr":0,
    "qs:placetype":"Town",
    "qs:pop_sr":"1",
    "qs:woe_adm0":23424843,
    "wd:wordcount":48,
    "wof:name":"Popovi\u0107i",
    "wof:placetype":"locality",
    "wof:population":5
},
  "geometry": {"coordinates":[18.75389,42.30667],"type":"Point"}
}