{
  "type": "Feature",
  "properties": {
    "gn:admin1_code":"5.0",
    "gn:asciiname":"Novoselje",
    "gn:country_code":"ME",
    "gn:dem":501,
    "gn:feature_class":"P",
    "gn:feature_code":"PPL",
    "gn:name":"Novoselje",
    "gn:population":0,
    "gn:timezone":"Europe/Podgorica",
    "iso:country":"ME",
    "name:srp_x_preferred":[
        "Novoselje"
    ],
    "wof:name":"Novoselje",
    "wof:placetype":"locality"
},
  "geometry": {"coordinates":[18.95611,42.21972],"type":"Point"}
}