{
  "type": "Feature",
  "properties": {
    "gn:admin1_code":"6.0",
    "gn:asciiname":"Donji Pipac",
    "gn:country_code":"ME",
    "gn:dem":94,
    "gn:feature_class":"P",
    "gn:feature_code":"PPL",
    "gn:name":"Donji Pipac",
    "gn:population":0,
    "gn:timezone":"Europe/Podgorica",
    "iso:country":"ME",
    "name:und_x_variant":[
        "Pipac",
        "Donji Pipac"
    ],
    "wof:name":"Donji Pipac",
    "wof:placetype":"locality"
},
  "geometry": {"coordinates":[19.10806,42.36361],"type":"Point"}
}