{
  "type": "Feature",
  "properties": {
    "gn:admin1_code":"12.0",
    "gn:asciiname":"Drenovci",
    "gn:country_code":"ME",
    "gn:dem":998,
    "gn:feature_class":"P",
    "gn:feature_code":"PPL",
    "gn:name":"Drenovci",
    "gn:population":0,
    "gn:timezone":"Europe/Podgorica",
    "iso:country":"ME",
    "name:bos_x_preferred":[
        "Drenovci"
    ],
    "name:ceb_x_preferred":[
        "Drenovci"
    ],
    "name:fra_x_preferred":[
        "Drenovci"
    ],
    "name:hrv_x_preferred":[
        "Drenovci"
    ],
    "name:ita_x_preferred":[
        "Drenovci"
    ],
    "name:nld_x_preferred":[
        "Drenovci"
    ],
    "name:pol_x_preferred":[
        "Gmina Drenovci"
    ],
    "name:ron_x_preferred":[
        "Comuna Drenovci"
    ],
    "name:slv_x_preferred":[
        "Drenovci"
    ],
    "name:srp_x_preferred":[
        "Drenovci"
    ],
    "name:srp_x_variant":[
        "\u0414\u0440\u0435\u043d\u043e\u0432\u0446\u0438"
    ],
    "name:ukr_x_preferred":[
        "\u0414\u0440\u0435\u043d\u043e\u0432\u0446\u0456"
    ],
    "name:war_x_preferred":[
        "Drenovci"
    ],
    "wof:name":"Drenovci",
    "wof:placetype":"locality"
},
  "geometry": {"coordinates":[18.50083,42.93333],"type":"Point"}
}