{
  "type": "Feature",
  "properties": {
    "gn:admin1_code":"1.0",
    "gn:asciiname":"Kuti",
    "gn:country_code":"ME",
    "gn:dem":1019,
    "gn:feature_class":"P",
    "gn:feature_code":"PPL",
    "gn:name":"Kuti",
    "gn:population":0,
    "gn:timezone":"Europe/Podgorica",
    "iso:country":"ME",
    "name:bos_x_preferred":[
        "Kuti"
    ],
    "name:ceb_x_preferred":[
        "Kuti"
    ],
    "name:deu_x_preferred":[
        "Kuti"
    ],
    "name:fra_x_preferred":[
        "Kuti"
    ],
    "name:hrv_x_preferred":[
        "Kuti"
    ],
    "name:pol_x_preferred":[
        "Kuti"
    ],
    "name:rus_x_preferred":[
        "\u041a\u0443\u0442\u0438"
    ],
    "name:slv_x_preferred":[
        "Kuti"
    ],
    "name:srp_x_preferred":[
        "Kuti"
    ],
    "name:srp_x_variant":[
        "\u041a\u0443\u0442\u0438"
    ],
    "name:swe_x_preferred":[
        "Kuti"
    ],
    "wof:name":"Kuti",
    "wof:placetype":"locality"
},
  "geometry": {"coordinates":[19.78556,42.61889],"type":"Point"}
}