{
  "type": "Feature",
  "properties": {
    "gn:admin1_code":"15.0",
    "gn:asciiname":"Seljani",
    "gn:country_code":"ME",
    "gn:dem":1005,
    "gn:feature_class":"P",
    "gn:feature_code":"PPLL",
    "gn:name":"Seljani",
    "gn:population":0,
    "gn:timezone":"Europe/Podgorica",
    "iso:country":"ME",
    "name:bos_x_preferred":[
        "Seljani"
    ],
    "name:fra_x_preferred":[
        "Seljani"
    ],
    "name:hrv_x_preferred":[
        "Seljani"
    ],
    "name:slv_x_preferred":[
        "Seljani"
    ],
    "name:srp_x_preferred":[
        "\u0421\u0435\u0459\u0430\u043d\u0438"
    ],
    "wof:name":"Seljani",
    "wof:placetype":"locality"
},
  "geometry": {"coordinates":[18.84528,43.09167],"type":"Point"}
}