{
  "type": "Feature",
  "properties": {
    "gn:admin1_code":"4.0",
    "gn:asciiname":"Dolina",
    "gn:country_code":"ME",
    "gn:dem":892,
    "gn:feature_class":"P",
    "gn:feature_code":"PPL",
    "gn:name":"Dolina",
    "gn:population":0,
    "gn:timezone":"Europe/Podgorica",
    "iso:country":"ME",
    "name:srp_x_preferred":[
        "Dolina"
    ],
    "wof:name":"Dolina",
    "wof:placetype":"locality"
},
  "geometry": {"coordinates":[19.72889,43.15861],"type":"Point"}
}