{
  "type": "Feature",
  "properties": {
    "gn:admin1_code":"16.0",
    "gn:asciiname":"Macaj",
    "gn:country_code":"ME",
    "gn:dem":576,
    "gn:feature_class":"P",
    "gn:feature_code":"PPL",
    "gn:name":"Ma\u010daj",
    "gn:population":0,
    "gn:timezone":"Europe/Podgorica",
    "iso:country":"ME",
    "name:srp_x_preferred":[
        "Ma\u010daj"
    ],
    "wof:name":"Macaj",
    "wof:placetype":"locality"
},
  "geometry": {"coordinates":[19.40861,42.36083],"type":"Point"}
}