{
  "type": "Feature",
  "properties": {
    "gn:admin1_code":"14.0",
    "gn:asciiname":"Lipova Ravan",
    "gn:country_code":"ME",
    "gn:dem":1138,
    "gn:feature_class":"P",
    "gn:feature_code":"PPL",
    "gn:name":"Lipova Ravan",
    "gn:population":0,
    "gn:timezone":"Europe/Podgorica",
    "iso:country":"ME",
    "name:srp_x_preferred":[
        "Lipova Ravan"
    ],
    "wof:name":"Lipova Ravan",
    "wof:placetype":"locality"
},
  "geometry": {"coordinates":[19.31889,43.11944],"type":"Point"}
}