{
  "type": "Feature",
  "properties": {
    "gn:admin1_code":"10.0",
    "gn:asciiname":"Muo",
    "gn:country_code":"ME",
    "gn:dem":10,
    "gn:feature_class":"P",
    "gn:feature_code":"PPL",
    "gn:name":"Muo",
    "gn:population":645,
    "gn:timezone":"Europe/Podgorica",
    "iso:country":"ME",
    "name:srp_x_preferred":[
        "Muo"
    ],
    "name:und_x_variant":[
        "Selo Muo",
        "Muo"
    ],
    "wof:name":"Muo",
    "wof:placetype":"locality",
    "wof:population":645
},
  "geometry": {"coordinates":[18.7575,42.43167],"type":"Point"}
}