{
  "type": "Feature",
  "properties": {
    "gn:country":"ME",
    "gn:fcode":"PPL",
    "gn:pop":147,
    "iso:country":"ME",
    "name:srp_x_preferred":[
        "Lalevi\u0107i"
    ],
    "qs:name":"Lalevi\u0107i",
    "qs:photos_9r":0,
    "qs:photos_sr":0,
    "qs:pop_sr":"1",
    "wd:wordcount":2727,
    "wof:name":"Lalevi\u0107i",
    "wof:placetype":"locality",
    "wof:population":147
},
  "geometry": {"coordinates":[19.09333,42.565],"type":"Point"}
}