{
  "type": "Feature",
  "properties": {
    "gn:admin1_code":"15.0",
    "gn:asciiname":"Brljevo",
    "gn:country_code":"ME",
    "gn:dem":1209,
    "gn:feature_class":"P",
    "gn:feature_code":"PPL",
    "gn:name":"Brljevo",
    "gn:population":0,
    "gn:timezone":"Europe/Podgorica",
    "iso:country":"ME",
    "name:srp_x_preferred":[
        "Brljevo"
    ],
    "wof:name":"Brljevo",
    "wof:placetype":"locality"
},
  "geometry": {"coordinates":[18.82917,43.18861],"type":"Point"}
}