{
  "type": "Feature",
  "properties": {
    "gn:admin1_code":"20.0",
    "gn:asciiname":"Denasevici",
    "gn:country_code":"ME",
    "gn:dem":295,
    "gn:feature_class":"P",
    "gn:feature_code":"PPL",
    "gn:name":"\u00d0ena\u0161evi\u0107i",
    "gn:population":0,
    "gn:timezone":"Europe/Podgorica",
    "iso:country":"ME",
    "name:und_x_variant":[
        "\u00d0ena\u0161i",
        "\u00d0ena\u0161evi\u0107i"
    ],
    "wof:name":"Denasevici",
    "wof:placetype":"locality"
},
  "geometry": {"coordinates":[19.31028,42.07667],"type":"Point"}
}