{
  "type": "Feature",
  "properties": {
    "gn:admin1_code":"16.0",
    "gn:asciiname":"Sinjac",
    "gn:country_code":"ME",
    "gn:dem":23,
    "gn:feature_class":"P",
    "gn:feature_code":"PPL",
    "gn:name":"Sinjac",
    "gn:population":0,
    "gn:timezone":"Europe/Podgorica",
    "iso:country":"ME",
    "name:ceb_x_preferred":[
        "Sinjac"
    ],
    "name:fra_x_preferred":[
        "Sinjac"
    ],
    "name:msa_x_preferred":[
        "Sinjac"
    ],
    "name:por_x_preferred":[
        "Sinjac"
    ],
    "name:slv_x_preferred":[
        "Sinjac"
    ],
    "name:srp_x_preferred":[
        "Sinjac"
    ],
    "name:srp_x_variant":[
        "\u0421\u0438\u045a\u0430\u0446"
    ],
    "wof:name":"Sinjac",
    "wof:placetype":"locality"
},
  "geometry": {"coordinates":[19.15028,42.36556],"type":"Point"}
}