{
  "type": "Feature",
  "properties": {
    "gn:admin1_code":"6.0",
    "gn:asciiname":"Kovacev Do",
    "gn:country_code":"ME",
    "gn:dem":948,
    "gn:feature_class":"P",
    "gn:feature_code":"PPL",
    "gn:name":"Kova\u010dev Do",
    "gn:population":0,
    "gn:timezone":"Europe/Podgorica",
    "iso:country":"ME",
    "name:srp_x_preferred":[
        "Kova\u010dev Do"
    ],
    "wof:name":"Kovacev Do",
    "wof:placetype":"locality"
},
  "geometry": {"coordinates":[18.76556,42.645],"type":"Point"}
}