{
  "type": "Feature",
  "properties": {
    "gn:admin1_code":"1.0",
    "gn:asciiname":"Gunjaje",
    "gn:country_code":"ME",
    "gn:dem":936,
    "gn:feature_class":"P",
    "gn:feature_code":"PPL",
    "gn:name":"Gunjaje",
    "gn:population":0,
    "gn:timezone":"Europe/Podgorica",
    "iso:country":"ME",
    "name:und_x_variant":[
        "Gunjaja",
        "Gunjaje"
    ],
    "wof:name":"Gunjaje",
    "wof:placetype":"locality"
},
  "geometry": {"coordinates":[19.80083,42.74667],"type":"Point"}
}