{
  "type": "Feature",
  "properties": {
    "gn:admin1_code":"6.0",
    "gn:asciiname":"Rzani Do",
    "gn:country_code":"ME",
    "gn:dem":600,
    "gn:feature_class":"P",
    "gn:feature_code":"PPL",
    "gn:name":"R\u017eani Do",
    "gn:population":0,
    "gn:timezone":"Europe/Podgorica",
    "iso:country":"ME",
    "name:srp_x_preferred":[
        "R\u017eani Do"
    ],
    "wof:name":"Rzani Do",
    "wof:placetype":"locality"
},
  "geometry": {"coordinates":[18.83861,42.51361],"type":"Point"}
}