{
  "type": "Feature",
  "properties": {
    "gn:admin1_code":"16.0",
    "gn:asciiname":"Klopot",
    "gn:country_code":"ME",
    "gn:dem":449,
    "gn:feature_class":"P",
    "gn:feature_code":"PPL",
    "gn:name":"Klopot",
    "gn:population":0,
    "gn:timezone":"Europe/Podgorica",
    "iso:country":"ME",
    "name:srp_x_preferred":[
        "Klopot"
    ],
    "wof:name":"Klopot",
    "wof:placetype":"locality"
},
  "geometry": {"coordinates":[19.37833,42.55944],"type":"Point"}
}