{
  "type": "Feature",
  "properties": {
    "gn:admin1_code":"4.0",
    "gn:asciiname":"Durino Brdo",
    "gn:country_code":"ME",
    "gn:dem":1340,
    "gn:feature_class":"P",
    "gn:feature_code":"PPL",
    "gn:name":"\u00d0urino Brdo",
    "gn:population":0,
    "gn:timezone":"Europe/Podgorica",
    "iso:country":"ME",
    "name:srp_x_preferred":[
        "\u00d0urino Brdo"
    ],
    "wof:name":"Durino Brdo",
    "wof:placetype":"locality"
},
  "geometry": {"coordinates":[19.55694,43.12444],"type":"Point"}
}