{
  "type": "Feature",
  "properties": {
    "gn:admin1_code":"10.0",
    "gn:asciiname":"Lastvica",
    "gn:country_code":"ME",
    "gn:dem":141,
    "gn:feature_class":"P",
    "gn:feature_code":"PPL",
    "gn:name":"Lastvica",
    "gn:population":0,
    "gn:timezone":"Europe/Podgorica",
    "iso:country":"ME",
    "name:und_x_variant":[
        "Lastva",
        "Lastvica"
    ],
    "wof:name":"Lastvica",
    "wof:placetype":"locality"
},
  "geometry": {"coordinates":[18.69528,42.49861],"type":"Point"}
}