{
  "type": "Feature",
  "properties": {
    "gn:admin1_code":"4.0",
    "gn:asciiname":"Cernica",
    "gn:country_code":"ME",
    "gn:dem":842,
    "gn:feature_class":"P",
    "gn:feature_code":"PPL",
    "gn:name":"Cernica",
    "gn:population":0,
    "gn:timezone":"Europe/Podgorica",
    "iso:country":"ME",
    "name:ceb_x_preferred":[
        "Comuna Cernica"
    ],
    "name:ita_x_preferred":[
        "Cernica"
    ],
    "name:msa_x_preferred":[
        "Cernica"
    ],
    "name:nld_x_preferred":[
        "Cernica"
    ],
    "name:pol_x_preferred":[
        "Gmina Cernica"
    ],
    "name:por_x_preferred":[
        "Cernica"
    ],
    "name:ron_x_preferred":[
        "Comuna Cernica"
    ],
    "name:srp_x_preferred":[
        "Cernica"
    ],
    "name:srp_x_variant":[
        "\u041e\u043f\u0448\u0442\u0438\u043d\u0430 \u0427\u0435\u0440\u043d\u0438\u043a\u0430"
    ],
    "name:ukr_x_preferred":[
        "\u0427\u0435\u0440\u043d\u0456\u043a\u0430"
    ],
    "name:vie_x_preferred":[
        "Cernica"
    ],
    "name:vol_x_preferred":[
        "Cernica"
    ],
    "name:zho_x_preferred":[
        "\u5207\u723e\u5c3c\u5361\u9109"
    ],
    "wof:name":"Cernica",
    "wof:placetype":"locality"
},
  "geometry": {"coordinates":[19.61972,43.04667],"type":"Point"}
}