{
  "type": "Feature",
  "properties": {
    "gn:admin1_code":"15.0",
    "gn:asciiname":"Rudinice",
    "gn:country_code":"ME",
    "gn:dem":1001,
    "gn:feature_class":"P",
    "gn:feature_code":"PPLL",
    "gn:name":"Rudinice",
    "gn:population":0,
    "gn:timezone":"Europe/Podgorica",
    "iso:country":"ME",
    "name:und_x_variant":[
        "Rudinica",
        "Rudinice"
    ],
    "wof:name":"Rudinice",
    "wof:placetype":"locality"
},
  "geometry": {"coordinates":[18.85833,43.07056],"type":"Point"}
}