{
  "type": "Feature",
  "properties": {
    "gn:admin1_code":"4.0",
    "gn:asciiname":"Obrov",
    "gn:country_code":"ME",
    "gn:dem":656,
    "gn:feature_class":"P",
    "gn:feature_code":"PPL",
    "gn:name":"Obrov",
    "gn:population":0,
    "gn:timezone":"Europe/Podgorica",
    "iso:country":"ME",
    "name:fra_x_preferred":[
        "Obrov"
    ],
    "name:ron_x_preferred":[
        "Obrov"
    ],
    "name:slv_x_preferred":[
        "Obrov"
    ],
    "name:srp_x_preferred":[
        "\u041e\u0431\u0440\u043e\u0432"
    ],
    "name:und_x_variant":[
        "Obrovo"
    ],
    "wof:name":"Obrov",
    "wof:placetype":"locality"
},
  "geometry": {"coordinates":[19.74944,43.02806],"type":"Point"}
}