{
  "type": "Feature",
  "properties": {
    "gn:admin1_code":"6.0",
    "gn:asciiname":"Vodni Do",
    "gn:country_code":"ME",
    "gn:dem":691,
    "gn:feature_class":"P",
    "gn:feature_code":"PPL",
    "gn:name":"Vodni Do",
    "gn:population":0,
    "gn:timezone":"Europe/Podgorica",
    "iso:country":"ME",
    "name:srp_x_preferred":[
        "Vodni Do"
    ],
    "wof:name":"Vodni Do",
    "wof:placetype":"locality"
},
  "geometry": {"coordinates":[18.77417,42.55222],"type":"Point"}
}