{
  "type": "Feature",
  "properties": {
    "gn:admin1_code":"16.0",
    "gn:asciiname":"Novo Selo",
    "gn:country_code":"ME",
    "gn:dem":73,
    "gn:feature_class":"P",
    "gn:feature_code":"PPL",
    "gn:name":"Novo Selo",
    "gn:population":0,
    "gn:timezone":"Europe/Podgorica",
    "iso:country":"ME",
    "name:srp_x_preferred":[
        "Novo Selo"
    ],
    "wof:name":"Novo Selo",
    "wof:placetype":"locality"
},
  "geometry": {"coordinates":[19.30833,42.42528],"type":"Point"}
}