{
  "type": "Feature",
  "properties": {
    "iso:country":"ME",
    "name:bos_x_preferred":[
        "Perast"
    ],
    "name:bul_x_preferred":[
        "\u041f\u0435\u0440\u0430\u0441\u0442"
    ],
    "name:ceb_x_preferred":[
        "Perast"
    ],
    "name:ces_x_preferred":[
        "Perast"
    ],
    "name:deu_x_preferred":[
        "Perast"
    ],
    "name:ell_x_preferred":[
        "\u03a0\u03ad\u03c1\u03b1\u03c3\u03c4"
    ],
    "name:eng_x_preferred":[
        "Perast"
    ],
    "name:est_x_preferred":[
        "Perast"
    ],
    "name:fas_x_preferred":[
        "\u067e\u0631\u0627\u0633\u062a"
    ],
    "name:fra_x_preferred":[
        "Perast"
    ],
    "name:hbs_x_preferred":[
        "Perast"
    ],
    "name:heb_x_preferred":[
        "\u05e4\u05e8\u05d0\u05e1\u05d8"
    ],
    "name:hrv_x_preferred":[
        "Perast"
    ],
    "name:hye_x_preferred":[
        "\u054a\u0565\u0580\u0561\u057d\u057f"
    ],
    "name:ind_x_preferred":[
        "Perast"
    ],
    "name:ita_x_preferred":[
        "Perasto"
    ],
    "name:jpn_x_preferred":[
        "\u307a\u30e9\u30b9\u30c8"
    ],
    "name:kor_x_preferred":[
        "\ud398\ub77c\uc2a4\ud2b8"
    ],
    "name:lat_x_preferred":[
        "Perastum"
    ],
    "name:lit_x_preferred":[
        "Perastas"
    ],
    "name:msa_x_preferred":[
        "Perast"
    ],
    "name:nld_x_preferred":[
        "Perast"
    ],
    "name:pol_x_preferred":[
        "Perast"
    ],
    "name:ron_x_preferred":[
        "Perast"
    ],
    "name:rus_x_preferred":[
        "\u041f\u0435\u0440\u0430\u0441\u0442"
    ],
    "name:slv_x_preferred":[
        "Perast"
    ],
    "name:spa_x_preferred":[
        "Perast"
    ],
    "name:srp_x_preferred":[
        "\u041f\u0435\u0440\u0430\u0441\u0442"
    ],
    "name:swe_x_preferred":[
        "Perast"
    ],
    "name:tur_x_preferred":[
        "Perast"
    ],
    "name:ukr_x_preferred":[
        "\u041f\u0435\u0440\u0430\u0441\u0442"
    ],
    "name:vec_x_preferred":[
        "Perasto"
    ],
    "name:zho_x_preferred":[
        "\u4f69\u62c9\u65af\u7279"
    ],
    "qs:gn_country":"ME",
    "qs:gn_fcode":"PPL",
    "qs:gn_pop":551,
    "qs:name":"Perast",
    "qs:name_adm0":"Montenegro",
    "qs:name_adm1":"Kotor",
    "qs:photos":1924,
    "qs:photos_1k":390,
    "qs:photos_9k":9,
    "qs:photos_9r":9,
    "qs:photos_all":1924,
    "qs:photos_sr":15,
    "qs:placetype":"Town",
    "qs:pop_sr":"2",
    "qs:woe_adm0":20069817,
    "wd:wordcount":1346,
    "wof:name":"Perast",
    "wof:placetype":"locality",
    "wof:population":551
},
  "geometry": {"coordinates":[18.69917,42.48694],"type":"Point"}
}