{
  "type": "Feature",
  "properties": {
    "gn:admin1_code":"16.0",
    "gn:asciiname":"Braka",
    "gn:country_code":"ME",
    "gn:dem":912,
    "gn:feature_class":"P",
    "gn:feature_code":"PPL",
    "gn:name":"Braka",
    "gn:population":0,
    "gn:timezone":"Europe/Podgorica",
    "iso:country":"ME",
    "name:srp_x_preferred":[
        "Braka"
    ],
    "wof:name":"Braka",
    "wof:placetype":"locality"
},
  "geometry": {"coordinates":[19.395,42.44028],"type":"Point"}
}