{
  "type": "Feature",
  "properties": {
    "gn:admin1_code":"16.0",
    "gn:asciiname":"Prelevici",
    "gn:country_code":"ME",
    "gn:dem":500,
    "gn:feature_class":"P",
    "gn:feature_code":"PPL",
    "gn:name":"Prelevi\u0107i",
    "gn:population":0,
    "gn:timezone":"Europe/Podgorica",
    "iso:country":"ME",
    "name:srp_x_preferred":[
        "Prelevi\u0107i"
    ],
    "wof:name":"Prelevici",
    "wof:placetype":"locality"
},
  "geometry": {"coordinates":[19.39833,42.48861],"type":"Point"}
}