{
  "type": "Feature",
  "properties": {
    "gn:admin1_code":"4.0",
    "gn:asciiname":"Brzava",
    "gn:country_code":"ME",
    "gn:dem":632,
    "gn:feature_class":"P",
    "gn:feature_code":"PPL",
    "gn:name":"Brzava",
    "gn:population":0,
    "gn:timezone":"Europe/Podgorica",
    "iso:country":"ME",
    "name:srp_x_preferred":[
        "Brzava"
    ],
    "wof:name":"Brzava",
    "wof:placetype":"locality"
},
  "geometry": {"coordinates":[19.80944,42.96389],"type":"Point"}
}