{
  "type": "Feature",
  "properties": {
    "gn:admin1_code":"9.0",
    "gn:asciiname":"Trmanje",
    "gn:country_code":"ME",
    "gn:dem":1018,
    "gn:feature_class":"P",
    "gn:feature_code":"PPL",
    "gn:name":"Trmanje",
    "gn:population":0,
    "gn:timezone":"Europe/Podgorica",
    "iso:country":"ME",
    "name:srp_x_preferred":[
        "Trmanje"
    ],
    "wof:name":"Trmanje",
    "wof:placetype":"locality"
},
  "geometry": {"coordinates":[19.34472,42.6475],"type":"Point"}
}