{
  "type": "Feature",
  "properties": {
    "gn:admin1_code":"4.0",
    "gn:asciiname":"Rodijelja",
    "gn:country_code":"ME",
    "gn:dem":556,
    "gn:feature_class":"P",
    "gn:feature_code":"PPL",
    "gn:name":"Rodijelja",
    "gn:population":0,
    "gn:timezone":"Europe/Podgorica",
    "iso:country":"ME",
    "name:fra_x_preferred":[
        "Rodijelja"
    ],
    "name:ron_x_preferred":[
        "Rodijelja"
    ],
    "name:slv_x_preferred":[
        "Rodijelja"
    ],
    "name:srp_x_preferred":[
        "\u0420\u043e\u0434\u0438\u0458\u0435\u0459\u0430"
    ],
    "name:und_x_variant":[
        "Radijelja"
    ],
    "wof:name":"Rodijelja",
    "wof:placetype":"locality"
},
  "geometry": {"coordinates":[19.80028,43.09889],"type":"Point"}
}