{
  "type": "Feature",
  "properties": {
    "gn:admin1_code":"20.0",
    "gn:asciiname":"Perovici",
    "gn:country_code":"ME",
    "gn:dem":68,
    "gn:feature_class":"P",
    "gn:feature_code":"PPL",
    "gn:name":"Perovi\u0107i",
    "gn:population":0,
    "gn:timezone":"Europe/Podgorica",
    "iso:country":"ME",
    "name:srp_x_preferred":[
        "Perovi\u0107i"
    ],
    "wof:name":"Perovici",
    "wof:placetype":"locality"
},
  "geometry": {"coordinates":[19.36111,42.08611],"type":"Point"}
}