{
  "type": "Feature",
  "properties": {
    "gn:admin1_code":"6.0",
    "gn:asciiname":"Droskoricki Dolovi",
    "gn:country_code":"ME",
    "gn:dem":929,
    "gn:feature_class":"P",
    "gn:feature_code":"PPL",
    "gn:name":"Dro\u0161kori\u010dki Dolovi",
    "gn:population":0,
    "gn:timezone":"Europe/Podgorica",
    "iso:country":"ME",
    "name:und_x_variant":[
        "Grahovski Dolovi",
        "Dro\u0161kori\u010dki Dolovi"
    ],
    "wof:name":"Droskoricki Dolovi",
    "wof:placetype":"locality"
},
  "geometry": {"coordinates":[18.71889,42.65222],"type":"Point"}
}