{
  "type": "Feature",
  "properties": {
    "gn:admin1_code":"14.0",
    "gn:asciiname":"Radeta",
    "gn:country_code":"ME",
    "gn:dem":904,
    "gn:feature_class":"P",
    "gn:feature_code":"PPL",
    "gn:name":"Radeta",
    "gn:population":0,
    "gn:timezone":"Europe/Podgorica",
    "iso:country":"ME",
    "name:srp_x_preferred":[
        "Radeta"
    ],
    "wof:name":"Radeta",
    "wof:placetype":"locality"
},
  "geometry": {"coordinates":[19.265,43.38944],"type":"Point"}
}