{
  "type": "Feature",
  "properties": {
    "gn:admin1_code":"11.0",
    "gn:asciiname":"Kruske",
    "gn:country_code":"ME",
    "gn:dem":1217,
    "gn:feature_class":"P",
    "gn:feature_code":"PPL",
    "gn:name":"Kru\u0161ke",
    "gn:population":0,
    "gn:timezone":"Europe/Podgorica",
    "iso:country":"ME",
    "wof:name":"Kruske",
    "wof:placetype":"locality"
},
  "geometry": {"coordinates":[19.45333,43.00972],"type":"Point"}
}