{
  "type": "Feature",
  "properties": {
    "gn:admin1_code":"14.0",
    "gn:asciiname":"Krstasi",
    "gn:country_code":"ME",
    "gn:dem":1165,
    "gn:feature_class":"P",
    "gn:feature_code":"PPL",
    "gn:name":"Krsta\u0161i",
    "gn:population":0,
    "gn:timezone":"Europe/Podgorica",
    "iso:country":"ME",
    "name:srp_x_preferred":[
        "Krsta\u0161i"
    ],
    "wof:name":"Krstasi",
    "wof:placetype":"locality"
},
  "geometry": {"coordinates":[19.23639,43.45194],"type":"Point"}
}