{
  "type": "Feature",
  "properties": {
    "gn:admin1_code":"14.0",
    "gn:asciiname":"Dublje",
    "gn:country_code":"ME",
    "gn:dem":976,
    "gn:feature_class":"P",
    "gn:feature_code":"PPL",
    "gn:name":"Dublje",
    "gn:population":0,
    "gn:timezone":"Europe/Podgorica",
    "iso:country":"ME",
    "name:ceb_x_preferred":[
        "Dublje"
    ],
    "name:fra_x_preferred":[
        "Dublje"
    ],
    "name:nld_x_preferred":[
        "Dublje"
    ],
    "name:por_x_preferred":[
        "Dublje"
    ],
    "name:slv_x_preferred":[
        "Dublje"
    ],
    "name:srp_x_preferred":[
        "\u0414\u0443\u0431\u0459\u0435"
    ],
    "name:swe_x_preferred":[
        "Dublje"
    ],
    "name:und_x_variant":[
        "Dubline",
        "Dublje"
    ],
    "wof:name":"Dublje",
    "wof:placetype":"locality"
},
  "geometry": {"coordinates":[19.16861,43.43444],"type":"Point"}
}