{
  "type": "Feature",
  "properties": {
    "gn:admin1_code":"9.0",
    "gn:asciiname":"Lijepi Brijeg",
    "gn:country_code":"ME",
    "gn:dem":511,
    "gn:feature_class":"P",
    "gn:feature_code":"PPL",
    "gn:name":"Lijepi Brijeg",
    "gn:population":0,
    "gn:timezone":"Europe/Podgorica",
    "iso:country":"ME",
    "name:srp_x_preferred":[
        "Lijepi Brijeg"
    ],
    "wof:name":"Lijepi Brijeg",
    "wof:placetype":"locality"
},
  "geometry": {"coordinates":[19.34944,42.70028],"type":"Point"}
}