{
  "type": "Feature",
  "properties": {
    "gn:admin1_code":"16.0",
    "gn:asciiname":"Mitrovici",
    "gn:country_code":"ME",
    "gn:dem":20,
    "gn:feature_class":"P",
    "gn:feature_code":"PPL",
    "gn:name":"Mitrovi\u0107i",
    "gn:population":0,
    "gn:timezone":"Europe/Podgorica",
    "iso:country":"ME",
    "name:srp_x_preferred":[
        "Mitrovi\u0107i"
    ],
    "wof:name":"Mitrovici",
    "wof:placetype":"locality"
},
  "geometry": {"coordinates":[19.22611,42.3675],"type":"Point"}
}