{
  "type": "Feature",
  "properties": {
    "gn:admin1_code":"11.0",
    "gn:asciiname":"Pod Milojevica",
    "gn:country_code":"ME",
    "gn:dem":846,
    "gn:feature_class":"P",
    "gn:feature_code":"PPL",
    "gn:name":"Pod Milojevi\u0107a",
    "gn:population":0,
    "gn:timezone":"Europe/Podgorica",
    "iso:country":"ME",
    "name:und_x_variant":[
        "Pod Miljevi\u0107a",
        "Pod Milojevi\u0107a"
    ],
    "wof:name":"Pod Milojevica",
    "wof:placetype":"locality"
},
  "geometry": {"coordinates":[19.53028,42.97194],"type":"Point"}
}