{
  "type": "Feature",
  "properties": {
    "gn:admin1_code":"12.0",
    "gn:asciiname":"Gornje Kunovo",
    "gn:country_code":"ME",
    "gn:dem":875,
    "gn:feature_class":"P",
    "gn:feature_code":"PPL",
    "gn:name":"Gornje Kunovo",
    "gn:population":0,
    "gn:timezone":"Europe/Podgorica",
    "iso:country":"ME",
    "name:srp_x_preferred":[
        "Gornje Kunovo"
    ],
    "wof:name":"Gornje Kunovo",
    "wof:placetype":"locality"
},
  "geometry": {"coordinates":[19.0375,42.7875],"type":"Point"}
}