{
  "type": "Feature",
  "properties": {
    "gn:admin1_code":"14.0",
    "gn:asciiname":"Kartali",
    "gn:country_code":"ME",
    "gn:dem":1129,
    "gn:feature_class":"P",
    "gn:feature_code":"PPL",
    "gn:name":"Kartali",
    "gn:population":0,
    "gn:timezone":"Europe/Podgorica",
    "iso:country":"ME",
    "name:srp_x_preferred":[
        "Kartali"
    ],
    "wof:name":"Kartali",
    "wof:placetype":"locality"
},
  "geometry": {"coordinates":[19.44611,43.26444],"type":"Point"}
}