{
  "type": "Feature",
  "properties": {
    "gn:country":"ME",
    "gn:fcode":"PPL",
    "gn:pop":5,
    "iso:country":"ME",
    "name:dut_x_preferred":[
        "Dub"
    ],
    "name:eng_x_preferred":[
        "Dub"
    ],
    "name:fre_x_preferred":[
        "Dub"
    ],
    "name:rum_x_preferred":[
        "Dub"
    ],
    "name:slv_x_preferred":[
        "Dub"
    ],
    "name:srp_x_preferred":[
        "Dub"
    ],
    "name:ukr_x_preferred":[
        "\u0414\u0443\u0431"
    ],
    "qs:name":"Dub",
    "qs:photos_9r":0,
    "qs:photos_sr":0,
    "qs:pop_sr":"1",
    "wd:wordcount":533,
    "wof:name":"Dub",
    "wof:placetype":"locality",
    "wof:population":5
},
  "geometry": {"coordinates":[18.76472,42.38667],"type":"Point"}
}