{
  "type": "Feature",
  "properties": {
    "gn:country":"ME",
    "gn:fcode":"PPL",
    "gn:population":5,
    "iso:country":"ME",
    "name:ell_x_preferred":[
        "\u039d\u03c4\u03bf\u03c5\u03bc\u03c0"
    ],
    "name:eng_x_preferred":[
        "Dub"
    ],
    "name:fra_x_preferred":[
        "Dub"
    ],
    "name:nld_x_preferred":[
        "Dub"
    ],
    "name:ron_x_preferred":[
        "Dub"
    ],
    "name:slv_x_preferred":[
        "Dub"
    ],
    "name:srp_x_preferred":[
        "Dub"
    ],
    "name:srp_x_variant":[
        "\u0414\u0443\u0431"
    ],
    "name:ukr_x_preferred":[
        "\u0414\u0443\u0431"
    ],
    "qs:name":"Dub",
    "qs:photos_9r":0,
    "qs:photos_sr":0,
    "qs:pop_sr":"1",
    "wd:wordcount":533,
    "wof:name":"Dub",
    "wof:placetype":"locality",
    "wof:population":5
},
  "geometry": {"coordinates":[18.76472,42.38667],"type":"Point"}
}