{
  "type": "Feature",
  "properties": {
    "gn:country":"ME",
    "gn:fcode":"PPL",
    "gn:pop":182,
    "iso:country":"ME",
    "name:srp_x_preferred":[
        "Buronji"
    ],
    "qs:name":"Buronji",
    "qs:photos_9r":0,
    "qs:photos_sr":0,
    "qs:pop_sr":"1",
    "wof:name":"Buronji",
    "wof:placetype":"locality",
    "wof:population":182
},
  "geometry": {"coordinates":[19.10194,42.43056],"type":"Point"}
}