{
  "type": "Feature",
  "properties": {
    "gn:admin1_code":"6.0",
    "gn:asciiname":"Brestovi",
    "gn:country_code":"ME",
    "gn:dem":900,
    "gn:feature_class":"P",
    "gn:feature_code":"PPL",
    "gn:name":"Brestovi",
    "gn:population":0,
    "gn:timezone":"Europe/Podgorica",
    "iso:country":"ME",
    "name:srp_x_preferred":[
        "Brestovi"
    ],
    "wof:name":"Brestovi",
    "wof:placetype":"locality"
},
  "geometry": {"coordinates":[18.90944,42.55722],"type":"Point"}
}