{
  "type": "Feature",
  "properties": {
    "gn:admin1_code":"15.0",
    "gn:asciiname":"Brijeg",
    "gn:country_code":"ME",
    "gn:dem":868,
    "gn:feature_class":"P",
    "gn:feature_code":"PPLL",
    "gn:name":"Brijeg",
    "gn:population":0,
    "gn:timezone":"Europe/Podgorica",
    "iso:country":"ME",
    "wof:name":"Brijeg",
    "wof:placetype":"locality"
},
  "geometry": {"coordinates":[18.88778,43.34861],"type":"Point"}
}