{
  "type": "Feature",
  "properties": {
    "gn:admin1_code":"16.0",
    "gn:asciiname":"Ubli",
    "gn:country_code":"ME",
    "gn:dem":477,
    "gn:feature_class":"P",
    "gn:feature_code":"PPL",
    "gn:name":"Ubli",
    "gn:population":0,
    "gn:timezone":"Europe/Podgorica",
    "iso:country":"ME",
    "name:ceb_x_preferred":[
        "Ubli"
    ],
    "name:fra_x_preferred":[
        "Ubli"
    ],
    "name:hrv_x_preferred":[
        "Ubli"
    ],
    "name:srp_x_preferred":[
        "Ubli"
    ],
    "name:srp_x_variant":[
        "\u0423\u0431\u043b\u0438"
    ],
    "name:swe_x_preferred":[
        "Ubli"
    ],
    "wof:name":"Ubli",
    "wof:placetype":"locality"
},
  "geometry": {"coordinates":[19.39583,42.49056],"type":"Point"}
}