{
  "type": "Feature",
  "properties": {
    "gn:admin1_code":"2.0",
    "gn:asciiname":"Dracevica",
    "gn:country_code":"ME",
    "gn:dem":251,
    "gn:feature_class":"P",
    "gn:feature_code":"PPL",
    "gn:name":"Dra\u010devica",
    "gn:population":0,
    "gn:timezone":"Europe/Podgorica",
    "iso:country":"ME",
    "name:und_x_variant":[
        "Dra\u010devico",
        "Dra\u010devica"
    ],
    "wof:name":"Dracevica",
    "wof:placetype":"locality"
},
  "geometry": {"coordinates":[19.19028,42.18556],"type":"Point"}
}