{
  "type": "Feature",
  "properties": {
    "gn:admin1_code":"2.0",
    "gn:asciiname":"Dobra Voda",
    "gn:country_code":"ME",
    "gn:dem":213,
    "gn:feature_class":"P",
    "gn:feature_code":"PPLL",
    "gn:name":"Dobra Voda",
    "gn:population":995,
    "gn:timezone":"Europe/Podgorica",
    "iso:country":"ME",
    "name:rus_x_preferred":[
        "\u0414\u043e\u0431\u0440\u0430 \u0412\u043e\u0434\u0430"
    ],
    "name:srp_x_preferred":[
        "Dobra Voda"
    ],
    "wof:name":"Dobra Voda",
    "wof:placetype":"locality",
    "wof:population":995
},
  "geometry": {"coordinates":[19.14389,42.04889],"type":"Point"}
}