{
  "type": "Feature",
  "properties": {
    "gn:country":"ME",
    "gn:fcode":"PPL",
    "gn:pop":493,
    "iso:country":"ME",
    "name:eng_x_preferred":[
        "Ubli"
    ],
    "name:fas_x_preferred":[
        "\u06cc\u0648\u0628\u0644\u06cc\u060c \u067e\u062f\u06af\u0631\u06cc\u06a9\u0627"
    ],
    "name:fra_x_preferred":[
        "Ubli"
    ],
    "name:nld_x_preferred":[
        "Ubli"
    ],
    "name:ron_x_preferred":[
        "Ubli"
    ],
    "name:slv_x_preferred":[
        "Ubli"
    ],
    "name:srp_x_preferred":[
        "Ubli"
    ],
    "name:swe_x_preferred":[
        "\u017divkovi\u0107i"
    ],
    "name:urd_x_preferred":[
        "\u0627\u0628\u0644\u06cc\u060c \u067e\u0648\u0688\u06af\u0648\u0631\u06cc\u06a9\u0627"
    ],
    "qs:name":"Ubli",
    "qs:photos_9r":0,
    "qs:photos_sr":0,
    "qs:pop_sr":"2",
    "wd:wordcount":58,
    "wof:name":"Ubli",
    "wof:placetype":"locality",
    "wof:population":493
},
  "geometry": {"coordinates":[19.25667,42.58417],"type":"Point"}
}