{
  "type": "Feature",
  "properties": {
    "gn:country":"ME",
    "gn:fcode":"PPL",
    "gn:population":5,
    "iso:country":"ME",
    "name:bos_x_preferred":[
        "Staje"
    ],
    "name:bul_x_preferred":[
        "\u0421\u0442\u0430\u0435"
    ],
    "name:ceb_x_preferred":[
        "Staje"
    ],
    "name:nld_x_preferred":[
        "Staje"
    ],
    "name:pol_x_preferred":[
        "Staje"
    ],
    "name:ron_x_preferred":[
        "Staje"
    ],
    "name:slv_x_preferred":[
        "Staje"
    ],
    "name:srp_x_preferred":[
        "Staje"
    ],
    "name:ukr_x_preferred":[
        "\u0421\u0442\u0430\u0454"
    ],
    "qs:name":"Staje",
    "qs:photos_9r":0,
    "qs:photos_sr":0,
    "qs:pop_sr":"1",
    "wd:wordcount":49,
    "wof:name":"Staje",
    "wof:placetype":"locality",
    "wof:population":5
},
  "geometry": {"coordinates":[18.89833,42.49167],"type":"Point"}
}