{
  "type": "Feature",
  "properties": {
    "gn:admin1_code":"6.0",
    "gn:asciiname":"Rpavac",
    "gn:country_code":"ME",
    "gn:dem":778,
    "gn:feature_class":"P",
    "gn:feature_code":"PPL",
    "gn:name":"Rpavac",
    "gn:population":0,
    "gn:timezone":"Europe/Podgorica",
    "iso:country":"ME",
    "name:und_x_variant":[
        "Orpovac",
        "Rvavac",
        "Rpavac"
    ],
    "wof:name":"Rpavac",
    "wof:placetype":"locality"
},
  "geometry": {"coordinates":[18.76917000000001,42.54389000000001],"type":"Point"}
}