{
  "type": "Feature",
  "properties": {
    "gn:country":"ME",
    "gn:fcode":"PPLL",
    "gn:pop":170,
    "iso:country":"ME",
    "qs:name":"Sotoni\u0107i",
    "qs:photos_9r":0,
    "qs:photos_sr":0,
    "qs:pop_sr":"1",
    "wof:name":"Sotoni\u0107i",
    "wof:placetype":"locality",
    "wof:population":170
},
  "geometry": {"coordinates":[19.04917,42.23444],"type":"Point"}
}