{
  "type": "Feature",
  "properties": {
    "gn:admin1_code":"14.0",
    "gn:asciiname":"Nadgora",
    "gn:country_code":"ME",
    "gn:dem":1535,
    "gn:feature_class":"P",
    "gn:feature_code":"PPL",
    "gn:name":"Nadgora",
    "gn:population":0,
    "gn:timezone":"Europe/Podgorica",
    "iso:country":"ME",
    "name:srp_x_preferred":[
        "Nadgora"
    ],
    "wof:name":"Nadgora",
    "wof:placetype":"locality"
},
  "geometry": {"coordinates":[19.09361,43.18417],"type":"Point"}
}