{
  "type": "Feature",
  "properties": {
    "gn:country":"ME",
    "gn:fcode":"PPL",
    "gn:pop":5,
    "iso:country":"ME",
    "name:srp_x_preferred":[
        "Kadaru\u0161a"
    ],
    "qs:name":"Kadaru\u0161a",
    "qs:photos_9r":0,
    "qs:photos_sr":0,
    "qs:pop_sr":"1",
    "wof:name":"Kadaru\u0161a",
    "wof:placetype":"locality",
    "wof:population":5
},
  "geometry": {"coordinates":[18.94444,42.34417],"type":"Point"}
}