{
  "type": "Feature",
  "properties": {
    "gn:admin1_code":"16.0",
    "gn:asciiname":"Dedinice",
    "gn:country_code":"ME",
    "gn:dem":968,
    "gn:feature_class":"P",
    "gn:feature_code":"PPL",
    "gn:name":"Dedinice",
    "gn:population":0,
    "gn:timezone":"Europe/Podgorica",
    "iso:country":"ME",
    "name:srp_x_preferred":[
        "Dedinice"
    ],
    "wof:name":"Dedinice",
    "wof:placetype":"locality"
},
  "geometry": {"coordinates":[19.44639,42.6375],"type":"Point"}
}