{
  "type": "Feature",
  "properties": {
    "gn:admin1_code":"6.0",
    "gn:asciiname":"Grandov Do",
    "gn:country_code":"ME",
    "gn:dem":884,
    "gn:feature_class":"P",
    "gn:feature_code":"PPL",
    "gn:name":"Grandov Do",
    "gn:population":0,
    "gn:timezone":"Europe/Podgorica",
    "iso:country":"ME",
    "name:srp_x_preferred":[
        "Grandov Do"
    ],
    "wof:name":"Grandov Do",
    "wof:placetype":"locality"
},
  "geometry": {"coordinates":[18.72639,42.59361],"type":"Point"}
}