{
  "type": "Feature",
  "properties": {
    "gn:admin1_code":"10.0",
    "gn:asciiname":"Ljeskovi Do",
    "gn:country_code":"ME",
    "gn:dem":917,
    "gn:feature_class":"P",
    "gn:feature_code":"PPL",
    "gn:name":"Ljeskovi Do",
    "gn:population":0,
    "gn:timezone":"Europe/Podgorica",
    "iso:country":"ME",
    "name:srp_x_preferred":[
        "Ljeskovi Do"
    ],
    "wof:name":"Ljeskovi Do",
    "wof:placetype":"locality"
},
  "geometry": {"coordinates":[18.62583,42.55444],"type":"Point"}
}