{
  "type": "Feature",
  "properties": {
    "gn:admin1_code":"6.0",
    "gn:asciiname":"Dajcin Do",
    "gn:country_code":"ME",
    "gn:dem":1215,
    "gn:feature_class":"P",
    "gn:feature_code":"PPL",
    "gn:name":"Daj\u010din Do",
    "gn:population":0,
    "gn:timezone":"Europe/Podgorica",
    "iso:country":"ME",
    "name:und_x_variant":[
        "Doj\u010din Do",
        "Daj\u010din Do"
    ],
    "wof:name":"Dajcin Do",
    "wof:placetype":"locality"
},
  "geometry": {"coordinates":[18.8175,42.65306],"type":"Point"}
}