{
  "type": "Feature",
  "properties": {
    "gn:country":"ME",
    "gn:fcode":"PPL",
    "gn:population":5,
    "iso:country":"ME",
    "name:srp_x_preferred":[
        "Luki\u0107i"
    ],
    "qs:name":"Luki\u0107i",
    "qs:photos_9r":0,
    "qs:photos_sr":0,
    "qs:pop_sr":"1",
    "wof:name":"Luki\u0107i",
    "wof:placetype":"locality",
    "wof:population":5
},
  "geometry": {"coordinates":[19.17889,42.16833],"type":"Point"}
}