{
  "type": "Feature",
  "properties": {
    "gn:country":"ME",
    "gn:fcode":"PPL",
    "gn:pop":66,
    "iso:country":"ME",
    "name:bos_x_preferred":[
        "Vrba"
    ],
    "name:ceb_x_preferred":[
        "Vrba"
    ],
    "name:ces_x_preferred":[
        "Vrba"
    ],
    "name:deu_x_preferred":[
        "Vrba"
    ],
    "name:fra_x_preferred":[
        "Vrba"
    ],
    "name:hrv_x_preferred":[
        "Vrba"
    ],
    "name:ita_x_preferred":[
        "Vrba"
    ],
    "name:nld_x_preferred":[
        "Vrba"
    ],
    "name:rus_x_preferred":[
        "\u0412\u0440\u0431\u0430"
    ],
    "name:slv_x_preferred":[
        "Vrba"
    ],
    "name:srp_x_preferred":[
        "Vrba"
    ],
    "name:srp_x_variant":[
        "\u0412\u0440\u0431\u0430"
    ],
    "name:swe_x_preferred":[
        "Vrba"
    ],
    "name:ukr_x_preferred":[
        "\u0412\u0440\u0431\u0430"
    ],
    "qs:name":"Vrba",
    "qs:photos_9r":0,
    "qs:photos_sr":0,
    "qs:pop_sr":"1",
    "wd:wordcount":391,
    "wof:name":"Vrba",
    "wof:placetype":"locality",
    "wof:population":66
},
  "geometry": {"coordinates":[18.91167,42.25],"type":"Point"}
}