{
  "type": "Feature",
  "properties": {
    "gn:country":"ME",
    "gn:fcode":"PPL",
    "gn:pop":66,
    "iso:country":"ME",
    "name:srp_x_preferred":[
        "Vrba"
    ],
    "qs:name":"Vrba",
    "qs:photos_9r":0,
    "qs:photos_sr":0,
    "qs:pop_sr":"1",
    "wd:wordcount":391,
    "wof:name":"Vrba",
    "wof:placetype":"locality",
    "wof:population":66
},
  "geometry": {"coordinates":[18.91167,42.25],"type":"Point"}
}