{
  "type": "Feature",
  "properties": {
    "gn:admin1_code":"4.0",
    "gn:asciiname":"Dobrodole",
    "gn:country_code":"ME",
    "gn:dem":1275,
    "gn:feature_class":"P",
    "gn:feature_code":"PPL",
    "gn:name":"Dobrodole",
    "gn:population":0,
    "gn:timezone":"Europe/Podgorica",
    "iso:country":"ME",
    "name:und_x_variant":[
        "Dobrodol",
        "Dobrdoli",
        "Dob\u00ebrdol",
        "Dobrodole"
    ],
    "wof:name":"Dobrodole",
    "wof:placetype":"locality"
},
  "geometry": {"coordinates":[19.99694,42.96472],"type":"Point"}
}