{
  "type": "Feature",
  "properties": {
    "gn:admin1_code":"17.0",
    "gn:asciiname":"Gusnice",
    "gn:country_code":"ME",
    "gn:dem":1226,
    "gn:feature_class":"P",
    "gn:feature_code":"PPL",
    "gn:name":"Gusnice",
    "gn:population":0,
    "gn:timezone":"Europe/Podgorica",
    "iso:country":"ME",
    "name:srp_x_preferred":[
        "Gusnice"
    ],
    "wof:name":"Gusnice",
    "wof:placetype":"locality"
},
  "geometry": {"coordinates":[20.09306,42.87278],"type":"Point"}
}