{
  "type": "Feature",
  "properties": {
    "gn:admin1_code":"6.0",
    "gn:asciiname":"Celinacki Dolovi",
    "gn:country_code":"ME",
    "gn:dem":886,
    "gn:feature_class":"P",
    "gn:feature_code":"PPL",
    "gn:name":"\u010celina\u010dki Dolovi",
    "gn:population":0,
    "gn:timezone":"Europe/Podgorica",
    "iso:country":"ME",
    "name:srp_x_preferred":[
        "\u010celina\u010dki Dolovi"
    ],
    "wof:name":"Celinacki Dolovi",
    "wof:placetype":"locality"
},
  "geometry": {"coordinates":[18.92667,42.46722000000001],"type":"Point"}
}