{
  "type": "Feature",
  "properties": {
    "gn:admin1_code":"12.0",
    "gn:asciiname":"Zeljev Do",
    "gn:country_code":"ME",
    "gn:dem":745,
    "gn:feature_class":"P",
    "gn:feature_code":"PPL",
    "gn:name":"\u017deljev Do",
    "gn:population":0,
    "gn:timezone":"Europe/Podgorica",
    "iso:country":"ME",
    "name:srp_x_preferred":[
        "\u017deljev Do"
    ],
    "wof:name":"Zeljev Do",
    "wof:placetype":"locality"
},
  "geometry": {"coordinates":[18.51139,42.78972],"type":"Point"}
}