{
  "type": "Feature",
  "properties": {
    "gn:admin1_code":"14.0",
    "gn:asciiname":"Omerovici",
    "gn:country_code":"ME",
    "gn:dem":851,
    "gn:feature_class":"P",
    "gn:feature_code":"PPL",
    "gn:name":"Omerovi\u0107i",
    "gn:population":0,
    "gn:timezone":"Europe/Podgorica",
    "iso:country":"ME",
    "name:srp_x_preferred":[
        "Omerovi\u0107i"
    ],
    "wof:name":"Omerovici",
    "wof:placetype":"locality"
},
  "geometry": {"coordinates":[19.03111,43.42361],"type":"Point"}
}