{
  "type": "Feature",
  "properties": {
    "gn:admin1_code":"9.0",
    "gn:asciiname":"Presjeka",
    "gn:country_code":"ME",
    "gn:dem":1047,
    "gn:feature_class":"P",
    "gn:feature_code":"PPL",
    "gn:name":"Presjeka",
    "gn:population":0,
    "gn:timezone":"Europe/Podgorica",
    "iso:country":"ME",
    "name:bos_x_preferred":[
        "Presjeka"
    ],
    "name:ceb_x_preferred":[
        "Presjeka"
    ],
    "name:fra_x_preferred":[
        "Presjeka"
    ],
    "name:hrv_x_preferred":[
        "Presjeka"
    ],
    "name:rus_x_preferred":[
        "\u041f\u0440\u0435\u0441\u0435\u043a\u0430"
    ],
    "name:srp_x_preferred":[
        "Presjeka"
    ],
    "name:srp_x_variant":[
        "\u041f\u0440\u0435\u0441\u0458\u0435\u043a\u0430"
    ],
    "name:swe_x_preferred":[
        "Presjeka"
    ],
    "wof:name":"Presjeka",
    "wof:placetype":"locality"
},
  "geometry": {"coordinates":[19.45361,42.74861],"type":"Point"}
}