{
  "type": "Feature",
  "properties": {
    "gn:admin1_code":"14.0",
    "gn:asciiname":"Potkrusa",
    "gn:country_code":"ME",
    "gn:dem":975,
    "gn:feature_class":"P",
    "gn:feature_code":"PPL",
    "gn:name":"Potkru\u0161a",
    "gn:population":0,
    "gn:timezone":"Europe/Podgorica",
    "iso:country":"ME",
    "name:und_x_variant":[
        "Potrku\u0161a",
        "Podkru\u0161a",
        "Potkru\u0161a"
    ],
    "wof:name":"Potkrusa",
    "wof:placetype":"locality"
},
  "geometry": {"coordinates":[19.28944,43.33556],"type":"Point"}
}