{
  "type": "Feature",
  "properties": {
    "gn:admin1_code":"9.0",
    "gn:asciiname":"Raskrsnica",
    "gn:country_code":"ME",
    "gn:dem":1156,
    "gn:feature_class":"P",
    "gn:feature_code":"PPL",
    "gn:name":"Raskrsnica",
    "gn:population":0,
    "gn:timezone":"Europe/Podgorica",
    "iso:country":"ME",
    "name:srp_x_preferred":[
        "Raskrsnica"
    ],
    "wof:name":"Raskrsnica",
    "wof:placetype":"locality"
},
  "geometry": {"coordinates":[19.27944,42.89],"type":"Point"}
}