{
  "type": "Feature",
  "properties": {
    "gn:admin1_code":"18.0",
    "gn:asciiname":"Duricin Do",
    "gn:country_code":"ME",
    "gn:dem":1367,
    "gn:feature_class":"P",
    "gn:feature_code":"PPL",
    "gn:name":"\u00d0uri\u010din Do",
    "gn:population":0,
    "gn:timezone":"Europe/Podgorica",
    "iso:country":"ME",
    "wof:name":"Duricin Do",
    "wof:placetype":"locality"
},
  "geometry": {"coordinates":[19.1225,43.04306],"type":"Point"}
}