{
  "type": "Feature",
  "properties": {
    "gn:admin1_code":"9.0",
    "gn:asciiname":"Dragovica Polje",
    "gn:country_code":"ME",
    "gn:dem":668,
    "gn:feature_class":"P",
    "gn:feature_code":"PPLL",
    "gn:name":"Dragovi\u0107a Polje",
    "gn:population":0,
    "gn:timezone":"Europe/Podgorica",
    "iso:country":"ME",
    "wof:name":"Dragovica Polje",
    "wof:placetype":"locality"
},
  "geometry": {"coordinates":[19.32,42.86167],"type":"Point"}
}