{
  "type": "Feature",
  "properties": {
    "gn:admin1_code":"20.0",
    "gn:asciiname":"Valdanos",
    "gn:country_code":"ME",
    "gn:dem":22,
    "gn:feature_class":"P",
    "gn:feature_code":"PPL",
    "gn:name":"Valdanos",
    "gn:population":0,
    "gn:timezone":"Europe/Podgorica",
    "iso:country":"ME",
    "wof:name":"Valdanos",
    "wof:placetype":"locality"
},
  "geometry": {"coordinates":[19.16583,41.94917],"type":"Point"}
}