{
  "type": "Feature",
  "properties": {
    "gn:admin1_code":"2.0",
    "gn:asciiname":"Tejani",
    "gn:country_code":"ME",
    "gn:dem":476,
    "gn:feature_class":"P",
    "gn:feature_code":"PPL",
    "gn:name":"Tejani",
    "gn:population":0,
    "gn:timezone":"Europe/Podgorica",
    "iso:country":"ME",
    "name:und_x_variant":[
        "Tijana",
        "Tejani"
    ],
    "wof:name":"Tejani",
    "wof:placetype":"locality"
},
  "geometry": {"coordinates":[19.24333,42.10278],"type":"Point"}
}