{
  "type": "Feature",
  "properties": {
    "gn:admin1_code":"12.0",
    "gn:asciiname":"Zavraca",
    "gn:country_code":"ME",
    "gn:dem":838,
    "gn:feature_class":"P",
    "gn:feature_code":"PPL",
    "gn:name":"Zavraca",
    "gn:population":0,
    "gn:timezone":"Europe/Podgorica",
    "iso:country":"ME",
    "name:srp_x_preferred":[
        "Zavraca"
    ],
    "wof:name":"Zavraca",
    "wof:placetype":"locality"
},
  "geometry": {"coordinates":[18.88472,42.82778],"type":"Point"}
}