{
  "type": "Feature",
  "properties": {
    "gn:admin1_code":"7.0",
    "gn:asciiname":"Povrhpoljina",
    "gn:country_code":"ME",
    "gn:dem":236,
    "gn:feature_class":"P",
    "gn:feature_code":"PPL",
    "gn:name":"Povrhpoljina",
    "gn:population":0,
    "gn:timezone":"Europe/Podgorica",
    "iso:country":"ME",
    "name:srp_x_preferred":[
        "Povrhpoljina"
    ],
    "wof:name":"Povrhpoljina",
    "wof:placetype":"locality"
},
  "geometry": {"coordinates":[19.07694,42.50417],"type":"Point"}
}