{
  "type": "Feature",
  "properties": {
    "gn:admin1_code":"3.0",
    "gn:asciiname":"Rujista",
    "gn:country_code":"ME",
    "gn:dem":1032,
    "gn:feature_class":"P",
    "gn:feature_code":"PPL",
    "gn:name":"Ruji\u0161ta",
    "gn:population":0,
    "gn:timezone":"Europe/Podgorica",
    "iso:country":"ME",
    "name:srp_x_preferred":[
        "Ruji\u0161ta"
    ],
    "wof:name":"Rujista",
    "wof:placetype":"locality"
},
  "geometry": {"coordinates":[19.81778,42.91944],"type":"Point"}
}