{
  "type": "Feature",
  "properties": {
    "gn:admin1_code":"16.0",
    "gn:asciiname":"Krivaca",
    "gn:country_code":"ME",
    "gn:dem":621,
    "gn:feature_class":"P",
    "gn:feature_code":"PPL",
    "gn:name":"Kriva\u010da",
    "gn:population":0,
    "gn:timezone":"Europe/Podgorica",
    "iso:country":"ME",
    "name:srp_x_preferred":[
        "Kriva\u010da"
    ],
    "wof:name":"Krivaca",
    "wof:placetype":"locality"
},
  "geometry": {"coordinates":[19.25472,42.5525],"type":"Point"}
}