{
  "type": "Feature",
  "properties": {
    "gn:admin1_code":"17.0",
    "gn:asciiname":"Donja Crnca",
    "gn:country_code":"ME",
    "gn:dem":1018,
    "gn:feature_class":"P",
    "gn:feature_code":"PPL",
    "gn:name":"Donja Crn\u010da",
    "gn:population":0,
    "gn:timezone":"Europe/Podgorica",
    "iso:country":"ME",
    "name:und_x_variant":[
        "Donje Crn\u010de",
        "Crn\u010da",
        "Donja Crn\u010da"
    ],
    "wof:name":"Donja Crnca",
    "wof:placetype":"locality"
},
  "geometry": {"coordinates":[20.32389,42.91194],"type":"Point"}
}