{
  "type": "Feature",
  "properties": {
    "gn:admin1_code":"14.0",
    "gn:asciiname":"Ovcarevo",
    "gn:country_code":"ME",
    "gn:dem":1018,
    "gn:feature_class":"P",
    "gn:feature_code":"PPL",
    "gn:name":"Ov\u010darevo",
    "gn:population":0,
    "gn:timezone":"Europe/Podgorica",
    "iso:country":"ME",
    "name:srp_x_preferred":[
        "Ov\u010darevo"
    ],
    "wof:name":"Ovcarevo",
    "wof:placetype":"locality"
},
  "geometry": {"coordinates":[19.28583,43.41111],"type":"Point"}
}