{
  "type": "Feature",
  "properties": {
    "gn:admin1_code":"20.0",
    "gn:asciiname":"Gornji Stoj",
    "gn:country_code":"ME",
    "gn:dem":2,
    "gn:feature_class":"P",
    "gn:feature_code":"PPL",
    "gn:name":"Gornji \u0160toj",
    "gn:population":0,
    "gn:timezone":"Europe/Podgorica",
    "iso:country":"ME",
    "name:srp_x_preferred":[
        "Gornji \u0160toj"
    ],
    "wof:name":"Gornji Stoj",
    "wof:placetype":"locality"
},
  "geometry": {"coordinates":[19.35139,41.88806],"type":"Point"}
}