{
  "type": "Feature",
  "properties": {
    "gn:admin1_code":"4.0",
    "gn:asciiname":"Lepenac",
    "gn:country_code":"ME",
    "gn:dem":912,
    "gn:feature_class":"P",
    "gn:feature_code":"PPL",
    "gn:name":"Lepenac",
    "gn:population":0,
    "gn:timezone":"Europe/Podgorica",
    "iso:country":"ME",
    "name:bul_x_preferred":[
        "\u041b\u0435\u043f\u0435\u043d\u0435\u0446"
    ],
    "name:ceb_x_preferred":[
        "Lepenec"
    ],
    "name:ces_x_preferred":[
        "Lepenac"
    ],
    "name:deu_x_preferred":[
        "Lepenac"
    ],
    "name:fas_x_preferred":[
        "\u0644\u067e\u0646\u0627\u06a9"
    ],
    "name:fra_x_preferred":[
        "Lepenac"
    ],
    "name:hrv_x_preferred":[
        "Lepenac"
    ],
    "name:hun_x_preferred":[
        "Lepenac"
    ],
    "name:lit_x_preferred":[
        "Lepenacas"
    ],
    "name:mkd_x_preferred":[
        "\u041b\u0435\u043f\u0435\u043d\u0435\u0446"
    ],
    "name:nno_x_preferred":[
        "Lepenats"
    ],
    "name:pol_x_preferred":[
        "Lepenac"
    ],
    "name:rus_x_preferred":[
        "\u041b\u0435\u043f\u0435\u043d\u0430\u0446"
    ],
    "name:srp_x_preferred":[
        "Lepenac"
    ],
    "name:srp_x_variant":[
        "\u041b\u0435\u043f\u0435\u043d\u0430\u0446"
    ],
    "name:swe_x_preferred":[
        "Lepenec"
    ],
    "name:tgk_x_preferred":[
        "\u041b\u0435\u043f\u0435\u043d\u0430\u043a"
    ],
    "name:ukr_x_preferred":[
        "\u041b\u0435\u043f\u0435\u043d\u0435\u0446"
    ],
    "wof:name":"Lepenac",
    "wof:placetype":"locality"
},
  "geometry": {"coordinates":[19.59194,42.99972],"type":"Point"}
}