{
  "type": "Feature",
  "properties": {
    "gn:admin1_code":"12.0",
    "gn:asciiname":"Bogetici",
    "gn:country_code":"ME",
    "gn:dem":469,
    "gn:feature_class":"P",
    "gn:feature_code":"PPL",
    "gn:name":"Bogeti\u0107i",
    "gn:population":0,
    "gn:timezone":"Europe/Podgorica",
    "iso:country":"ME",
    "wof:name":"Bogetici",
    "wof:placetype":"locality"
},
  "geometry": {"coordinates":[18.96704,42.68294],"type":"Point"}
}