{
  "type": "Feature",
  "properties": {
    "gn:admin1_code":"10.0",
    "gn:asciiname":"Marovici",
    "gn:country_code":"ME",
    "gn:dem":232,
    "gn:feature_class":"P",
    "gn:feature_code":"PPL",
    "gn:name":"Marovi\u0107i",
    "gn:population":0,
    "gn:timezone":"Europe/Podgorica",
    "iso:country":"ME",
    "name:srp_x_preferred":[
        "Marovi\u0107i"
    ],
    "wof:name":"Marovici",
    "wof:placetype":"locality"
},
  "geometry": {"coordinates":[18.76,42.32111],"type":"Point"}
}