{
  "type": "Feature",
  "properties": {
    "gn:admin1_code":"21.0",
    "gn:asciiname":"Krs",
    "gn:country_code":"ME",
    "gn:dem":1426,
    "gn:feature_class":"P",
    "gn:feature_code":"PPLL",
    "gn:name":"Kr\u0161",
    "gn:population":0,
    "gn:timezone":"Europe/Podgorica",
    "iso:country":"ME",
    "wof:name":"Krs",
    "wof:placetype":"locality"
},
  "geometry": {"coordinates":[19.26806,43.11361],"type":"Point"}
}