{
  "type": "Feature",
  "properties": {
    "gn:admin1_code":"22.0",
    "gn:asciiname":"Zarunica",
    "gn:country_code":"ME",
    "gn:dem":1265,
    "gn:feature_class":"P",
    "gn:feature_code":"PPL",
    "gn:name":"Zarunica",
    "gn:population":0,
    "gn:timezone":"Europe/Podgorica",
    "iso:country":"ME",
    "name:srp_x_preferred":[
        "Zarunica"
    ],
    "wof:name":"Zarunica",
    "wof:placetype":"locality"
},
  "geometry": {"coordinates":[19.86667000000001,42.51889],"type":"Point"}
}