{
  "type": "Feature",
  "properties": {
    "gn:admin1_code":"5.0",
    "gn:asciiname":"Podlicak",
    "gn:country_code":"ME",
    "gn:dem":89,
    "gn:feature_class":"P",
    "gn:feature_code":"PPL",
    "gn:name":"Podli\u010dak",
    "gn:population":0,
    "gn:timezone":"Europe/Podgorica",
    "iso:country":"ME",
    "name:srp_x_preferred":[
        "Podli\u010dak"
    ],
    "wof:name":"Podlicak",
    "wof:placetype":"locality"
},
  "geometry": {"coordinates":[18.89861,42.27],"type":"Point"}
}