{
  "type": "Feature",
  "properties": {
    "gn:admin1_code":"14.0",
    "gn:asciiname":"Crljenice",
    "gn:country_code":"ME",
    "gn:dem":1053,
    "gn:feature_class":"P",
    "gn:feature_code":"PPL",
    "gn:name":"Crljenice",
    "gn:population":0,
    "gn:timezone":"Europe/Podgorica",
    "iso:country":"ME",
    "name:fra_x_preferred":[
        "Crljenice"
    ],
    "name:ron_x_preferred":[
        "Crljenice"
    ],
    "name:slv_x_preferred":[
        "Crljenice"
    ],
    "name:srp_x_preferred":[
        "Crljenice"
    ],
    "name:srp_x_variant":[
        "\u0426\u0440\u0459\u0435\u043d\u0438\u0446\u0435"
    ],
    "wof:name":"Crljenice",
    "wof:placetype":"locality"
},
  "geometry": {"coordinates":[19.39833,43.36139],"type":"Point"}
}