{
  "type": "Feature",
  "properties": {
    "gn:admin1_code":"20.0",
    "gn:asciiname":"Stegvasi",
    "gn:country_code":"ME",
    "gn:dem":236,
    "gn:feature_class":"P",
    "gn:feature_code":"PPL",
    "gn:name":"Stegva\u0161i",
    "gn:population":0,
    "gn:timezone":"Europe/Podgorica",
    "iso:country":"ME",
    "name:srp_x_preferred":[
        "Stegva\u0161i"
    ],
    "wof:name":"Stegvasi",
    "wof:placetype":"locality"
},
  "geometry": {"coordinates":[19.36639,42.05861],"type":"Point"}
}