{
  "type": "Feature",
  "properties": {
    "gn:admin1_code":"6.0",
    "gn:asciiname":"Celina",
    "gn:country_code":"ME",
    "gn:dem":630,
    "gn:feature_class":"P",
    "gn:feature_code":"PPL",
    "gn:name":"\u010celina",
    "gn:population":0,
    "gn:timezone":"Europe/Podgorica",
    "iso:country":"ME",
    "name:bul_x_preferred":[
        "\u0426\u0435\u043b\u0438\u043d\u0430"
    ],
    "name:ceb_x_preferred":[
        "Celina"
    ],
    "name:ces_x_preferred":[
        "Celina"
    ],
    "name:fra_x_preferred":[
        "Celina"
    ],
    "name:hun_x_preferred":[
        "Celina"
    ],
    "name:ita_x_preferred":[
        "Celina"
    ],
    "name:nld_x_preferred":[
        "Celina"
    ],
    "name:pol_x_preferred":[
        "Celina"
    ],
    "name:por_x_preferred":[
        "Celina"
    ],
    "name:slk_x_preferred":[
        "Celina"
    ],
    "name:slv_x_preferred":[
        "Celina"
    ],
    "name:srp_x_preferred":[
        "\u010celina"
    ],
    "name:srp_x_variant":[
        "\u0421\u0435\u043b\u0430\u0458\u043d\u0430"
    ],
    "name:swe_x_preferred":[
        "Celina"
    ],
    "name:vol_x_preferred":[
        "Celina"
    ],
    "wof:name":"Celina",
    "wof:placetype":"locality"
},
  "geometry": {"coordinates":[18.81972,42.54444],"type":"Point"}
}