{
  "type": "Feature",
  "properties": {
    "gn:admin1_code":"18.0",
    "gn:asciiname":"Sticje",
    "gn:country_code":"ME",
    "gn:dem":1360,
    "gn:feature_class":"P",
    "gn:feature_code":"PPL",
    "gn:name":"\u0160ti\u010dje",
    "gn:population":0,
    "gn:timezone":"Europe/Podgorica",
    "iso:country":"ME",
    "wof:name":"Sticje",
    "wof:placetype":"locality"
},
  "geometry": {"coordinates":[19.21389,42.95306],"type":"Point"}
}