{
  "type": "Feature",
  "properties": {
    "gn:admin1_code":"6.0",
    "gn:asciiname":"Meoca Cucka",
    "gn:country_code":"ME",
    "gn:dem":887,
    "gn:feature_class":"P",
    "gn:feature_code":"PPL",
    "gn:name":"Meoca Cucka",
    "gn:population":0,
    "gn:timezone":"Europe/Podgorica",
    "iso:country":"ME",
    "name:und_x_variant":[
        "Meoce Cucke",
        "Meoca Cucka"
    ],
    "wof:name":"Meoca Cucka",
    "wof:placetype":"locality"
},
  "geometry": {"coordinates":[18.85139,42.595],"type":"Point"}
}