{
  "type": "Feature",
  "properties": {
    "gn:admin1_code":"4.0",
    "gn:asciiname":"Buturice",
    "gn:country_code":"ME",
    "gn:dem":592,
    "gn:feature_class":"P",
    "gn:feature_code":"PPL",
    "gn:name":"Buturi\u0107e",
    "gn:population":0,
    "gn:timezone":"Europe/Podgorica",
    "iso:country":"ME",
    "name:fra_x_preferred":[
        "Boturi\u0107i"
    ],
    "name:ron_x_preferred":[
        "Boturi\u0107i"
    ],
    "name:rus_x_preferred":[
        "\u0411\u043e\u0442\u0443\u0440\u0438\u0447\u0438"
    ],
    "name:slv_x_preferred":[
        "Boturi\u0107i"
    ],
    "name:srp_x_preferred":[
        "\u0411\u043e\u0442\u0443\u0440\u0438\u045b\u0438"
    ],
    "name:und_x_variant":[
        "Boturi\u0107e",
        "Boturi\u0107",
        "Boturi\u0107i",
        "Buturi\u0107e"
    ],
    "wof:name":"Buturice",
    "wof:placetype":"locality"
},
  "geometry": {"coordinates":[19.82139,43.06972],"type":"Point"}
}