{
  "type": "Feature",
  "properties": {
    "gn:admin1_code":"10.0",
    "gn:asciiname":"Pavlovici",
    "gn:country_code":"ME",
    "gn:dem":231,
    "gn:feature_class":"P",
    "gn:feature_code":"PPL",
    "gn:name":"Pavlovi\u0107i",
    "gn:population":0,
    "gn:timezone":"Europe/Podgorica",
    "iso:country":"ME",
    "name:srp_x_preferred":[
        "Pavlovi\u0107i"
    ],
    "wof:name":"Pavlovici",
    "wof:placetype":"locality"
},
  "geometry": {"coordinates":[18.74111,42.35306],"type":"Point"}
}