{
  "type": "Feature",
  "properties": {
    "gn:admin1_code":"16.0",
    "gn:asciiname":"Palic",
    "gn:country_code":"ME",
    "gn:dem":332,
    "gn:feature_class":"P",
    "gn:feature_code":"PPL",
    "gn:name":"Pali\u0107",
    "gn:population":0,
    "gn:timezone":"Europe/Podgorica",
    "iso:country":"ME",
    "name:srp_x_preferred":[
        "Pali\u0107"
    ],
    "wof:name":"Palic",
    "wof:placetype":"locality"
},
  "geometry": {"coordinates":[19.14556,42.41472],"type":"Point"}
}