{
  "type": "Feature",
  "properties": {
    "gn:admin1_code":"4.0",
    "gn:asciiname":"Resnik",
    "gn:country_code":"ME",
    "gn:dem":574,
    "gn:feature_class":"P",
    "gn:feature_code":"PPL",
    "gn:name":"Resnik",
    "gn:population":0,
    "gn:timezone":"Europe/Podgorica",
    "iso:country":"ME",
    "name:ceb_x_preferred":[
        "Resnik"
    ],
    "name:fas_x_preferred":[
        "\u0631\u0633\u0646\u06cc\u06a9"
    ],
    "name:fra_x_preferred":[
        "Resnik"
    ],
    "name:ron_x_preferred":[
        "Resnik"
    ],
    "name:slv_x_preferred":[
        "Resnik"
    ],
    "name:srp_x_preferred":[
        "\u0420\u0435\u0441\u043d\u0438\u043a"
    ],
    "wof:name":"Resnik",
    "wof:placetype":"locality"
},
  "geometry": {"coordinates":[19.77389,43.04139],"type":"Point"}
}