{
  "type": "Feature",
  "properties": {
    "gn:admin1_code":"9.0",
    "gn:asciiname":"Donja Ljuta",
    "gn:country_code":"ME",
    "gn:dem":768,
    "gn:feature_class":"P",
    "gn:feature_code":"PPL",
    "gn:name":"Donja Ljuta",
    "gn:population":0,
    "gn:timezone":"Europe/Podgorica",
    "iso:country":"ME",
    "name:srp_x_preferred":[
        "Donja Ljuta"
    ],
    "wof:name":"Donja Ljuta",
    "wof:placetype":"locality"
},
  "geometry": {"coordinates":[19.35333,42.82528],"type":"Point"}
}