{
  "type": "Feature",
  "properties": {
    "gn:admin1_code":"12.0",
    "gn:asciiname":"Liverovo Polje",
    "gn:country_code":"ME",
    "gn:dem":874,
    "gn:feature_class":"P",
    "gn:feature_code":"PPL",
    "gn:name":"Liverovo Polje",
    "gn:population":0,
    "gn:timezone":"Europe/Podgorica",
    "iso:country":"ME",
    "name:und_x_variant":[
        "Lirovo Polje",
        "Liverovo Polje"
    ],
    "wof:name":"Liverovo Polje",
    "wof:placetype":"locality"
},
  "geometry": {"coordinates":[18.65417,42.79667],"type":"Point"}
}