{
  "type": "Feature",
  "properties": {
    "gn:admin1_code":"14.0",
    "gn:asciiname":"Livadani",
    "gn:country_code":"ME",
    "gn:dem":972,
    "gn:feature_class":"P",
    "gn:feature_code":"PPL",
    "gn:name":"Liva\u0111ani",
    "gn:population":0,
    "gn:timezone":"Europe/Podgorica",
    "iso:country":"ME",
    "name:srp_x_preferred":[
        "Liva\u0111ani"
    ],
    "wof:name":"Livadani",
    "wof:placetype":"locality"
},
  "geometry": {"coordinates":[19.29528,43.38667],"type":"Point"}
}