{
  "type": "Feature",
  "properties": {
    "gn:admin1_code":"9.0",
    "gn:asciiname":"Vlahovici",
    "gn:country_code":"ME",
    "gn:dem":738,
    "gn:feature_class":"P",
    "gn:feature_code":"PPLL",
    "gn:name":"Vlahovi\u0107i",
    "gn:population":0,
    "gn:timezone":"Europe/Podgorica",
    "iso:country":"ME",
    "wof:name":"Vlahovici",
    "wof:placetype":"locality"
},
  "geometry": {"coordinates":[19.35083,42.68889],"type":"Point"}
}