{
  "type": "Feature",
  "properties": {
    "gn:admin1_code":"14.0",
    "gn:asciiname":"Presmenice",
    "gn:country_code":"ME",
    "gn:dem":840,
    "gn:feature_class":"P",
    "gn:feature_code":"PPL",
    "gn:name":"Pre\u0161menice",
    "gn:population":0,
    "gn:timezone":"Europe/Podgorica",
    "iso:country":"ME",
    "name:srp_x_preferred":[
        "Pre\u0161menice"
    ],
    "wof:name":"Presmenice",
    "wof:placetype":"locality"
},
  "geometry": {"coordinates":[19.22167,43.41667],"type":"Point"}
}