{
  "type": "Feature",
  "properties": {
    "gn:admin1_code":"20.0",
    "gn:asciiname":"Curaj",
    "gn:country_code":"ME",
    "gn:dem":228,
    "gn:feature_class":"P",
    "gn:feature_code":"PPL",
    "gn:name":"Curaj",
    "gn:population":0,
    "gn:timezone":"Europe/Podgorica",
    "iso:country":"ME",
    "name:srp_x_preferred":[
        "Curaj"
    ],
    "wof:name":"Curaj",
    "wof:placetype":"locality"
},
  "geometry": {"coordinates":[19.32139,42.04222],"type":"Point"}
}