{
  "type": "Feature",
  "properties": {
    "gn:country":"ME",
    "gn:fcode":"PPL",
    "gn:pop":5,
    "iso:country":"ME",
    "name:srp_x_preferred":[
        "Kola\u010d"
    ],
    "qs:name":"Kola\u010d",
    "qs:photos_9r":0,
    "qs:photos_sr":0,
    "qs:pop_sr":"1",
    "wof:name":"Kola\u010d",
    "wof:placetype":"locality",
    "wof:population":5
},
  "geometry": {"coordinates":[18.97417,42.18111],"type":"Point"}
}