{
  "type": "Feature",
  "properties": {
    "gn:admin1_code":"12.0",
    "gn:asciiname":"Potkita",
    "gn:country_code":"ME",
    "gn:dem":909,
    "gn:feature_class":"P",
    "gn:feature_code":"PPL",
    "gn:name":"Potkita",
    "gn:population":0,
    "gn:timezone":"Europe/Podgorica",
    "iso:country":"ME",
    "name:und_x_variant":[
        "Podkita",
        "Potkita"
    ],
    "wof:name":"Potkita",
    "wof:placetype":"locality"
},
  "geometry": {"coordinates":[18.80667,42.78806],"type":"Point"}
}