{
  "type": "Feature",
  "properties": {
    "gn:admin1_code":"12.0",
    "gn:asciiname":"Gornje Carade",
    "gn:country_code":"ME",
    "gn:dem":913,
    "gn:feature_class":"P",
    "gn:feature_code":"PPL",
    "gn:name":"Gornje \u010cara\u0111e",
    "gn:population":0,
    "gn:timezone":"Europe/Podgorica",
    "iso:country":"ME",
    "name:und_x_variant":[
        "\u010cara\u0111e",
        "Gornje \u010cara\u0111e"
    ],
    "wof:name":"Gornje Carade",
    "wof:placetype":"locality"
},
  "geometry": {"coordinates":[18.68528,43.00556],"type":"Point"}
}