{
  "type": "Feature",
  "properties": {
    "gn:admin1_code":"9.0",
    "gn:asciiname":"Stanci",
    "gn:country_code":"ME",
    "gn:dem":234,
    "gn:feature_class":"P",
    "gn:feature_code":"PPL",
    "gn:name":"Stanci",
    "gn:population":0,
    "gn:timezone":"Europe/Podgorica",
    "iso:country":"ME",
    "name:srp_x_preferred":[
        "Stanci"
    ],
    "wof:name":"Stanci",
    "wof:placetype":"locality"
},
  "geometry": {"coordinates":[19.3675,42.71611],"type":"Point"}
}