{
  "type": "Feature",
  "properties": {
    "gn:admin1_code":"10.0",
    "gn:asciiname":"Bratesici",
    "gn:country_code":"ME",
    "gn:dem":328,
    "gn:feature_class":"P",
    "gn:feature_code":"PPL",
    "gn:name":"Brate\u0161i\u0107i",
    "gn:population":0,
    "gn:timezone":"Europe/Podgorica",
    "iso:country":"ME",
    "name:srp_x_preferred":[
        "Brate\u0161i\u0107i"
    ],
    "wof:name":"Bratesici",
    "wof:placetype":"locality"
},
  "geometry": {"coordinates":[18.78917,42.34722],"type":"Point"}
}