{
  "type": "Feature",
  "properties": {
    "gn:admin1_code":"8.0",
    "gn:asciiname":"Donji Morinj",
    "gn:country_code":"ME",
    "gn:dem":15,
    "gn:feature_class":"P",
    "gn:feature_code":"PPL",
    "gn:name":"Donji Morinj",
    "gn:population":0,
    "gn:timezone":"Europe/Podgorica",
    "iso:country":"ME",
    "name:und_x_variant":[
        "Morinj",
        "Morigno",
        "Donji Morinj"
    ],
    "wof:name":"Donji Morinj",
    "wof:placetype":"locality"
},
  "geometry": {"coordinates":[18.64722,42.48944],"type":"Point"}
}