{
  "type": "Feature",
  "properties": {
    "gn:admin1_code":"10.0",
    "gn:asciiname":"Brezov Do",
    "gn:country_code":"ME",
    "gn:dem":1013,
    "gn:feature_class":"P",
    "gn:feature_code":"PPL",
    "gn:name":"Brezov Do",
    "gn:population":0,
    "gn:timezone":"Europe/Podgorica",
    "iso:country":"ME",
    "name:srp_x_preferred":[
        "Brezov Do"
    ],
    "wof:name":"Brezov Do",
    "wof:placetype":"locality"
},
  "geometry": {"coordinates":[18.60917,42.55194],"type":"Point"}
}