{
  "type": "Feature",
  "properties": {
    "gn:admin1_code":"8.0",
    "gn:asciiname":"Milovici",
    "gn:country_code":"ME",
    "gn:dem":200,
    "gn:feature_class":"P",
    "gn:feature_code":"PPL",
    "gn:name":"Milovi\u0107i",
    "gn:population":0,
    "gn:timezone":"Europe/Podgorica",
    "iso:country":"ME",
    "name:srp_x_preferred":[
        "Milovi\u0107i"
    ],
    "wof:name":"Milovici",
    "wof:placetype":"locality"
},
  "geometry": {"coordinates":[18.49361,42.48722],"type":"Point"}
}