{
  "type": "Feature",
  "properties": {
    "gn:admin1_code":"14.0",
    "gn:asciiname":"Trebljevine",
    "gn:country_code":"ME",
    "gn:dem":1204,
    "gn:feature_class":"P",
    "gn:feature_code":"PPLL",
    "gn:name":"Trebljevine",
    "gn:population":0,
    "gn:timezone":"Europe/Podgorica",
    "iso:country":"ME",
    "wof:name":"Trebljevine",
    "wof:placetype":"locality"
},
  "geometry": {"coordinates":[19.345,43.16889000000001],"type":"Point"}
}