{
  "type": "Feature",
  "properties": {
    "gn:admin1_code":"4.0",
    "gn:asciiname":"Negobratina",
    "gn:country_code":"ME",
    "gn:dem":1146,
    "gn:feature_class":"P",
    "gn:feature_code":"PPLL",
    "gn:name":"Negobratina",
    "gn:population":0,
    "gn:timezone":"Europe/Podgorica",
    "iso:country":"ME",
    "wof:name":"Negobratina",
    "wof:placetype":"locality"
},
  "geometry": {"coordinates":[19.9225,43.02833],"type":"Point"}
}