{
  "type": "Feature",
  "properties": {
    "gn:admin1_code":"4.0",
    "gn:asciiname":"Negobratina",
    "gn:country_code":"ME",
    "gn:dem":1146,
    "gn:feature_class":"P",
    "gn:feature_code":"PPLL",
    "gn:name":"Negobratina",
    "gn:population":0,
    "gn:timezone":"Europe/Podgorica",
    "iso:country":"ME",
    "name:fra_x_preferred":[
        "Negobratina"
    ],
    "name:ron_x_preferred":[
        "Negobratina"
    ],
    "name:slv_x_preferred":[
        "Negobratina"
    ],
    "name:srp_x_preferred":[
        "\u041d\u0435\u0433\u043e\u0431\u0440\u0430\u0442\u0438\u043d\u0430"
    ],
    "wof:name":"Negobratina",
    "wof:placetype":"locality"
},
  "geometry": {"coordinates":[19.9225,43.02833],"type":"Point"}
}