{
  "type": "Feature",
  "properties": {
    "gn:admin1_code":"3.0",
    "gn:asciiname":"Gornja Mala",
    "gn:country_code":"ME",
    "gn:dem":911,
    "gn:feature_class":"P",
    "gn:feature_code":"PPL",
    "gn:name":"Gornja Mala",
    "gn:population":0,
    "gn:timezone":"Europe/Podgorica",
    "iso:country":"ME",
    "name:srp_x_preferred":[
        "Gornja Mala"
    ],
    "wof:name":"Gornja Mala",
    "wof:placetype":"locality"
},
  "geometry": {"coordinates":[19.93194,42.78667],"type":"Point"}
}