{
  "type": "Feature",
  "properties": {
    "gn:admin1_code":"14.0",
    "gn:asciiname":"Potoci",
    "gn:country_code":"ME",
    "gn:dem":801,
    "gn:feature_class":"P",
    "gn:feature_code":"PPLL",
    "gn:name":"Potoci",
    "gn:population":0,
    "gn:timezone":"Europe/Podgorica",
    "iso:country":"ME",
    "wof:name":"Potoci",
    "wof:placetype":"locality"
},
  "geometry": {"coordinates":[19.25528,43.35972],"type":"Point"}
}