{
  "type": "Feature",
  "properties": {
    "gn:admin1_code":"16.0",
    "gn:asciiname":"Prifta",
    "gn:country_code":"ME",
    "gn:dem":337,
    "gn:feature_class":"P",
    "gn:feature_code":"PPL",
    "gn:name":"Prifta",
    "gn:population":0,
    "gn:timezone":"Europe/Podgorica",
    "iso:country":"ME",
    "name:und_x_variant":[
        "Prifti",
        "Prifta"
    ],
    "wof:name":"Prifta",
    "wof:placetype":"locality"
},
  "geometry": {"coordinates":[19.39056,42.40194],"type":"Point"}
}