{
  "type": "Feature",
  "properties": {
    "gn:country":"ME",
    "gn:fcode":"PPL",
    "gn:population":20,
    "iso:country":"ME",
    "name:und_x_variant":[
        "Daci"
    ],
    "qs:name":"\u00d0alci",
    "qs:photos_9r":0,
    "qs:photos_sr":0,
    "qs:pop_sr":"1",
    "wof:name":"\u00d0alci",
    "wof:placetype":"locality",
    "wof:population":20
},
  "geometry": {"coordinates":[19.04,42.41861],"type":"Point"}
}