{
  "type": "Feature",
  "properties": {
    "gn:admin1_code":"13.0",
    "gn:asciiname":"Hakanje",
    "gn:country_code":"ME",
    "gn:dem":928,
    "gn:feature_class":"P",
    "gn:feature_code":"PPL",
    "gn:name":"Hakanje",
    "gn:population":0,
    "gn:timezone":"Europe/Podgorica",
    "iso:country":"ME",
    "name:und_x_variant":[
        "Akani",
        "Hakanje"
    ],
    "wof:name":"Hakanje",
    "wof:placetype":"locality"
},
  "geometry": {"coordinates":[19.90083,42.57111],"type":"Point"}
}