{
  "type": "Feature",
  "properties": {
    "gn:admin1_code":"7.0",
    "gn:asciiname":"Kalezici",
    "gn:country_code":"ME",
    "gn:dem":229,
    "gn:feature_class":"P",
    "gn:feature_code":"PPL",
    "gn:name":"Kalezi\u0107i",
    "gn:population":0,
    "gn:timezone":"Europe/Podgorica",
    "iso:country":"ME",
    "name:srp_x_preferred":[
        "Kalezi\u0107i"
    ],
    "wof:name":"Kalezici",
    "wof:placetype":"locality"
},
  "geometry": {"coordinates":[19.10972000000001,42.59917],"type":"Point"}
}