{
  "type": "Feature",
  "properties": {
    "gn:admin1_code":"14.0",
    "gn:asciiname":"Kotorac",
    "gn:country_code":"ME",
    "gn:dem":954,
    "gn:feature_class":"P",
    "gn:feature_code":"PPL",
    "gn:name":"Kotorac",
    "gn:population":0,
    "gn:timezone":"Europe/Podgorica",
    "iso:country":"ME",
    "name:fra_x_preferred":[
        "Kotorac"
    ],
    "name:ron_x_preferred":[
        "Kotorac"
    ],
    "name:slv_x_preferred":[
        "Kotorac"
    ],
    "name:srp_x_preferred":[
        "Kotorac"
    ],
    "name:srp_x_variant":[
        "\u041a\u043e\u0442\u043e\u0440\u0430\u0446"
    ],
    "wof:name":"Kotorac",
    "wof:placetype":"locality"
},
  "geometry": {"coordinates":[19.18806,43.43],"type":"Point"}
}