{
  "type": "Feature",
  "properties": {
    "gn:admin1_code":"16.0",
    "gn:asciiname":"Bradasica",
    "gn:country_code":"ME",
    "gn:dem":1037,
    "gn:feature_class":"P",
    "gn:feature_code":"PPL",
    "gn:name":"Brada\u0161ica",
    "gn:population":0,
    "gn:timezone":"Europe/Podgorica",
    "iso:country":"ME",
    "wof:name":"Bradasica",
    "wof:placetype":"locality"
},
  "geometry": {"coordinates":[19.48472000000001,42.61417],"type":"Point"}
}