{
  "type": "Feature",
  "properties": {
    "gn:country":"ME",
    "gn:fcode":"PPL",
    "gn:population":5,
    "iso:country":"ME",
    "name:bos_x_preferred":[
        "Orahovo"
    ],
    "name:ceb_x_preferred":[
        "Orahovo"
    ],
    "name:deu_x_preferred":[
        "Orahovo"
    ],
    "name:eng_x_preferred":[
        "Orahovo"
    ],
    "name:fra_x_preferred":[
        "Orahovo"
    ],
    "name:hrv_x_preferred":[
        "Orahovo"
    ],
    "name:ita_x_preferred":[
        "Orahovo"
    ],
    "name:nld_x_preferred":[
        "Orahovo"
    ],
    "name:por_x_preferred":[
        "Orahovo"
    ],
    "name:slv_x_preferred":[
        "Orahovo"
    ],
    "name:spa_x_preferred":[
        "Orahovo"
    ],
    "name:srp_x_preferred":[
        "Orahovo"
    ],
    "name:srp_x_variant":[
        "\u041e\u0440\u0430\u0445\u043e\u0432\u043e"
    ],
    "name:swe_x_preferred":[
        "Orahovo"
    ],
    "qs:name":"Orahovo",
    "qs:photos_9r":0,
    "qs:photos_sr":0,
    "qs:pop_sr":"1",
    "wd:wordcount":72,
    "wof:name":"Orahovo",
    "wof:placetype":"locality",
    "wof:population":5
},
  "geometry": {"coordinates":[19.06444,42.24361],"type":"Point"}
}