{
  "type": "Feature",
  "properties": {
    "gn:country":"ME",
    "gn:fcode":"PPL",
    "gn:pop":5,
    "iso:country":"ME",
    "name:srp_x_preferred":[
        "Orahovo"
    ],
    "qs:name":"Orahovo",
    "qs:photos_9r":0,
    "qs:photos_sr":0,
    "qs:pop_sr":"1",
    "wd:wordcount":72,
    "wof:name":"Orahovo",
    "wof:placetype":"locality",
    "wof:population":5
},
  "geometry": {"coordinates":[19.06444,42.24361],"type":"Point"}
}