{
  "type": "Feature",
  "properties": {
    "gn:admin1_code":"12.0",
    "gn:asciiname":"Ovcarica",
    "gn:country_code":"ME",
    "gn:dem":1064,
    "gn:feature_class":"P",
    "gn:feature_code":"PPL",
    "gn:name":"Ov\u010darica",
    "gn:population":0,
    "gn:timezone":"Europe/Podgorica",
    "iso:country":"ME",
    "name:srp_x_preferred":[
        "Ov\u010darica"
    ],
    "wof:name":"Ovcarica",
    "wof:placetype":"locality"
},
  "geometry": {"coordinates":[18.69278,42.98639],"type":"Point"}
}