{
  "type": "Feature",
  "properties": {
    "gn:admin1_code":"4.0",
    "gn:asciiname":"Usanovici",
    "gn:country_code":"ME",
    "gn:dem":603,
    "gn:feature_class":"P",
    "gn:feature_code":"PPL",
    "gn:name":"Usanovi\u010di",
    "gn:population":0,
    "gn:timezone":"Europe/Podgorica",
    "iso:country":"ME",
    "name:srp_x_preferred":[
        "Usanovi\u010di"
    ],
    "wof:name":"Usanovici",
    "wof:placetype":"locality"
},
  "geometry": {"coordinates":[19.81528,43.08861],"type":"Point"}
}