{
  "type": "Feature",
  "properties": {
    "gn:admin1_code":"9.0",
    "gn:asciiname":"Jasen",
    "gn:country_code":"ME",
    "gn:dem":1026,
    "gn:feature_class":"P",
    "gn:feature_code":"PPL",
    "gn:name":"Jasen",
    "gn:population":0,
    "gn:timezone":"Europe/Podgorica",
    "iso:country":"ME",
    "name:bos_x_preferred":[
        "Jasen"
    ],
    "name:bul_x_preferred":[
        "\u042f\u0441\u0435\u043d"
    ],
    "name:ceb_x_preferred":[
        "Jasen"
    ],
    "name:deu_x_preferred":[
        "Jasen"
    ],
    "name:fra_x_preferred":[
        "Jasen"
    ],
    "name:hrv_x_preferred":[
        "Jasen"
    ],
    "name:nld_x_preferred":[
        "Jasen"
    ],
    "name:pol_x_preferred":[
        "Jasen"
    ],
    "name:rus_x_preferred":[
        "\u042f\u0441\u0435\u043d"
    ],
    "name:slk_x_preferred":[
        "Jase\u0148"
    ],
    "name:slv_x_preferred":[
        "Jasen"
    ],
    "name:srp_x_preferred":[
        "Jasen"
    ],
    "name:srp_x_variant":[
        "\u0408\u0430\u0441\u0435\u043d"
    ],
    "name:swe_x_preferred":[
        "Jasen"
    ],
    "wof:name":"Jasen",
    "wof:placetype":"locality"
},
  "geometry": {"coordinates":[19.54056,42.74833],"type":"Point"}
}