{
  "type": "Feature",
  "properties": {
    "gn:country":"ME",
    "gn:fcode":"PPLL",
    "gn:pop":10,
    "iso:country":"ME",
    "name:cat_x_preferred":[
        "\u010celobrdo"
    ],
    "name:deu_x_preferred":[
        "\u010celobrdo"
    ],
    "name:eng_x_preferred":[
        "\u010celobrdo"
    ],
    "name:fra_x_preferred":[
        "\u010celobrdo"
    ],
    "name:glg_x_preferred":[
        "\u010celobrdo"
    ],
    "name:nld_x_preferred":[
        "\u010celobrdo"
    ],
    "name:por_x_preferred":[
        "\u010celobrdo"
    ],
    "name:ron_x_preferred":[
        "\u010celobrdo"
    ],
    "name:slv_x_preferred":[
        "\u010celobrdo"
    ],
    "name:spa_x_preferred":[
        "\u010celobrdo"
    ],
    "name:srp_x_preferred":[
        "\u0427\u0435\u043b\u043e\u0431\u0440\u0434\u043e"
    ],
    "name:ukr_x_preferred":[
        "\u0427\u0435\u043b\u043e\u0431\u0440\u0434\u043e"
    ],
    "qs:name":"\u010celobrdo",
    "qs:photos_9r":0,
    "qs:photos_sr":0,
    "qs:pop_sr":"1",
    "wof:name":"\u010celobrdo",
    "wof:placetype":"locality",
    "wof:population":10
},
  "geometry": {"coordinates":[18.90833,42.26833],"type":"Point"}
}