{
  "type": "Feature",
  "properties": {
    "gn:country":"ME",
    "gn:fcode":"PPLX",
    "gn:pop":5,
    "iso:country":"ME",
    "qs:name":"Popovi\u0107i",
    "qs:photos_9r":0,
    "qs:photos_sr":0,
    "qs:pop_sr":"1",
    "wd:wordcount":48,
    "wof:name":"Popovi\u0107i",
    "wof:placetype":"neighbourhood",
    "wof:population":5
},
  "geometry": {"coordinates":[19.10528,42.09194],"type":"Point"}
}