{
  "type": "Feature",
  "properties": {
    "gn:country":"ME",
    "gn:fcode":"PPLX",
    "gn:population":5,
    "iso:country":"ME",
    "name:bos_x_preferred":[
        "Popovi\u0107i"
    ],
    "name:fra_x_preferred":[
        "Popovi\u0107i"
    ],
    "name:hrv_x_preferred":[
        "Popovi\u0107i"
    ],
    "name:hun_x_preferred":[
        "Popovi\u0107i"
    ],
    "name:slv_x_preferred":[
        "Popovi\u0107i"
    ],
    "name:srp_x_preferred":[
        "\u041f\u043e\u043f\u043e\u0432\u0438\u045b\u0438"
    ],
    "qs:name":"Popovi\u0107i",
    "qs:photos_9r":0,
    "qs:photos_sr":0,
    "qs:pop_sr":"1",
    "wd:wordcount":48,
    "wof:name":"Popovi\u0107i",
    "wof:placetype":"neighbourhood",
    "wof:population":5
},
  "geometry": {"coordinates":[19.10528,42.09194],"type":"Point"}
}