{
  "type": "Feature",
  "properties": {
    "gn:admin1_code":"10.0",
    "gn:asciiname":"Veljinici",
    "gn:country_code":"ME",
    "gn:dem":648,
    "gn:feature_class":"P",
    "gn:feature_code":"PPL",
    "gn:name":"Veljini\u0107i",
    "gn:population":0,
    "gn:timezone":"Europe/Podgorica",
    "iso:country":"ME",
    "name:und_x_variant":[
        "Velini\u0107i",
        "Veljini\u0107i"
    ],
    "wof:name":"Veljinici",
    "wof:placetype":"locality"
},
  "geometry": {"coordinates":[18.70806,42.50222],"type":"Point"}
}