{
  "type": "Feature",
  "properties": {
    "gn:admin1_code":"19.0",
    "gn:asciiname":"Franciskovici",
    "gn:country_code":"ME",
    "gn:dem":10,
    "gn:feature_class":"P",
    "gn:feature_code":"PPL",
    "gn:name":"Franciskovi\u0107i",
    "gn:population":0,
    "gn:timezone":"Europe/Podgorica",
    "iso:country":"ME",
    "name:srp_x_preferred":[
        "Franciskovi\u0107i"
    ],
    "wof:name":"Franciskovici",
    "wof:placetype":"locality"
},
  "geometry": {"coordinates":[18.65472,42.40806],"type":"Point"}
}