{
  "type": "Feature",
  "properties": {
    "gn:admin1_code":"12.0",
    "gn:asciiname":"Carine",
    "gn:country_code":"ME",
    "gn:dem":904,
    "gn:feature_class":"P",
    "gn:feature_code":"PPL",
    "gn:name":"Carine",
    "gn:population":0,
    "gn:timezone":"Europe/Podgorica",
    "iso:country":"ME",
    "name:bre_x_preferred":[
        "Carine"
    ],
    "name:hrv_x_preferred":[
        "Carine"
    ],
    "name:srp_x_preferred":[
        "Carine"
    ],
    "wof:name":"Carine",
    "wof:placetype":"locality"
},
  "geometry": {"coordinates":[18.61028,42.72833],"type":"Point"}
}