{
  "type": "Feature",
  "properties": {
    "gn:admin1_code":"17.0",
    "gn:asciiname":"Ibarac",
    "gn:country_code":"ME",
    "gn:dem":1057,
    "gn:feature_class":"P",
    "gn:feature_code":"PPL",
    "gn:name":"Ibarac",
    "gn:population":0,
    "gn:timezone":"Europe/Podgorica",
    "iso:country":"ME",
    "name:bos_x_preferred":[
        "Ibarac"
    ],
    "name:est_x_preferred":[
        "Ibarac"
    ],
    "name:fas_x_preferred":[
        "\u0627\u06cc\u0628\u0627\u0631\u0627\u062a\u0633"
    ],
    "name:fra_x_preferred":[
        "Ibarac"
    ],
    "name:ron_x_preferred":[
        "Ibarac"
    ],
    "name:slv_x_preferred":[
        "Ibarac"
    ],
    "name:srp_x_preferred":[
        "\u0418\u0431\u0430\u0440\u0430\u0446"
    ],
    "name:ukr_x_preferred":[
        "\u0406\u0431\u0430\u0440\u0430\u0446"
    ],
    "wof:name":"Ibarac",
    "wof:placetype":"locality"
},
  "geometry": {"coordinates":[20.16194,42.83611],"type":"Point"}
}