{
  "type": "Feature",
  "properties": {
    "gn:admin1_code":"17.0",
    "gn:asciiname":"Ibarac",
    "gn:country_code":"ME",
    "gn:dem":1057,
    "gn:feature_class":"P",
    "gn:feature_code":"PPL",
    "gn:name":"Ibarac",
    "gn:population":0,
    "gn:timezone":"Europe/Podgorica",
    "iso:country":"ME",
    "wof:name":"Ibarac",
    "wof:placetype":"locality"
},
  "geometry": {"coordinates":[20.16194,42.83611],"type":"Point"}
}