{
  "type": "Feature",
  "properties": {
    "gn:admin1_code":"9.0",
    "gn:asciiname":"Smreka",
    "gn:country_code":"ME",
    "gn:dem":551,
    "gn:feature_class":"P",
    "gn:feature_code":"PPL",
    "gn:name":"Smreka",
    "gn:population":0,
    "gn:timezone":"Europe/Podgorica",
    "iso:country":"ME",
    "name:srp_x_preferred":[
        "Smreka"
    ],
    "wof:name":"Smreka",
    "wof:placetype":"locality"
},
  "geometry": {"coordinates":[19.34389,42.72194],"type":"Point"}
}