{
  "type": "Feature",
  "properties": {
    "gn:admin1_code":"4.0",
    "gn:asciiname":"Ravce Polje",
    "gn:country_code":"ME",
    "gn:dem":641,
    "gn:feature_class":"P",
    "gn:feature_code":"PPL",
    "gn:name":"Rav\u010de Polje",
    "gn:population":0,
    "gn:timezone":"Europe/Podgorica",
    "iso:country":"ME",
    "name:srp_x_preferred":[
        "Rav\u010de Polje"
    ],
    "wof:name":"Ravce Polje",
    "wof:placetype":"locality"
},
  "geometry": {"coordinates":[19.73444,42.99056],"type":"Point"}
}