{
  "type": "Feature",
  "properties": {
    "gn:admin1_code":"23.0",
    "gn:asciiname":"Trnavice",
    "gn:country_code":"ME",
    "gn:dem":1158,
    "gn:feature_class":"P",
    "gn:feature_code":"PPL",
    "gn:name":"Trnavice",
    "gn:population":0,
    "gn:timezone":"Europe/Podgorica",
    "iso:country":"ME",
    "name:srp_x_preferred":[
        "Trnavice"
    ],
    "wof:name":"Trnavice",
    "wof:placetype":"locality"
},
  "geometry": {"coordinates":[20.00806,42.93361],"type":"Point"}
}