{
  "type": "Feature",
  "properties": {
    "gn:admin1_code":"5.0",
    "gn:asciiname":"Babalonija",
    "gn:country_code":"ME",
    "gn:dem":23,
    "gn:feature_class":"P",
    "gn:feature_code":"PPL",
    "gn:name":"Babalonija",
    "gn:population":0,
    "gn:timezone":"Europe/Podgorica",
    "iso:country":"ME",
    "name:srp_x_preferred":[
        "Babalonija"
    ],
    "wof:name":"Babalonija",
    "wof:placetype":"locality"
},
  "geometry": {"coordinates":[18.84472,42.29333],"type":"Point"}
}