{
  "type": "Feature",
  "properties": {
    "gn:admin1_code":"12.0",
    "gn:asciiname":"Siroki Do",
    "gn:country_code":"ME",
    "gn:dem":803,
    "gn:feature_class":"P",
    "gn:feature_code":"PPL",
    "gn:name":"\u0160iroki Do",
    "gn:population":0,
    "gn:timezone":"Europe/Podgorica",
    "iso:country":"ME",
    "name:srp_x_preferred":[
        "\u0160iroki Do"
    ],
    "wof:name":"Siroki Do",
    "wof:placetype":"locality"
},
  "geometry": {"coordinates":[18.69611,42.74611],"type":"Point"}
}