{
  "type": "Feature",
  "properties": {
    "gn:admin1_code":"17.0",
    "gn:asciiname":"Kaluderski Laz",
    "gn:country_code":"ME",
    "gn:dem":1429,
    "gn:feature_class":"P",
    "gn:feature_code":"PPLL",
    "gn:name":"Kalu\u0111erski Laz",
    "gn:population":0,
    "gn:timezone":"Europe/Podgorica",
    "iso:country":"ME",
    "name:und_x_variant":[
        "Kalu\u0111erski Lazi",
        "Husovi\u0107i",
        "Kalu\u0111erski Laz"
    ],
    "wof:name":"Kaluderski Laz",
    "wof:placetype":"locality"
},
  "geometry": {"coordinates":[20.19583,42.78],"type":"Point"}
}