{
  "type": "Feature",
  "properties": {
    "gn:country":"ME",
    "gn:fcode":"PPL",
    "gn:population":144,
    "iso:country":"ME",
    "name:bos_x_preferred":[
        "Gornji Kokoti"
    ],
    "name:ceb_x_preferred":[
        "Gornji Kokoti"
    ],
    "name:deu_x_preferred":[
        "Gornji Kokoti"
    ],
    "name:eng_x_preferred":[
        "Gornji Kokoti"
    ],
    "name:fra_x_preferred":[
        "Gornji Kokoti"
    ],
    "name:nld_x_preferred":[
        "Gornji Kokoti"
    ],
    "name:pol_x_preferred":[
        "Gornji Kokoti"
    ],
    "name:por_x_preferred":[
        "Gornji Kokoti"
    ],
    "name:ron_x_preferred":[
        "Gornji Kokoti"
    ],
    "name:sco_x_preferred":[
        "Gornji Kokoti"
    ],
    "name:slv_x_preferred":[
        "Gornji Kokoti"
    ],
    "name:spa_x_preferred":[
        "Gornji Kokoti"
    ],
    "name:spa_x_variant":[
        "Kulja\u010de"
    ],
    "name:srp_x_preferred":[
        "Gornji Kokoti"
    ],
    "name:srp_x_variant":[
        "\u0413\u043e\u0440\u045a\u0438 \u041a\u043e\u043a\u043e\u0442\u0438"
    ],
    "name:swe_x_preferred":[
        "Gornji Kokoti"
    ],
    "qs:name":"Gornji Kokoti",
    "qs:photos_9r":0,
    "qs:photos_sr":0,
    "qs:pop_sr":"1",
    "wof:name":"Gornji Kokoti",
    "wof:placetype":"locality",
    "wof:population":144
},
  "geometry": {"coordinates":[19.17556,42.39806],"type":"Point"}
}