{
  "type": "Feature",
  "properties": {
    "gn:country":"ME",
    "gn:fcode":"PPL",
    "gn:pop":144,
    "iso:country":"ME",
    "name:dut_x_preferred":[
        "Gornji Kokoti"
    ],
    "name:eng_x_preferred":[
        "Gornji Kokoti"
    ],
    "name:fre_x_preferred":[
        "Gornji Kokoti"
    ],
    "name:ger_x_preferred":[
        "Gornji Kokoti"
    ],
    "name:por_x_preferred":[
        "Gornji Kokoti"
    ],
    "name:rum_x_preferred":[
        "Gornji Kokoti"
    ],
    "name:sco_x_preferred":[
        "Gornji Kokoti"
    ],
    "name:slv_x_preferred":[
        "Gornji Kokoti"
    ],
    "name:spa_x_preferred":[
        "Gornji Kokoti"
    ],
    "name:srp_x_preferred":[
        "Gornji Kokoti"
    ],
    "name:swe_x_preferred":[
        "Gornji Kokoti"
    ],
    "qs:name":"Gornji Kokoti",
    "qs:photos_9r":0,
    "qs:photos_sr":0,
    "qs:pop_sr":"1",
    "wof:name":"Gornji Kokoti",
    "wof:placetype":"locality",
    "wof:population":144
},
  "geometry": {"coordinates":[19.17556,42.39806],"type":"Point"}
}