{
  "type": "Feature",
  "properties": {
    "gn:admin1_code":"14.0",
    "gn:asciiname":"Sakovo Selo",
    "gn:country_code":"ME",
    "gn:dem":979,
    "gn:feature_class":"P",
    "gn:feature_code":"PPL",
    "gn:name":"Sakovo Selo",
    "gn:population":0,
    "gn:timezone":"Europe/Podgorica",
    "iso:country":"ME",
    "wof:name":"Sakovo Selo",
    "wof:placetype":"locality"
},
  "geometry": {"coordinates":[19.26028,43.33111],"type":"Point"}
}