{
  "type": "Feature",
  "properties": {
    "gn:admin1_code":"10.0",
    "gn:asciiname":"Jastrin Do",
    "gn:country_code":"ME",
    "gn:dem":717,
    "gn:feature_class":"P",
    "gn:feature_code":"PPL",
    "gn:name":"Jastrin Do",
    "gn:population":0,
    "gn:timezone":"Europe/Podgorica",
    "iso:country":"ME",
    "name:und_x_variant":[
        "Jestrin Do",
        "Jastrin Do"
    ],
    "wof:name":"Jastrin Do",
    "wof:placetype":"locality"
},
  "geometry": {"coordinates":[18.71889,42.55417],"type":"Point"}
}