{
  "type": "Feature",
  "properties": {
    "gn:admin1_code":"12.0",
    "gn:asciiname":"Pejovici",
    "gn:country_code":"ME",
    "gn:dem":844,
    "gn:feature_class":"P",
    "gn:feature_code":"PPL",
    "gn:name":"Pejovi\u0107i",
    "gn:population":0,
    "gn:timezone":"Europe/Podgorica",
    "iso:country":"ME",
    "name:srp_x_preferred":[
        "Pejovi\u0107i"
    ],
    "wof:name":"Pejovici",
    "wof:placetype":"locality"
},
  "geometry": {"coordinates":[18.49306,42.76222],"type":"Point"}
}