{
  "type": "Feature",
  "properties": {
    "gn:admin1_code":"16.0",
    "gn:asciiname":"Duske",
    "gn:country_code":"ME",
    "gn:dem":1040,
    "gn:feature_class":"P",
    "gn:feature_code":"PPL",
    "gn:name":"Du\u0161ke",
    "gn:population":0,
    "gn:timezone":"Europe/Podgorica",
    "iso:country":"ME",
    "name:und_x_variant":[
        "Du\u0161ko",
        "Du\u0161ke"
    ],
    "wof:name":"Duske",
    "wof:placetype":"locality"
},
  "geometry": {"coordinates":[19.44333,42.62833],"type":"Point"}
}