{
  "type": "Feature",
  "properties": {
    "gn:admin1_code":"18.0",
    "gn:asciiname":"Gornja Bijela",
    "gn:country_code":"ME",
    "gn:dem":1080,
    "gn:feature_class":"P",
    "gn:feature_code":"PPL",
    "gn:name":"Gornja Bijela",
    "gn:population":0,
    "gn:timezone":"Europe/Podgorica",
    "iso:country":"ME",
    "name:srp_x_preferred":[
        "Gornja Bijela"
    ],
    "wof:name":"Gornja Bijela",
    "wof:placetype":"locality"
},
  "geometry": {"coordinates":[19.155,42.90222],"type":"Point"}
}