{
  "type": "Feature",
  "properties": {
    "gn:admin1_code":"16.0",
    "gn:asciiname":"Gosici",
    "gn:country_code":"ME",
    "gn:dem":12,
    "gn:feature_class":"P",
    "gn:feature_code":"PPL",
    "gn:name":"Go\u0161i\u0107i",
    "gn:population":0,
    "gn:timezone":"Europe/Podgorica",
    "iso:country":"ME",
    "name:srp_x_preferred":[
        "Go\u0161i\u0107i"
    ],
    "wof:name":"Gosici",
    "wof:placetype":"locality"
},
  "geometry": {"coordinates":[19.26167,42.31861],"type":"Point"}
}