{
  "type": "Feature",
  "properties": {
    "gn:admin1_code":"6.0",
    "gn:asciiname":"Strugari",
    "gn:country_code":"ME",
    "gn:dem":282,
    "gn:feature_class":"P",
    "gn:feature_code":"PPL",
    "gn:name":"Strugari",
    "gn:population":0,
    "gn:timezone":"Europe/Podgorica",
    "iso:country":"ME",
    "name:srp_x_preferred":[
        "Strugari"
    ],
    "wof:name":"Strugari",
    "wof:placetype":"locality"
},
  "geometry": {"coordinates":[18.97778,42.36806],"type":"Point"}
}