{
  "type": "Feature",
  "properties": {
    "gn:admin1_code":"9.0",
    "gn:asciiname":"Trnovica",
    "gn:country_code":"ME",
    "gn:dem":702,
    "gn:feature_class":"P",
    "gn:feature_code":"PPL",
    "gn:name":"Trnovica",
    "gn:population":0,
    "gn:timezone":"Europe/Podgorica",
    "iso:country":"ME",
    "name:und_x_variant":[
        "Trnovice",
        "Trnovica"
    ],
    "wof:name":"Trnovica",
    "wof:placetype":"locality"
},
  "geometry": {"coordinates":[19.33694,42.85694],"type":"Point"}
}