{
  "type": "Feature",
  "properties": {
    "gn:admin1_code":"15.0",
    "gn:asciiname":"Nadublje",
    "gn:country_code":"ME",
    "gn:dem":1164,
    "gn:feature_class":"P",
    "gn:feature_code":"PPL",
    "gn:name":"Nadublje",
    "gn:population":0,
    "gn:timezone":"Europe/Podgorica",
    "iso:country":"ME",
    "name:srp_x_preferred":[
        "Nadublje"
    ],
    "wof:name":"Nadublje",
    "wof:placetype":"locality"
},
  "geometry": {"coordinates":[18.90361,43.05861],"type":"Point"}
}