{
  "type": "Feature",
  "properties": {
    "gn:admin1_code":"14.0",
    "gn:asciiname":"Lijesce",
    "gn:country_code":"ME",
    "gn:dem":966,
    "gn:feature_class":"P",
    "gn:feature_code":"PPL",
    "gn:name":"Lije\u0161\u0107e",
    "gn:population":0,
    "gn:timezone":"Europe/Podgorica",
    "iso:country":"ME",
    "name:srp_x_preferred":[
        "Lije\u0161\u0107e"
    ],
    "wof:name":"Lijesce",
    "wof:placetype":"locality"
},
  "geometry": {"coordinates":[19.20028,43.43833],"type":"Point"}
}