{
  "type": "Feature",
  "properties": {
    "gn:admin1_code":"12.0",
    "gn:asciiname":"Buljusa",
    "gn:country_code":"ME",
    "gn:dem":1146,
    "gn:feature_class":"P",
    "gn:feature_code":"PPL",
    "gn:name":"Bulju\u0161a",
    "gn:population":0,
    "gn:timezone":"Europe/Podgorica",
    "iso:country":"ME",
    "name:und_x_variant":[
        "Gnjilavi Do",
        "Bulju\u0161a"
    ],
    "wof:name":"Buljusa",
    "wof:placetype":"locality"
},
  "geometry": {"coordinates":[18.59167,42.92],"type":"Point"}
}