{
  "type": "Feature",
  "properties": {
    "gn:admin1_code":"14.0",
    "gn:asciiname":"Potkras",
    "gn:country_code":"ME",
    "gn:dem":943,
    "gn:feature_class":"P",
    "gn:feature_code":"PPL",
    "gn:name":"Potkra\u0161",
    "gn:population":0,
    "gn:timezone":"Europe/Podgorica",
    "iso:country":"ME",
    "name:und_x_variant":[
        "Potkr\u0161",
        "Potkra\u0161"
    ],
    "wof:name":"Potkras",
    "wof:placetype":"locality"
},
  "geometry": {"coordinates":[19.40806,43.33194],"type":"Point"}
}