{
  "type": "Feature",
  "properties": {
    "gn:admin1_code":"14.0",
    "gn:asciiname":"Gornje Selo",
    "gn:country_code":"ME",
    "gn:dem":1012,
    "gn:feature_class":"P",
    "gn:feature_code":"PPLL",
    "gn:name":"Gornje Selo",
    "gn:population":0,
    "gn:timezone":"Europe/Podgorica",
    "iso:country":"ME",
    "wof:name":"Gornje Selo",
    "wof:placetype":"locality"
},
  "geometry": {"coordinates":[19.29389,43.26417],"type":"Point"}
}