{
  "type": "Feature",
  "properties": {
    "gn:admin1_code":"16.0",
    "gn:asciiname":"Vlase Vica",
    "gn:country_code":"ME",
    "gn:dem":656,
    "gn:feature_class":"P",
    "gn:feature_code":"PPL",
    "gn:name":"Vla\u0161e Vica",
    "gn:population":0,
    "gn:timezone":"Europe/Podgorica",
    "iso:country":"ME",
    "name:srp_x_preferred":[
        "Vla\u0161e Vica"
    ],
    "wof:name":"Vlase Vica",
    "wof:placetype":"locality"
},
  "geometry": {"coordinates":[19.36528,42.56944],"type":"Point"}
}