{
  "type": "Feature",
  "properties": {
    "gn:country":"ME",
    "gn:fcode":"PPL",
    "gn:pop":32,
    "iso:country":"ME",
    "name:srp_x_preferred":[
        "Dolovi"
    ],
    "qs:name":"Dolovi",
    "qs:photos_9r":0,
    "qs:photos_sr":0,
    "qs:pop_sr":"1",
    "wof:name":"Dolovi",
    "wof:placetype":"locality",
    "wof:population":32
},
  "geometry": {"coordinates":[19.05556,42.53417],"type":"Point"}
}