{
  "type": "Feature",
  "properties": {
    "gn:admin1_code":"16.0",
    "gn:asciiname":"Kostrikovica",
    "gn:country_code":"ME",
    "gn:dem":994,
    "gn:feature_class":"P",
    "gn:feature_code":"PPL",
    "gn:name":"Kostrikovica",
    "gn:population":0,
    "gn:timezone":"Europe/Podgorica",
    "iso:country":"ME",
    "name:srp_x_preferred":[
        "Kostrikovica"
    ],
    "wof:name":"Kostrikovica",
    "wof:placetype":"locality"
},
  "geometry": {"coordinates":[19.29306,42.5575],"type":"Point"}
}