{
  "type": "Feature",
  "properties": {
    "gn:admin1_code":"14.0",
    "gn:asciiname":"Sevari",
    "gn:country_code":"ME",
    "gn:dem":752,
    "gn:feature_class":"P",
    "gn:feature_code":"PPL",
    "gn:name":"Sevari",
    "gn:population":0,
    "gn:timezone":"Europe/Podgorica",
    "iso:country":"ME",
    "name:srp_x_preferred":[
        "Sevari"
    ],
    "wof:name":"Sevari",
    "wof:placetype":"locality"
},
  "geometry": {"coordinates":[19.34306,43.35278],"type":"Point"}
}