{
  "type": "Feature",
  "properties": {
    "gn:admin1_code":"17.0",
    "gn:asciiname":"Gornja Lovnica",
    "gn:country_code":"ME",
    "gn:dem":1206,
    "gn:feature_class":"P",
    "gn:feature_code":"PPL",
    "gn:name":"Gornja Lovnica",
    "gn:population":0,
    "gn:timezone":"Europe/Podgorica",
    "iso:country":"ME",
    "name:und_x_variant":[
        "Gornja Lomnica",
        "Gornja Lovnica"
    ],
    "wof:name":"Gornja Lovnica",
    "wof:placetype":"locality"
},
  "geometry": {"coordinates":[20.11528,42.89444],"type":"Point"}
}