{
  "type": "Feature",
  "properties": {
    "gn:admin1_code":"4.0",
    "gn:asciiname":"Parazlame",
    "gn:country_code":"ME",
    "gn:dem":1018,
    "gn:feature_class":"P",
    "gn:feature_code":"PPL",
    "gn:name":"Parazlame",
    "gn:population":0,
    "gn:timezone":"Europe/Podgorica",
    "iso:country":"ME",
    "name:srp_x_preferred":[
        "Parazlame"
    ],
    "wof:name":"Parazlame",
    "wof:placetype":"locality"
},
  "geometry": {"coordinates":[19.6275,43.18667],"type":"Point"}
}