{
  "type": "Feature",
  "properties": {
    "gn:admin1_code":"12.0",
    "gn:asciiname":"Bastasi",
    "gn:country_code":"ME",
    "gn:dem":790,
    "gn:feature_class":"P",
    "gn:feature_code":"PPL",
    "gn:name":"Bastasi",
    "gn:population":0,
    "gn:timezone":"Europe/Podgorica",
    "iso:country":"ME",
    "name:srp_x_preferred":[
        "Bastasi"
    ],
    "wof:name":"Bastasi",
    "wof:placetype":"locality"
},
  "geometry": {"coordinates":[19.08583,42.73806],"type":"Point"}
}