{
  "type": "Feature",
  "properties": {
    "gn:admin1_code":"11.0",
    "gn:asciiname":"Pakljesica",
    "gn:country_code":"ME",
    "gn:dem":811,
    "gn:feature_class":"P",
    "gn:feature_code":"PPL",
    "gn:name":"Paklje\u0161ica",
    "gn:population":0,
    "gn:timezone":"Europe/Podgorica",
    "iso:country":"ME",
    "name:srp_x_preferred":[
        "Paklje\u0161ica"
    ],
    "wof:name":"Pakljesica",
    "wof:placetype":"locality"
},
  "geometry": {"coordinates":[19.58806,42.95556],"type":"Point"}
}