{
  "type": "Feature",
  "properties": {
    "iso:country":"ME",
    "name:bel_x_variant":[
        "\u041a\u0430\u043b\u0430\u0448\u044b\u043d"
    ],
    "name:bos_x_preferred":[
        "Kola\u0161in"
    ],
    "name:bul_x_preferred":[
        "\u041a\u043e\u043b\u0430\u0448\u0438\u043d"
    ],
    "name:ces_x_preferred":[
        "Kola\u0161in"
    ],
    "name:che_x_preferred":[
        "\u041a\u043e\u043b\u0430\u0448\u0438\u043d"
    ],
    "name:deu_x_preferred":[
        "Kola\u0161in"
    ],
    "name:ell_x_preferred":[
        "\u039a\u03cc\u03bb\u03b1\u03c3\u03b9\u03bd"
    ],
    "name:eng_x_preferred":[
        "Kola\u0161in"
    ],
    "name:est_x_preferred":[
        "Kola\u0161ini vald"
    ],
    "name:fas_x_preferred":[
        "\u06a9\u0648\u0644\u0627\u0634\u06cc\u0646"
    ],
    "name:fin_x_preferred":[
        "Kola\u0161in"
    ],
    "name:fra_x_preferred":[
        "Kola\u0161in"
    ],
    "name:hbs_x_preferred":[
        "Kola\u0161in"
    ],
    "name:heb_x_preferred":[
        "\u05e7\u05d5\u05dc\u05d0\u05e9\u05d9\u05df"
    ],
    "name:hrv_x_preferred":[
        "Kola\u0161in"
    ],
    "name:ita_x_preferred":[
        "Kola\u0161in"
    ],
    "name:jpn_x_preferred":[
        "\u30b3\u30e9\u30b7\u30f3"
    ],
    "name:kat_x_preferred":[
        "\u10d9\u10dd\u10da\u10d0\u10e8\u10d8\u10dc\u10d8"
    ],
    "name:kor_x_preferred":[
        "\ucf5c\ub77c\uc2e0"
    ],
    "name:lit_x_preferred":[
        "Kola\u0161inas"
    ],
    "name:nld_x_preferred":[
        "Kola\u0161in"
    ],
    "name:nob_x_preferred":[
        "Kola\u0161in"
    ],
    "name:pol_x_preferred":[
        "Kola\u0161in"
    ],
    "name:por_x_preferred":[
        "Kola\u0161in"
    ],
    "name:ron_x_preferred":[
        "Kola\u0161in"
    ],
    "name:rus_x_preferred":[
        "\u041a\u043e\u043b\u0430\u0448\u0438\u043d"
    ],
    "name:slv_x_preferred":[
        "Kola\u0161in"
    ],
    "name:spa_x_preferred":[
        "Kola\u0161in"
    ],
    "name:sqi_x_preferred":[
        "Koloshini"
    ],
    "name:srp_x_preferred":[
        "\u041a\u043e\u043b\u0430\u0448\u0438\u043d"
    ],
    "name:tur_x_preferred":[
        "Kola\u015fin"
    ],
    "name:tur_x_variant":[
        "Kola\u0161in"
    ],
    "name:ukr_x_preferred":[
        "\u041a\u043e\u043b\u0430\u0448\u0438\u043d"
    ],
    "name:urd_x_preferred":[
        "\u06a9\u0648\u0644\u0627\u0634\u0646"
    ],
    "name:zho_x_preferred":[
        "\u79d1\u62c9\u6b23"
    ],
    "qs:gn_country":"ME",
    "qs:gn_fcode":"PPL",
    "qs:gn_pop":2989,
    "qs:name":"Kola\u00b5in",
    "qs:name_adm0":"Montenegro",
    "qs:name_adm1":"Kola\u0161in",
    "qs:photos":181,
    "qs:photos_1k":37,
    "qs:photos_9k":1,
    "qs:photos_9r":4,
    "qs:photos_all":181,
    "qs:photos_sr":4,
    "qs:placetype":"Town",
    "qs:pop_sr":"4",
    "qs:woe_adm0":20069817,
    "wd:wordcount":1101,
    "wof:name":"Kola\u00b5in",
    "wof:placetype":"locality",
    "wof:population":2989
},
  "geometry": {"coordinates":[19.51653,42.82229],"type":"Point"}
}