{
  "type": "Feature",
  "properties": {
    "gn:admin1_code":"12.0",
    "gn:asciiname":"Ornice",
    "gn:country_code":"ME",
    "gn:dem":625,
    "gn:feature_class":"P",
    "gn:feature_code":"PPL",
    "gn:name":"Ornice",
    "gn:population":0,
    "gn:timezone":"Europe/Podgorica",
    "iso:country":"ME",
    "name:bos_x_preferred":[
        "Ornice"
    ],
    "name:hrv_x_preferred":[
        "Ornice"
    ],
    "name:hun_x_preferred":[
        "Ornice"
    ],
    "name:nld_x_preferred":[
        "Ornice"
    ],
    "name:slv_x_preferred":[
        "Ornice"
    ],
    "name:spa_x_preferred":[
        "Ornice"
    ],
    "name:srp_x_preferred":[
        "Ornice"
    ],
    "name:srp_x_variant":[
        "\u041e\u0440\u043d\u0438\u0446\u0435"
    ],
    "name:ukr_x_preferred":[
        "\u041e\u0440\u043d\u0438\u0446\u0435"
    ],
    "wof:name":"Ornice",
    "wof:placetype":"locality"
},
  "geometry": {"coordinates":[18.93778,42.81417],"type":"Point"}
}