{
  "type": "Feature",
  "properties": {
    "gn:admin1_code":"12.0",
    "gn:asciiname":"Ornice",
    "gn:country_code":"ME",
    "gn:dem":625,
    "gn:feature_class":"P",
    "gn:feature_code":"PPL",
    "gn:name":"Ornice",
    "gn:population":0,
    "gn:timezone":"Europe/Podgorica",
    "iso:country":"ME",
    "name:srp_x_preferred":[
        "Ornice"
    ],
    "wof:name":"Ornice",
    "wof:placetype":"locality"
},
  "geometry": {"coordinates":[18.93778,42.81417],"type":"Point"}
}