{
  "type": "Feature",
  "properties": {
    "gn:admin1_code":"16.0",
    "gn:asciiname":"Potkrs",
    "gn:country_code":"ME",
    "gn:dem":314,
    "gn:feature_class":"P",
    "gn:feature_code":"PPL",
    "gn:name":"Potkr\u0161",
    "gn:population":0,
    "gn:timezone":"Europe/Podgorica",
    "iso:country":"ME",
    "name:srp_x_preferred":[
        "Potkr\u0161"
    ],
    "wof:name":"Potkrs",
    "wof:placetype":"locality"
},
  "geometry": {"coordinates":[19.37222,42.54556],"type":"Point"}
}