{
  "type": "Feature",
  "properties": {
    "gn:admin1_code":"4.0",
    "gn:asciiname":"Ravna Rijeka",
    "gn:country_code":"ME",
    "gn:dem":684,
    "gn:feature_class":"P",
    "gn:feature_code":"PPL",
    "gn:name":"Ravna Rijeka",
    "gn:population":0,
    "gn:timezone":"Europe/Podgorica",
    "iso:country":"ME",
    "name:fra_x_preferred":[
        "Ravna Rijeka"
    ],
    "name:ron_x_preferred":[
        "Ravna Rijeka"
    ],
    "name:slv_x_preferred":[
        "Ravna Rijeka"
    ],
    "name:srp_x_preferred":[
        "\u0420\u0430\u0432\u043d\u0430 \u0420\u0438\u0458\u0435\u043a\u0430"
    ],
    "name:und_x_variant":[
        "Vla\u0161ko Polje",
        "Ravna Rijeka"
    ],
    "wof:name":"Ravna Rijeka",
    "wof:placetype":"locality"
},
  "geometry": {"coordinates":[19.71444,42.98861],"type":"Point"}
}