{
  "type": "Feature",
  "properties": {
    "gn:admin1_code":"14.0",
    "gn:asciiname":"Alici",
    "gn:country_code":"ME",
    "gn:dem":851,
    "gn:feature_class":"P",
    "gn:feature_code":"PPL",
    "gn:name":"Ali\u0107i",
    "gn:population":0,
    "gn:timezone":"Europe/Podgorica",
    "iso:country":"ME",
    "name:fra_x_preferred":[
        "Ali\u0107i"
    ],
    "name:ron_x_preferred":[
        "Ali\u0107i"
    ],
    "name:slv_x_preferred":[
        "Ali\u017ei"
    ],
    "name:srp_x_preferred":[
        "Ali\u0107i"
    ],
    "name:srp_x_variant":[
        "\u0410\u043b\u0438\u045b\u0438"
    ],
    "wof:name":"Alici",
    "wof:placetype":"locality"
},
  "geometry": {"coordinates":[19.35639,43.25583],"type":"Point"}
}