{
  "type": "Feature",
  "properties": {
    "gn:admin1_code":"12.0",
    "gn:asciiname":"Boksin Do",
    "gn:country_code":"ME",
    "gn:dem":884,
    "gn:feature_class":"P",
    "gn:feature_code":"PPL",
    "gn:name":"Bok\u0161in Do",
    "gn:population":0,
    "gn:timezone":"Europe/Podgorica",
    "iso:country":"ME",
    "name:srp_x_preferred":[
        "Bok\u0161in Do"
    ],
    "wof:name":"Boksin Do",
    "wof:placetype":"locality"
},
  "geometry": {"coordinates":[18.66833,42.66861],"type":"Point"}
}