{
  "type": "Feature",
  "properties": {
    "gn:admin1_code":"1.0",
    "gn:asciiname":"Jagnjilo",
    "gn:country_code":"ME",
    "gn:dem":878,
    "gn:feature_class":"P",
    "gn:feature_code":"PPL",
    "gn:name":"Jagnjilo",
    "gn:population":0,
    "gn:timezone":"Europe/Podgorica",
    "iso:country":"ME",
    "name:srp_x_preferred":[
        "Jagnjilo"
    ],
    "wof:name":"Jagnjilo",
    "wof:placetype":"locality"
},
  "geometry": {"coordinates":[19.835,42.70806],"type":"Point"}
}