{
  "type": "Feature",
  "properties": {
    "gn:admin1_code":"1.0",
    "gn:asciiname":"Jagnjilo",
    "gn:country_code":"ME",
    "gn:dem":878,
    "gn:feature_class":"P",
    "gn:feature_code":"PPL",
    "gn:name":"Jagnjilo",
    "gn:population":0,
    "gn:timezone":"Europe/Podgorica",
    "iso:country":"ME",
    "name:ceb_x_preferred":[
        "Jagnjilo"
    ],
    "name:fra_x_preferred":[
        "Jagnjilo"
    ],
    "name:msa_x_preferred":[
        "Jagnjilo"
    ],
    "name:nld_x_preferred":[
        "Jagnjilo"
    ],
    "name:por_x_preferred":[
        "Jagnjilo"
    ],
    "name:slv_x_preferred":[
        "Jagnjilo"
    ],
    "name:srp_x_preferred":[
        "Jagnjilo"
    ],
    "name:srp_x_variant":[
        "\u0408\u0430\u0433\u045a\u0438\u043b\u043e"
    ],
    "name:urd_x_preferred":[
        "\u062c\u06af\u0646\u062c\u06cc\u0644\u0648"
    ],
    "wof:name":"Jagnjilo",
    "wof:placetype":"locality"
},
  "geometry": {"coordinates":[19.835,42.70806],"type":"Point"}
}