{
  "type": "Feature",
  "properties": {
    "gn:admin1_code":"12.0",
    "gn:asciiname":"Cerovo",
    "gn:country_code":"ME",
    "gn:dem":377,
    "gn:feature_class":"P",
    "gn:feature_code":"PPLL",
    "gn:name":"Cerovo",
    "gn:population":0,
    "gn:timezone":"Europe/Podgorica",
    "iso:country":"ME",
    "name:bos_x_preferred":[
        "Cerovo"
    ],
    "name:bul_x_preferred":[
        "\u0426\u0435\u0440\u043e\u0432\u043e"
    ],
    "name:ceb_x_preferred":[
        "Cerovo"
    ],
    "name:eus_x_preferred":[
        "Cerovo"
    ],
    "name:fra_x_preferred":[
        "Cerovo"
    ],
    "name:hrv_x_preferred":[
        "Cerovo"
    ],
    "name:mkd_x_preferred":[
        "\u0426\u0435\u0440\u043e\u0432\u043e"
    ],
    "name:nld_x_preferred":[
        "Cerovo"
    ],
    "name:ron_x_preferred":[
        "\u021aerovo"
    ],
    "name:rus_x_preferred":[
        "\u0426\u0435\u0440\u043e\u0432\u043e"
    ],
    "name:slk_x_preferred":[
        "Cerovo"
    ],
    "name:slv_x_preferred":[
        "Cerovo"
    ],
    "name:srp_x_preferred":[
        "\u0426\u0435\u0440\u043e\u0432\u043e"
    ],
    "name:swe_x_preferred":[
        "Cerovo"
    ],
    "name:ukr_x_preferred":[
        "\u0426\u0435\u0440\u043e\u0432\u043e"
    ],
    "wof:name":"Cerovo",
    "wof:placetype":"locality"
},
  "geometry": {"coordinates":[18.97278,42.66917],"type":"Point"}
}