{
  "type": "Feature",
  "properties": {
    "gn:admin1_code":"14.0",
    "gn:asciiname":"Crvena Lokva",
    "gn:country_code":"ME",
    "gn:dem":1481,
    "gn:feature_class":"P",
    "gn:feature_code":"PPLL",
    "gn:name":"Crvena Lokva",
    "gn:population":0,
    "gn:timezone":"Europe/Podgorica",
    "iso:country":"ME",
    "wof:name":"Crvena Lokva",
    "wof:placetype":"locality"
},
  "geometry": {"coordinates":[19.42806,43.05694],"type":"Point"}
}