{
  "type": "Feature",
  "properties": {
    "gn:admin1_code":"23.0",
    "gn:asciiname":"Bor",
    "gn:country_code":"ME",
    "gn:dem":1201,
    "gn:feature_class":"P",
    "gn:feature_code":"PPLL",
    "gn:name":"Bor",
    "gn:population":0,
    "gn:timezone":"Europe/Podgorica",
    "iso:country":"ME",
    "wof:name":"Bor",
    "wof:placetype":"locality"
},
  "geometry": {"coordinates":[20.01306,42.94722],"type":"Point"}
}