{
  "type": "Feature",
  "properties": {
    "gn:admin1_code":"10.0",
    "gn:asciiname":"Kavac",
    "gn:country_code":"ME",
    "gn:dem":124,
    "gn:feature_class":"P",
    "gn:feature_code":"PPLL",
    "gn:name":"Kava\u010d",
    "gn:population":0,
    "gn:timezone":"Europe/Podgorica",
    "iso:country":"ME",
    "wof:name":"Kavac",
    "wof:placetype":"locality"
},
  "geometry": {"coordinates":[18.74472,42.41222],"type":"Point"}
}