{
  "type": "Feature",
  "properties": {
    "gn:admin1_code":"15.0",
    "gn:asciiname":"Dondici",
    "gn:country_code":"ME",
    "gn:dem":1371,
    "gn:feature_class":"P",
    "gn:feature_code":"PPL",
    "gn:name":"Dondi\u0107i",
    "gn:population":0,
    "gn:timezone":"Europe/Podgorica",
    "iso:country":"ME",
    "name:srp_x_preferred":[
        "Dondi\u0107i"
    ],
    "wof:name":"Dondici",
    "wof:placetype":"locality"
},
  "geometry": {"coordinates":[18.90778,43.17806],"type":"Point"}
}