{
  "type": "Feature",
  "properties": {
    "gn:admin1_code":"17.0",
    "gn:asciiname":"Ovna",
    "gn:country_code":"ME",
    "gn:dem":1168,
    "gn:feature_class":"P",
    "gn:feature_code":"PPL",
    "gn:name":"Ovna",
    "gn:population":0,
    "gn:timezone":"Europe/Podgorica",
    "iso:country":"ME",
    "name:srp_x_preferred":[
        "Ovna"
    ],
    "wof:name":"Ovna",
    "wof:placetype":"locality"
},
  "geometry": {"coordinates":[20.31972,42.87917],"type":"Point"}
}