{
  "type": "Feature",
  "properties": {
    "gn:admin1_code":"12.0",
    "gn:asciiname":"Ziva",
    "gn:country_code":"ME",
    "gn:dem":1069,
    "gn:feature_class":"P",
    "gn:feature_code":"PPL",
    "gn:name":"\u017diva",
    "gn:population":0,
    "gn:timezone":"Europe/Podgorica",
    "iso:country":"ME",
    "name:srp_x_preferred":[
        "\u017diva"
    ],
    "wof:name":"Ziva",
    "wof:placetype":"locality"
},
  "geometry": {"coordinates":[18.70611,42.68722],"type":"Point"}
}