{
  "type": "Feature",
  "properties": {
    "gn:admin1_code":"18.0",
    "gn:asciiname":"Cer",
    "gn:country_code":"ME",
    "gn:dem":1153,
    "gn:feature_class":"P",
    "gn:feature_code":"PPL",
    "gn:name":"Cer",
    "gn:population":0,
    "gn:timezone":"Europe/Podgorica",
    "iso:country":"ME",
    "name:und_x_variant":[
        "Dolina",
        "Cer"
    ],
    "wof:name":"Cer",
    "wof:placetype":"locality"
},
  "geometry": {"coordinates":[19.18167,42.96444],"type":"Point"}
}