{
  "type": "Feature",
  "properties": {
    "gn:admin1_code":"14.0",
    "gn:asciiname":"Besevina",
    "gn:country_code":"ME",
    "gn:dem":867,
    "gn:feature_class":"P",
    "gn:feature_code":"PPL",
    "gn:name":"Be\u0161evina",
    "gn:population":0,
    "gn:timezone":"Europe/Podgorica",
    "iso:country":"ME",
    "name:srp_x_preferred":[
        "Be\u0161evina"
    ],
    "wof:name":"Besevina",
    "wof:placetype":"locality"
},
  "geometry": {"coordinates":[19.21833,43.37583],"type":"Point"}
}