{
  "type": "Feature",
  "properties": {
    "gn:country":"ME",
    "gn:fcode":"PPL",
    "gn:pop":44,
    "iso:country":"ME",
    "name:srp_x_preferred":[
        "Bra\u0107ani"
    ],
    "qs:name":"Bra\u0107ani",
    "qs:photos_9r":0,
    "qs:photos_sr":0,
    "qs:pop_sr":"1",
    "wof:name":"Bra\u0107ani",
    "wof:placetype":"locality",
    "wof:population":44
},
  "geometry": {"coordinates":[19.10583,42.48278],"type":"Point"}
}