{
  "type": "Feature",
  "properties": {
    "gn:country":"ME",
    "gn:fcode":"PPL",
    "gn:population":39,
    "iso:country":"ME",
    "name:srp_x_preferred":[
        "Za\u010dir"
    ],
    "qs:name":"Za\u010dir",
    "qs:photos_9r":0,
    "qs:photos_sr":0,
    "qs:pop_sr":"1",
    "wof:name":"Za\u010dir",
    "wof:placetype":"locality",
    "wof:population":39
},
  "geometry": {"coordinates":[18.99694,42.34333],"type":"Point"}
}