{
  "type": "Feature",
  "properties": {
    "gn:admin1_code":"10.0",
    "gn:asciiname":"Vitoglav",
    "gn:country_code":"ME",
    "gn:dem":88,
    "gn:feature_class":"P",
    "gn:feature_code":"PPL",
    "gn:name":"Vitoglav",
    "gn:population":0,
    "gn:timezone":"Europe/Podgorica",
    "iso:country":"ME",
    "name:srp_x_preferred":[
        "Vitoglav"
    ],
    "wof:name":"Vitoglav",
    "wof:placetype":"locality"
},
  "geometry": {"coordinates":[18.68083,42.51528],"type":"Point"}
}