{
  "type": "Feature",
  "properties": {
    "gn:admin1_code":"9.0",
    "gn:asciiname":"Vinogradine",
    "gn:country_code":"ME",
    "gn:dem":603,
    "gn:feature_class":"P",
    "gn:feature_code":"PPL",
    "gn:name":"Vinogradine",
    "gn:population":0,
    "gn:timezone":"Europe/Podgorica",
    "iso:country":"ME",
    "name:srp_x_preferred":[
        "Vinogradine"
    ],
    "wof:name":"Vinogradine",
    "wof:placetype":"locality"
},
  "geometry": {"coordinates":[19.42778,42.73389],"type":"Point"}
}