{
  "type": "Feature",
  "properties": {
    "gn:admin1_code":"16.0",
    "gn:asciiname":"Steci",
    "gn:country_code":"ME",
    "gn:dem":132,
    "gn:feature_class":"P",
    "gn:feature_code":"PPL",
    "gn:name":"\u0160teci",
    "gn:population":0,
    "gn:timezone":"Europe/Podgorica",
    "iso:country":"ME",
    "name:srp_x_preferred":[
        "\u0160teci"
    ],
    "wof:name":"Steci",
    "wof:placetype":"locality"
},
  "geometry": {"coordinates":[19.17583,42.41472],"type":"Point"}
}