{
  "type": "Feature",
  "properties": {
    "gn:admin1_code":"9.0",
    "gn:asciiname":"Strelicki Krs",
    "gn:country_code":"ME",
    "gn:dem":942,
    "gn:feature_class":"P",
    "gn:feature_code":"PPL",
    "gn:name":"Streli\u010dki Kr\u0161",
    "gn:population":0,
    "gn:timezone":"Europe/Podgorica",
    "iso:country":"ME",
    "name:srp_x_preferred":[
        "Streli\u010dki Kr\u0161"
    ],
    "wof:name":"Strelicki Krs",
    "wof:placetype":"locality"
},
  "geometry": {"coordinates":[19.51583,42.81694],"type":"Point"}
}