{
  "type": "Feature",
  "properties": {
    "gn:admin1_code":"12.0",
    "gn:asciiname":"Mali Orah",
    "gn:country_code":"ME",
    "gn:dem":721,
    "gn:feature_class":"P",
    "gn:feature_code":"PPL",
    "gn:name":"Mali Orah",
    "gn:population":0,
    "gn:timezone":"Europe/Podgorica",
    "iso:country":"ME",
    "name:srp_x_preferred":[
        "Mali Orah"
    ],
    "wof:name":"Mali Orah",
    "wof:placetype":"locality"
},
  "geometry": {"coordinates":[18.96833,42.86111],"type":"Point"}
}