{
  "type": "Feature",
  "properties": {
    "gn:country":"ME",
    "gn:fcode":"PPL",
    "gn:pop":16,
    "iso:country":"ME",
    "name:eng_x_preferred":[
        "Plakala"
    ],
    "name:fra_x_preferred":[
        "Plakala"
    ],
    "name:nld_x_preferred":[
        "Plakala"
    ],
    "name:ron_x_preferred":[
        "Plakala"
    ],
    "name:slv_x_preferred":[
        "Plakala"
    ],
    "name:srp_x_preferred":[
        "\u041f\u043b\u0430\u043a\u0430\u043b\u0430"
    ],
    "name:unk_x_variant":[
        "Plakala"
    ],
    "qs:name":"Plakali",
    "qs:photos_9r":0,
    "qs:photos_sr":0,
    "qs:pop_sr":"1",
    "wd:wordcount":105,
    "wof:name":"Plakali",
    "wof:placetype":"locality",
    "wof:population":16
},
  "geometry": {"coordinates":[19.08806,43.45667],"type":"Point"}
}