{
  "type": "Feature",
  "properties": {
    "gn:admin1_code":"9.0",
    "gn:asciiname":"Stolak",
    "gn:country_code":"ME",
    "gn:dem":616,
    "gn:feature_class":"P",
    "gn:feature_code":"PPL",
    "gn:name":"Stolak",
    "gn:population":0,
    "gn:timezone":"Europe/Podgorica",
    "iso:country":"ME",
    "name:srp_x_preferred":[
        "Stolak"
    ],
    "wof:name":"Stolak",
    "wof:placetype":"locality"
},
  "geometry": {"coordinates":[19.36333,42.74833],"type":"Point"}
}