{
  "type": "Feature",
  "properties": {
    "gn:admin1_code":"16.0",
    "gn:asciiname":"Misocelo",
    "gn:country_code":"ME",
    "gn:dem":983,
    "gn:feature_class":"P",
    "gn:feature_code":"PPL",
    "gn:name":"Miso\u010delo",
    "gn:population":0,
    "gn:timezone":"Europe/Podgorica",
    "iso:country":"ME",
    "name:srp_x_preferred":[
        "Miso\u010delo"
    ],
    "wof:name":"Misocelo",
    "wof:placetype":"locality"
},
  "geometry": {"coordinates":[18.99361,42.47806],"type":"Point"}
}