{
  "type": "Feature",
  "properties": {
    "gn:admin1_code":"3.0",
    "gn:asciiname":"Jodole",
    "gn:country_code":"ME",
    "gn:dem":864,
    "gn:feature_class":"P",
    "gn:feature_code":"PPL",
    "gn:name":"Jodole",
    "gn:population":0,
    "gn:timezone":"Europe/Podgorica",
    "iso:country":"ME",
    "name:und_x_variant":[
        "Dine",
        "Jodole"
    ],
    "wof:name":"Jodole",
    "wof:placetype":"locality"
},
  "geometry": {"coordinates":[19.92139,42.89056],"type":"Point"}
}