{
  "type": "Feature",
  "properties": {
    "gn:admin1_code":"17.0",
    "gn:asciiname":"Koljeno",
    "gn:country_code":"ME",
    "gn:dem":1157,
    "gn:feature_class":"P",
    "gn:feature_code":"PPL",
    "gn:name":"Koljeno",
    "gn:population":0,
    "gn:timezone":"Europe/Podgorica",
    "iso:country":"ME",
    "name:und_x_variant":[
        "Koleno",
        "Koljeno"
    ],
    "wof:name":"Koljeno",
    "wof:placetype":"locality"
},
  "geometry": {"coordinates":[20.10444,42.83861],"type":"Point"}
}