{
  "type": "Feature",
  "properties": {
    "gn:admin1_code":"4.0",
    "gn:asciiname":"Tustvo",
    "gn:country_code":"ME",
    "gn:dem":711,
    "gn:feature_class":"P",
    "gn:feature_code":"PPL",
    "gn:name":"Tustvo",
    "gn:population":0,
    "gn:timezone":"Europe/Podgorica",
    "iso:country":"ME",
    "name:und_x_variant":[
        "Tustovo",
        "Tustvo"
    ],
    "wof:name":"Tustvo",
    "wof:placetype":"locality"
},
  "geometry": {"coordinates":[19.65917,43.02139],"type":"Point"}
}