{
  "type": "Feature",
  "properties": {
    "gn:admin1_code":"3.0",
    "gn:asciiname":"Donje Zaostro",
    "gn:country_code":"ME",
    "gn:dem":750,
    "gn:feature_class":"P",
    "gn:feature_code":"PPL",
    "gn:name":"Donje Zaostro",
    "gn:population":0,
    "gn:timezone":"Europe/Podgorica",
    "iso:country":"ME",
    "name:srp_x_preferred":[
        "Donje Zaostro"
    ],
    "wof:name":"Donje Zaostro",
    "wof:placetype":"locality"
},
  "geometry": {"coordinates":[19.85528,42.88583],"type":"Point"}
}