{
  "type": "Feature",
  "properties": {
    "gn:country":"ME",
    "gn:fcode":"PPL",
    "gn:pop":62,
    "iso:country":"ME",
    "name:unk_x_variant":[
        "Komarino"
    ],
    "qs:name":"Komarno",
    "qs:photos_9r":0,
    "qs:photos_sr":0,
    "qs:pop_sr":"1",
    "wd:wordcount":51,
    "wof:name":"Komarno",
    "wof:placetype":"locality",
    "wof:population":62
},
  "geometry": {"coordinates":[19.06083,42.28833],"type":"Point"}
}