{
  "type": "Feature",
  "properties": {
    "gn:admin1_code":"6.0",
    "gn:asciiname":"Pozduj",
    "gn:country_code":"ME",
    "gn:dem":708,
    "gn:feature_class":"P",
    "gn:feature_code":"PPL",
    "gn:name":"Pozduj",
    "gn:population":0,
    "gn:timezone":"Europe/Podgorica",
    "iso:country":"ME",
    "name:srp_x_preferred":[
        "Pozduj"
    ],
    "wof:name":"Pozduj",
    "wof:placetype":"locality"
},
  "geometry": {"coordinates":[18.89833,42.39889],"type":"Point"}
}