{
  "type": "Feature",
  "properties": {
    "gn:country":"ME",
    "gn:fcode":"PPL",
    "gn:population":18,
    "iso:country":"ME",
    "name:eng_x_preferred":[
        "Kru\u0161evica"
    ],
    "name:fra_x_preferred":[
        "Kru\u0161evica"
    ],
    "name:nld_x_preferred":[
        "Kru\u0161evica"
    ],
    "name:ron_x_preferred":[
        "Kru\u0161evica"
    ],
    "name:slv_x_preferred":[
        "Kru\u0161evica"
    ],
    "name:srp_x_preferred":[
        "\u041a\u0440\u0443\u0448\u0435\u0432\u0438\u0446\u0430"
    ],
    "name:und_x_variant":[
        "Dabovi\u0107i"
    ],
    "qs:name":"Kru\u0161evica",
    "qs:photos_9r":0,
    "qs:photos_sr":0,
    "qs:pop_sr":"1",
    "wd:wordcount":76,
    "wof:name":"Kru\u0161evica",
    "wof:placetype":"locality",
    "wof:population":18
},
  "geometry": {"coordinates":[19.08278,42.26833],"type":"Point"}
}