{
  "type": "Feature",
  "properties": {
    "gn:admin1_code":"9.0",
    "gn:asciiname":"Vozarine",
    "gn:country_code":"ME",
    "gn:dem":865,
    "gn:feature_class":"P",
    "gn:feature_code":"PPL",
    "gn:name":"Vozarine",
    "gn:population":0,
    "gn:timezone":"Europe/Podgorica",
    "iso:country":"ME",
    "name:und_x_variant":[
        "Vozarina",
        "Vozarine"
    ],
    "wof:name":"Vozarine",
    "wof:placetype":"locality"
},
  "geometry": {"coordinates":[19.37389,42.8325],"type":"Point"}
}