{
  "type": "Feature",
  "properties": {
    "gn:admin1_code":"10.0",
    "gn:asciiname":"Kubasi",
    "gn:country_code":"ME",
    "gn:dem":254,
    "gn:feature_class":"P",
    "gn:feature_code":"PPL",
    "gn:name":"Kubasi",
    "gn:population":0,
    "gn:timezone":"Europe/Podgorica",
    "iso:country":"ME",
    "name:srp_x_preferred":[
        "Kubasi"
    ],
    "wof:name":"Kubasi",
    "wof:placetype":"locality"
},
  "geometry": {"coordinates":[18.75639,42.32444],"type":"Point"}
}