{
  "type": "Feature",
  "properties": {
    "gn:country":"ME",
    "gn:fcode":"PPL",
    "gn:population":34,
    "iso:country":"ME",
    "name:srp_x_preferred":[
        "Bokovo"
    ],
    "qs:name":"Bokovo",
    "qs:photos_9r":0,
    "qs:photos_sr":0,
    "qs:pop_sr":"1",
    "wof:name":"Bokovo",
    "wof:placetype":"locality",
    "wof:population":34
},
  "geometry": {"coordinates":[18.97,42.39861],"type":"Point"}
}