{
  "type": "Feature",
  "properties": {
    "gn:admin1_code":"8.0",
    "gn:asciiname":"Vecerici",
    "gn:country_code":"ME",
    "gn:dem":167,
    "gn:feature_class":"P",
    "gn:feature_code":"PPL",
    "gn:name":"Ve\u010deri\u0107i",
    "gn:population":0,
    "gn:timezone":"Europe/Podgorica",
    "iso:country":"ME",
    "name:srp_x_preferred":[
        "Ve\u010deri\u0107i"
    ],
    "wof:name":"Vecerici",
    "wof:placetype":"locality"
},
  "geometry": {"coordinates":[18.57306,42.41139],"type":"Point"}
}