{
  "type": "Feature",
  "properties": {
    "gn:country":"ME",
    "gn:fcode":"PPLL",
    "gn:pop":31,
    "iso:country":"ME",
    "name:unk_x_variant":[
        "Dujevo"
    ],
    "qs:name":"Dujeva",
    "qs:photos_9r":0,
    "qs:photos_sr":0,
    "qs:pop_sr":"1",
    "wof:name":"Dujeva",
    "wof:placetype":"locality",
    "wof:population":31
},
  "geometry": {"coordinates":[19.06611,42.33528],"type":"Point"}
}