{
  "type": "Feature",
  "properties": {
    "gn:admin1_code":"12.0",
    "gn:asciiname":"Glusje Selo",
    "gn:country_code":"ME",
    "gn:dem":767,
    "gn:feature_class":"P",
    "gn:feature_code":"PPL",
    "gn:name":"Glu\u0161je Selo",
    "gn:population":0,
    "gn:timezone":"Europe/Podgorica",
    "iso:country":"ME",
    "name:srp_x_preferred":[
        "Glu\u0161je Selo"
    ],
    "wof:name":"Glusje Selo",
    "wof:placetype":"locality"
},
  "geometry": {"coordinates":[19.05833,42.74194],"type":"Point"}
}