{
  "type": "Feature",
  "properties": {
    "gn:admin1_code":"16.0",
    "gn:asciiname":"Zagrade",
    "gn:country_code":"ME",
    "gn:dem":103,
    "gn:feature_class":"P",
    "gn:feature_code":"PPL",
    "gn:name":"Zagra\u0111e",
    "gn:population":0,
    "gn:timezone":"Europe/Podgorica",
    "iso:country":"ME",
    "name:fra_x_preferred":[
        "Zagra\u0111e"
    ],
    "name:ron_x_preferred":[
        "Zagra\u0111e"
    ],
    "name:slv_x_preferred":[
        "Zagra\u0111e Bar"
    ],
    "name:srp_x_preferred":[
        "Zagra\u0111e"
    ],
    "name:srp_x_variant":[
        "\u0417\u0430\u0433\u0440\u0430\u0452\u0435"
    ],
    "wof:name":"Zagrade",
    "wof:placetype":"locality"
},
  "geometry": {"coordinates":[19.34167,42.51944],"type":"Point"}
}