{
  "type": "Feature",
  "properties": {
    "gn:admin1_code":"4.0",
    "gn:asciiname":"Lekovina",
    "gn:country_code":"ME",
    "gn:dem":929,
    "gn:feature_class":"P",
    "gn:feature_code":"PPLL",
    "gn:name":"Lekovina",
    "gn:population":0,
    "gn:timezone":"Europe/Podgorica",
    "iso:country":"ME",
    "name:fra_x_preferred":[
        "Lekovina"
    ],
    "name:ron_x_preferred":[
        "Lekovina"
    ],
    "name:slv_x_preferred":[
        "Lekovina"
    ],
    "name:srp_x_preferred":[
        "\u041b\u0435\u043a\u043e\u0432\u0438\u043d\u0430"
    ],
    "wof:name":"Lekovina",
    "wof:placetype":"locality"
},
  "geometry": {"coordinates":[19.6125,43.15194],"type":"Point"}
}