{
  "type": "Feature",
  "properties": {
    "gn:country":"ME",
    "gn:fcode":"PPL",
    "gn:pop":5,
    "iso:country":"ME",
    "name:srp_x_preferred":[
        "\u010cavori"
    ],
    "qs:name":"\u010cavori",
    "qs:photos_9r":0,
    "qs:photos_sr":0,
    "qs:pop_sr":"1",
    "wof:name":"\u010cavori",
    "wof:placetype":"locality",
    "wof:population":5
},
  "geometry": {"coordinates":[18.80472,42.36361],"type":"Point"}
}