{
  "type": "Feature",
  "properties": {
    "gn:admin1_code":"22.0",
    "gn:asciiname":"Grncar",
    "gn:country_code":"ME",
    "gn:dem":935,
    "gn:feature_class":"P",
    "gn:feature_code":"PPLL",
    "gn:name":"Grn\u010dar",
    "gn:population":0,
    "gn:timezone":"Europe/Podgorica",
    "iso:country":"ME",
    "wof:name":"Grncar",
    "wof:placetype":"locality"
},
  "geometry": {"coordinates":[19.79694,42.57667],"type":"Point"}
}