{
  "type": "Feature",
  "properties": {
    "gn:country":"ME",
    "gn:fcode":"PPL",
    "gn:pop":5,
    "iso:country":"ME",
    "qs:name":"Gornji Su\u0161anj",
    "qs:photos_9r":0,
    "qs:photos_sr":0,
    "qs:pop_sr":"1",
    "wof:name":"Gornji Su\u0161anj",
    "wof:placetype":"locality",
    "wof:population":5
},
  "geometry": {"coordinates":[19.08,42.12472],"type":"Point"}
}