{
  "type": "Feature",
  "properties": {
    "gn:admin1_code":"4.0",
    "gn:asciiname":"Zaton",
    "gn:country_code":"ME",
    "gn:dem":646,
    "gn:feature_class":"P",
    "gn:feature_code":"PPL",
    "gn:name":"Zaton",
    "gn:population":0,
    "gn:timezone":"Europe/Podgorica",
    "iso:country":"ME",
    "name:fra_x_preferred":[
        "Zaton"
    ],
    "name:ron_x_preferred":[
        "Zaton"
    ],
    "name:slv_x_preferred":[
        "Zaton"
    ],
    "name:srp_x_preferred":[
        "Zaton"
    ],
    "name:srp_x_variant":[
        "\u0417\u0430\u0442\u043e\u043d"
    ],
    "wof:name":"Zaton",
    "wof:placetype":"locality"
},
  "geometry": {"coordinates":[19.78611,43.00306],"type":"Point"}
}