{
  "type": "Feature",
  "properties": {
    "gn:country":"ME",
    "gn:fcode":"PPL",
    "gn:pop":5,
    "iso:country":"ME",
    "name:eng_x_preferred":[
        "Bukovik"
    ],
    "name:fra_x_preferred":[
        "Bukovik"
    ],
    "name:nld_x_preferred":[
        "Bukovik"
    ],
    "name:ron_x_preferred":[
        "Bukovik"
    ],
    "name:slv_x_preferred":[
        "Bukovik"
    ],
    "name:sqi_x_preferred":[
        "Bukoviku"
    ],
    "name:srp_x_preferred":[
        "Bukovik"
    ],
    "name:srp_x_variant":[
        "\u0411\u0443\u043a\u043e\u0432\u0438\u043a"
    ],
    "qs:name":"Bukovik",
    "qs:photos_9r":0,
    "qs:photos_sr":0,
    "qs:pop_sr":"1",
    "wd:wordcount":29,
    "wof:name":"Bukovik",
    "wof:placetype":"locality",
    "wof:population":5
},
  "geometry": {"coordinates":[18.94306,42.30667],"type":"Point"}
}