{
  "type": "Feature",
  "properties": {
    "gn:admin1_code":"17.0",
    "gn:asciiname":"Donja Lovnica",
    "gn:country_code":"ME",
    "gn:dem":1140,
    "gn:feature_class":"P",
    "gn:feature_code":"PPL",
    "gn:name":"Donja Lovnica",
    "gn:population":0,
    "gn:timezone":"Europe/Podgorica",
    "iso:country":"ME",
    "name:und_x_variant":[
        "Ramovi\u0107i",
        "Dolenji Lovnica",
        "Donja Lovnica"
    ],
    "wof:name":"Donja Lovnica",
    "wof:placetype":"locality"
},
  "geometry": {"coordinates":[20.13889,42.87056],"type":"Point"}
}