{
  "type": "Feature",
  "properties": {
    "gn:admin1_code":"16.0",
    "gn:asciiname":"Babljace",
    "gn:country_code":"ME",
    "gn:dem":956,
    "gn:feature_class":"P",
    "gn:feature_code":"PPL",
    "gn:name":"Bablja\u010de",
    "gn:population":0,
    "gn:timezone":"Europe/Podgorica",
    "iso:country":"ME",
    "name:srp_x_preferred":[
        "Bablja\u010de"
    ],
    "wof:name":"Babljace",
    "wof:placetype":"locality"
},
  "geometry": {"coordinates":[19.47083,42.63306],"type":"Point"}
}