{
  "type": "Feature",
  "properties": {
    "gn:admin1_code":"14.0",
    "gn:asciiname":"Krusevo",
    "gn:country_code":"ME",
    "gn:dem":920,
    "gn:feature_class":"P",
    "gn:feature_code":"PPL",
    "gn:name":"Kru\u0161evo",
    "gn:population":0,
    "gn:timezone":"Europe/Podgorica",
    "iso:country":"ME",
    "name:und_x_variant":[
        "Kula",
        "Kru\u0161evo"
    ],
    "wof:name":"Krusevo",
    "wof:placetype":"locality"
},
  "geometry": {"coordinates":[19.02917,43.40611],"type":"Point"}
}