{
  "type": "Feature",
  "properties": {
    "gn:country":"ME",
    "gn:fcode":"PPLL",
    "gn:pop":196,
    "iso:country":"ME",
    "qs:name":"Ro\u0161ca",
    "qs:photos_9r":0,
    "qs:photos_sr":0,
    "qs:pop_sr":"1",
    "wof:name":"Ro\u0161ca",
    "wof:placetype":"locality",
    "wof:population":196
},
  "geometry": {"coordinates":[19.01139,42.65972],"type":"Point"}
}