{
  "type": "Feature",
  "properties": {
    "gn:admin1_code":"6.0",
    "gn:asciiname":"Jama Cevska",
    "gn:country_code":"ME",
    "gn:dem":1001,
    "gn:feature_class":"P",
    "gn:feature_code":"PPL",
    "gn:name":"Jama \u010cevska",
    "gn:population":0,
    "gn:timezone":"Europe/Podgorica",
    "iso:country":"ME",
    "name:srp_x_preferred":[
        "Jama \u010cevska"
    ],
    "wof:name":"Jama Cevska",
    "wof:placetype":"locality"
},
  "geometry": {"coordinates":[18.92083,42.56139],"type":"Point"}
}