{
  "type": "Feature",
  "properties": {
    "gn:admin1_code":"2.0",
    "gn:asciiname":"Alibrahimaj",
    "gn:country_code":"ME",
    "gn:dem":184,
    "gn:feature_class":"P",
    "gn:feature_code":"PPL",
    "gn:name":"Alibrahimaj",
    "gn:population":0,
    "gn:timezone":"Europe/Podgorica",
    "iso:country":"ME",
    "name:srp_x_preferred":[
        "Alibrahimaj"
    ],
    "wof:name":"Alibrahimaj",
    "wof:placetype":"locality"
},
  "geometry": {"coordinates":[19.29833,42.09111],"type":"Point"}
}