{
  "type": "Feature",
  "properties": {
    "gn:country":"ME",
    "gn:fcode":"PPL",
    "gn:pop":5,
    "iso:country":"ME",
    "name:srp_x_preferred":[
        "Brguli"
    ],
    "qs:name":"Brguli",
    "qs:photos_9r":0,
    "qs:photos_sr":0,
    "qs:pop_sr":"1",
    "wof:name":"Brguli",
    "wof:placetype":"locality",
    "wof:population":5
},
  "geometry": {"coordinates":[18.61722,42.3925],"type":"Point"}
}