{
  "type": "Feature",
  "properties": {
    "gn:admin1_code":"10.0",
    "gn:asciiname":"Drazin Vrt",
    "gn:country_code":"ME",
    "gn:dem":6,
    "gn:feature_class":"P",
    "gn:feature_code":"PPL",
    "gn:name":"Dra\u017ein Vrt",
    "gn:population":0,
    "gn:timezone":"Europe/Podgorica",
    "iso:country":"ME",
    "name:srp_x_preferred":[
        "Dra\u017ein Vrt"
    ],
    "wof:name":"Drazin Vrt",
    "wof:placetype":"locality"
},
  "geometry": {"coordinates":[18.73056,42.48444],"type":"Point"}
}