{
  "type": "Feature",
  "properties": {
    "gn:country":"ME",
    "gn:fcode":"PPL",
    "gn:population":68,
    "iso:country":"ME",
    "name:und_x_variant":[
        "Vrelo"
    ],
    "qs:name":"Vrela",
    "qs:photos_9r":0,
    "qs:photos_sr":0,
    "qs:pop_sr":"1",
    "wof:name":"Vrela",
    "wof:placetype":"locality",
    "wof:population":68
},
  "geometry": {"coordinates":[18.9275,42.32667],"type":"Point"}
}