{
  "type": "Feature",
  "properties": {
    "gn:admin1_code":"20.0",
    "gn:asciiname":"Ckla",
    "gn:country_code":"ME",
    "gn:dem":141,
    "gn:feature_class":"P",
    "gn:feature_code":"PPLL",
    "gn:name":"Ckla",
    "gn:population":0,
    "gn:timezone":"Europe/Podgorica",
    "iso:country":"ME",
    "wof:name":"Ckla",
    "wof:placetype":"locality"
},
  "geometry": {"coordinates":[19.36083,42.08361],"type":"Point"}
}