{
  "type": "Feature",
  "properties": {
    "gn:admin1_code":"10.0",
    "gn:asciiname":"Glavati",
    "gn:country_code":"ME",
    "gn:dem":46,
    "gn:feature_class":"P",
    "gn:feature_code":"PPL",
    "gn:name":"Glavati",
    "gn:population":0,
    "gn:timezone":"Europe/Podgorica",
    "iso:country":"ME",
    "wof:name":"Glavati",
    "wof:placetype":"locality"
},
  "geometry": {"coordinates":[18.7525,42.44194],"type":"Point"}
}