{
  "type": "Feature",
  "properties": {
    "gn:admin1_code":"12.0",
    "gn:asciiname":"Dubocke",
    "gn:country_code":"ME",
    "gn:dem":1091,
    "gn:feature_class":"P",
    "gn:feature_code":"PPLL",
    "gn:name":"Dubo\u010dke",
    "gn:population":0,
    "gn:timezone":"Europe/Podgorica",
    "iso:country":"ME",
    "wof:name":"Dubocke",
    "wof:placetype":"locality"
},
  "geometry": {"coordinates":[18.67444,42.89556],"type":"Point"}
}