{
  "type": "Feature",
  "properties": {
    "gn:admin1_code":"4.0",
    "gn:asciiname":"Sokolac",
    "gn:country_code":"ME",
    "gn:dem":1300,
    "gn:feature_class":"P",
    "gn:feature_code":"PPLL",
    "gn:name":"Sokolac",
    "gn:population":0,
    "gn:timezone":"Europe/Podgorica",
    "iso:country":"ME",
    "name:fra_x_preferred":[
        "Sokolac"
    ],
    "name:ron_x_preferred":[
        "Sokolac"
    ],
    "name:slv_x_preferred":[
        "Sokolac"
    ],
    "name:srp_x_preferred":[
        "\u0421\u043e\u043a\u043e\u043b\u0430\u0446"
    ],
    "wof:name":"Sokolac",
    "wof:placetype":"locality"
},
  "geometry": {"coordinates":[19.57361,43.08667],"type":"Point"}
}