{
  "type": "Feature",
  "properties": {
    "gn:country":"ME",
    "gn:fcode":"PPL",
    "gn:population":108,
    "iso:country":"ME",
    "name:srp_x_preferred":[
        "Bigor"
    ],
    "qs:name":"Bigor",
    "qs:photos_9r":0,
    "qs:photos_sr":0,
    "qs:pop_sr":"1",
    "wof:name":"Bigor",
    "wof:placetype":"locality",
    "wof:population":108
},
  "geometry": {"coordinates":[19.13222,42.39944],"type":"Point"}
}