{
  "type": "Feature",
  "properties": {
    "gn:admin1_code":"14.0",
    "gn:asciiname":"Colovici",
    "gn:country_code":"ME",
    "gn:dem":1190,
    "gn:feature_class":"P",
    "gn:feature_code":"PPL",
    "gn:name":"\u010colovi\u0107i",
    "gn:population":0,
    "gn:timezone":"Europe/Podgorica",
    "iso:country":"ME",
    "name:srp_x_preferred":[
        "\u010colovi\u0107i"
    ],
    "wof:name":"Colovici",
    "wof:placetype":"locality"
},
  "geometry": {"coordinates":[19.32639,43.41583],"type":"Point"}
}