{
  "type": "Feature",
  "properties": {
    "gn:admin1_code":"16.0",
    "gn:asciiname":"Korijen",
    "gn:country_code":"ME",
    "gn:dem":826,
    "gn:feature_class":"P",
    "gn:feature_code":"PPL",
    "gn:name":"Korijen",
    "gn:population":0,
    "gn:timezone":"Europe/Podgorica",
    "iso:country":"ME",
    "name:srp_x_preferred":[
        "Korijen"
    ],
    "wof:name":"Korijen",
    "wof:placetype":"locality"
},
  "geometry": {"coordinates":[19.47583,42.60972],"type":"Point"}
}