{
  "type": "Feature",
  "properties": {
    "iso:country":"ME",
    "name:alb_x_preferred":[
        "Komuna e Plav\u00ebs"
    ],
    "name:bel_x_variant":[
        "\u041f\u043b\u0430\u045e"
    ],
    "name:bos_x_preferred":[
        "Plav"
    ],
    "name:bul_x_preferred":[
        "\u041f\u043b\u0430\u0432"
    ],
    "name:cat_x_preferred":[
        "Plav-Gusinje"
    ],
    "name:ces_x_preferred":[
        "Plav"
    ],
    "name:chi_x_preferred":[
        "\u666e\u62c9\u592b"
    ],
    "name:cze_x_preferred":[
        "Plav"
    ],
    "name:deu_x_preferred":[
        "Plav"
    ],
    "name:dut_x_preferred":[
        "Plav"
    ],
    "name:eng_x_preferred":[
        "Plav"
    ],
    "name:est_x_preferred":[
        "Plavi vald"
    ],
    "name:fas_x_preferred":[
        "\u067e\u0644\u0627\u0648"
    ],
    "name:fin_x_preferred":[
        "Plav"
    ],
    "name:fra_x_preferred":[
        "Plav"
    ],
    "name:fre_x_preferred":[
        "Plav"
    ],
    "name:geo_x_preferred":[
        "\u10de\u10da\u10d0\u10d5\u10d8"
    ],
    "name:ger_x_preferred":[
        "Plav"
    ],
    "name:hbs_x_preferred":[
        "Plav"
    ],
    "name:hrv_x_preferred":[
        "Plav"
    ],
    "name:ita_x_preferred":[
        "Plav"
    ],
    "name:jpn_x_preferred":[
        "\u30d7\u30e9\u30f4"
    ],
    "name:kat_x_preferred":[
        "\u10de\u10da\u10d0\u10d5\u10d8"
    ],
    "name:kaz_x_preferred":[
        "\u041f\u043b\u0430\u0432"
    ],
    "name:kor_x_preferred":[
        "\ud50c\ub77c\ube0c"
    ],
    "name:lit_x_preferred":[
        "Plavas"
    ],
    "name:nld_x_preferred":[
        "Plav"
    ],
    "name:nno_x_preferred":[
        "Plav"
    ],
    "name:nob_x_preferred":[
        "Plav"
    ],
    "name:nor_x_preferred":[
        "Plav"
    ],
    "name:per_x_preferred":[
        "\u067e\u0644\u0627\u0648"
    ],
    "name:pol_x_preferred":[
        "Plav"
    ],
    "name:por_x_preferred":[
        "Plav"
    ],
    "name:ron_x_preferred":[
        "Plav"
    ],
    "name:rum_x_preferred":[
        "Plav"
    ],
    "name:rus_x_preferred":[
        "\u041f\u043b\u0430\u0432"
    ],
    "name:slv_x_preferred":[
        "Plav"
    ],
    "name:spa_x_preferred":[
        "Plav"
    ],
    "name:sqi_x_preferred":[
        "Komuna e Plav\u00ebs"
    ],
    "name:srp_x_preferred":[
        "\u041f\u043b\u0430\u0432"
    ],
    "name:swe_x_preferred":[
        "Plav"
    ],
    "name:ukr_x_preferred":[
        "\u041f\u043b\u0430\u0432"
    ],
    "name:unk_x_variant":[
        "Plav\u00eb"
    ],
    "name:urd_x_preferred":[
        "\u067e\u0644\u0627\u0648\u060c \u0645\u0648\u0646\u0679\u06cc\u0646\u06cc\u06af\u0631\u0648"
    ],
    "name:zho_x_preferred":[
        "\u666e\u62c9\u592b"
    ],
    "qs:gn_country":"ME",
    "qs:gn_fcode":"PPL",
    "qs:gn_pop":4,
    "qs:name":"Plav",
    "qs:name_adm0":"Montenegro",
    "qs:name_adm1":"Plav",
    "qs:photos":0,
    "qs:photos_1k":0,
    "qs:photos_9k":1,
    "qs:photos_9r":1,
    "qs:photos_all":13,
    "qs:photos_sr":0,
    "qs:placetype":"Town",
    "qs:pop_sr":"1",
    "qs:woe_adm0":20069817,
    "wd:wordcount":673,
    "wof:name":"Plav",
    "wof:placetype":"locality",
    "wof:population":4
},
  "geometry": {"coordinates":[19.94556,42.59694],"type":"Point"}
}