{
  "type": "Feature",
  "properties": {
    "gn:admin1_code":"12.0",
    "gn:asciiname":"Rzeni Do",
    "gn:country_code":"ME",
    "gn:dem":961,
    "gn:feature_class":"P",
    "gn:feature_code":"PPL",
    "gn:name":"R\u017eeni Do",
    "gn:population":0,
    "gn:timezone":"Europe/Podgorica",
    "iso:country":"ME",
    "name:srp_x_preferred":[
        "R\u017eeni Do"
    ],
    "wof:name":"Rzeni Do",
    "wof:placetype":"locality"
},
  "geometry": {"coordinates":[18.73361,42.70833],"type":"Point"}
}