{
  "type": "Feature",
  "properties": {
    "gn:admin1_code":"2.0",
    "gn:asciiname":"Pecurice",
    "gn:country_code":"ME",
    "gn:dem":178,
    "gn:feature_class":"P",
    "gn:feature_code":"PPL",
    "gn:name":"Pe\u010durice",
    "gn:population":0,
    "gn:timezone":"Europe/Podgorica",
    "iso:country":"ME",
    "name:und_x_variant":[
        "Pe\u010durici",
        "Pe\u010durica",
        "Pe\u010durice"
    ],
    "wof:name":"Pecurice",
    "wof:placetype":"locality"
},
  "geometry": {"coordinates":[19.17306,42.03028],"type":"Point"}
}