{
  "type": "Feature",
  "properties": {
    "gn:admin1_code":"10.0",
    "gn:asciiname":"Pobrde",
    "gn:country_code":"ME",
    "gn:dem":233,
    "gn:feature_class":"P",
    "gn:feature_code":"PPLL",
    "gn:name":"Pobr\u0111e",
    "gn:population":0,
    "gn:timezone":"Europe/Podgorica",
    "iso:country":"ME",
    "name:und_x_variant":[
        "Pobrgje",
        "Pobro",
        "Pobrjge",
        "Pobr\u0111e"
    ],
    "wof:name":"Pobrde",
    "wof:placetype":"locality"
},
  "geometry": {"coordinates":[18.73639,42.35639000000001],"type":"Point"}
}