{
  "type": "Feature",
  "properties": {
    "gn:admin1_code":"12.0",
    "gn:asciiname":"Pometenik",
    "gn:country_code":"ME",
    "gn:dem":969,
    "gn:feature_class":"P",
    "gn:feature_code":"PPL",
    "gn:name":"Pometenik",
    "gn:population":0,
    "gn:timezone":"Europe/Podgorica",
    "iso:country":"ME",
    "name:ceb_x_preferred":[
        "Pometenik"
    ],
    "name:srp_x_preferred":[
        "Pometenik"
    ],
    "wof:name":"Pometenik",
    "wof:placetype":"locality"
},
  "geometry": {"coordinates":[18.7625,42.79806],"type":"Point"}
}