{
  "type": "Feature",
  "properties": {
    "gn:admin1_code":"13.0",
    "gn:asciiname":"Brezojevica",
    "gn:country_code":"ME",
    "gn:dem":945,
    "gn:feature_class":"P",
    "gn:feature_code":"PPLL",
    "gn:name":"Brezojevica",
    "gn:population":0,
    "gn:timezone":"Europe/Podgorica",
    "iso:country":"ME",
    "name:und_x_variant":[
        "Donja Brezovica"
    ],
    "wof:name":"Brezojevica",
    "wof:placetype":"locality"
},
  "geometry": {"coordinates":[19.92667,42.62556],"type":"Point"}
}