{
  "type": "Feature",
  "properties": {
    "gn:admin1_code":"12.0",
    "gn:asciiname":"Podlazina",
    "gn:country_code":"ME",
    "gn:dem":764,
    "gn:feature_class":"P",
    "gn:feature_code":"PPL",
    "gn:name":"Podlazina",
    "gn:population":0,
    "gn:timezone":"Europe/Podgorica",
    "iso:country":"ME",
    "name:srp_x_preferred":[
        "Podlazina"
    ],
    "wof:name":"Podlazina",
    "wof:placetype":"locality"
},
  "geometry": {"coordinates":[18.62694,42.65972],"type":"Point"}
}