{
  "type": "Feature",
  "properties": {
    "gn:admin1_code":"16.0",
    "gn:asciiname":"Vidacica",
    "gn:country_code":"ME",
    "gn:dem":935,
    "gn:feature_class":"P",
    "gn:feature_code":"PPL",
    "gn:name":"Vida\u010dica",
    "gn:population":0,
    "gn:timezone":"Europe/Podgorica",
    "iso:country":"ME",
    "name:srp_x_preferred":[
        "Vida\u010dica"
    ],
    "wof:name":"Vidacica",
    "wof:placetype":"locality"
},
  "geometry": {"coordinates":[19.41694,42.59222000000001],"type":"Point"}
}